Workbook
Name MY_FUNCTION1: LAMBDA(COVARIANCE.P(Reliance!$K$3:$K$496,Reliance!$L$3:$L$496)/VARP(Reliance!$L$3:$L$496))

Sheet Reliance
A1: DATE | B1: OPEN | C1: HIGH | D1: LOW | E1: PREV. CLOSE | F1: CLOSE | G1: VWAP | H1: VOLUME | I1: VALUE | J1: NO. OF TRADES | K1: Daily Return | L1: NIFTY RETURN
A2: 45509 | B2: 2960 | C2: 2967.8 | D2: 2866.5 | E2: 2998.65 | F2: 2894.65 | G2: 2901.81 | H2: 85,23,352 | I2: 24,73,31,28,212.00 | J2: 4,48,630 | M2: =VALUE(SUBSTITUTE(H2,",","")) -> 8523352
A3: 45510 | B3: 2910.3 | C3: 2955 | D3: 2902.65 | E3: 2894.65 | F3: 2912.1 | G3: 2929.53 | H3: 51,18,093 | I3: 14,99,35,89,440.05 | J3: 1,97,549 | K3: 0.0060283627 | L3: -0.0026210113 | M3: =VALUE(SUBSTITUTE(H3,",","")) -> 5118093
A4: 45511 | B4: 2938 | C4: 2945 | D4: 2923 | E4: 2912.1 | F4: 2929.65 | G4: 2930.89 | H4: 40,87,284 | I4: 11,97,93,63,870.55 | J4: 2,76,362 | K4: 0.0060265788 | L4: 0.012710195 | M4: =VALUE(SUBSTITUTE(H4,",","")) -> 4087284
A5: 45512 | B5: 2915.05 | C5: 2930 | D5: 2891.85 | E5: 2929.65 | F5: 2898.25 | G5: 2905.69 | H5: 61,93,596 | I5: 17,99,66,62,105.65 | J5: 2,55,138 | K5: -0.010718004 | L5: -0.0074287478 | M5: =VALUE(SUBSTITUTE(H5,",","")) -> 6193596
A6: 45513 | B6: 2920 | C6: 2953 | D6: 2912 | E6: 2898.25 | F6: 2948.6 | G6: 2939.2 | H6: 31,24,888 | I6: 9,18,46,80,574.05 | J6: 1,50,169 | K6: 0.017372552 | L6: 0.010386864 | M6: =VALUE(SUBSTITUTE(H6,",","")) -> 3124888
A7: 45516 | B7: 2940 | C7: 2946 | D7: 2915.5 | E7: 2948.6 | F7: 2921.25 | G7: 2929.82 | H7: 40,92,292 | I7: 11,98,96,80,025.65 | J7: 1,88,301 | K7: -0.0092755884 | L7: -0.0008412845 | M7: =VALUE(SUBSTITUTE(H7,",","")) -> 4092292
A8: 45517 | B8: 2921.5 | C8: 2940.15 | D8: 2916 | E8: 2921.25 | F8: 2927.25 | G8: 2928.29 | H8: 31,32,532 | I8: 9,17,29,71,802.70 | J8: 1,34,517 | K8: 0.0020539153 | L8: -0.008543147 | M8: =VALUE(SUBSTITUTE(H8,",","")) -> 3132532
A9: 45518 | B9: 2927.1 | C9: 2944 | D9: 2907.4 | E9: 2927.25 | F9: 2923.7 | G9: 2925.78 | H9: 31,33,733 | I9: 9,16,86,16,380.80 | J9: 1,85,733 | K9: -0.0012127423 | L9: 0.000196777 | M9: =VALUE(SUBSTITUTE(H9,",","")) -> 3133733
A10: 45520 | B10: 2937.3 | C10: 2960.8 | D10: 2916.1 | E10: 2923.7 | F10: 2956.4 | G10: 2944.77 | H10: 47,08,451 | I10: 13,86,53,25,209.75 | J10: 1,87,365 | K10: 0.011184458 | L10: 0.016459746 | M10: =VALUE(SUBSTITUTE(H10,",","")) -> 4708451
A11: 45523 | B11: 2965 | C11: 2996.6 | D11: 2961 | E11: 2956.4 | F11: 2976.8 | G11: 2980.25 | H11: 68,98,871 | I11: 20,56,03,27,724.60 | J11: 2,00,328 | K11: 0.0069002841 | L11: 0.0012835584 | M11: =VALUE(SUBSTITUTE(H11,",","")) -> 6898871
A12: 45524 | B12: 2994.45 | C12: 3007.85 | D12: 2980.05 | E12: 2976.8 | F12: 2991.9 | G12: 2996.98 | H12: 42,05,904 | I12: 12,60,50,24,714.40 | J12: 1,75,516 | K12: 0.0050725611 | L12: 0.0051357912 | M12: =VALUE(SUBSTITUTE(H12,",","")) -> 4205904
A13: 45525 | B13: 2986.5 | C13: 3015.75 | D13: 2980 | E13: 2991.9 | F13: 2997.35 | G13: 3001.42 | H13: 38,84,998 | I13: 11,66,05,26,038.60 | J13: 1,41,353 | K13: 0.0018215849 | L13: 0.0028887985 | M13: =VALUE(SUBSTITUTE(H13,",","")) -> 3884998
A14: 45526 | B14: 3006 | C14: 3013 | D14: 2981.3 | E14: 2997.35 | F14: 2996.25 | G14: 2994.88 | H14: 52,22,891 | I14: 15,64,19,35,953.20 | J14: 2,33,216 | K14: -0.00036699084 | L14: 0.0016673261 | M14: =VALUE(SUBSTITUTE(H14,",","")) -> 5222891
... A59: 45590 | B59: 2687 | C59: 2688.7 | D59: 2644 | E59: 2679.6 | F59: 2655.7 | G59: 2659.8 | H59: 92,98,748 | I59: 24,73,28,26,126.10 | J59: 3,88,238 | K59: -0.0089192417 | L59: -0.0089592367 | M59: =VALUE(SUBSTITUTE(H59,",","")) -> 9298748
A60: 45593 | B60: 1337 | C60: 1353 | D60: 1322.1 | E60: 2655.7 | F60: 1334.35 | G60: 1337.7 | H60: 1,08,24,350 | I60: 14,47,97,33,719.25 | J60: 3,68,817 | L60: 0.006548584 | M60: =VALUE(SUBSTITUTE(H60,",","")) -> 10824350
A61: 45594 | B61: 1328.1 | C61: 1343.2 | D61: 1320.3 | E61: 1334.35 | F61: 1340 | G61: 1331.46 | H61: 1,20,08,361 | I61: 15,98,86,83,034.00 | J61: 4,36,915 | K61: 0.0042342714 | L61: 0.005246691 | M61: =VALUE(SUBSTITUTE(H61,",","")) -> 12008361
A62: 45595 | B62: 1335 | C62: 1350 | D62: 1325.35 | E62: 1340 | F62: 1343.9 | G62: 1341.16 | H62: 1,19,84,423 | I62: 16,07,30,73,274.15 | J62: 2,95,954 | K62: 0.0029104478 | L62: -0.0051498252 | M62: =VALUE(SUBSTITUTE(H62,",","")) -> 11984423
A63: 45596 | B63: 1340 | C63: 1343 | D63: 1326.15 | E63: 1343.9 | F63: 1332.05 | G63: 1334.14 | H63: 93,31,650 | I63: 12,44,97,44,606.90 | J63: 4,14,741 | K63: -0.0088176204 | L63: -0.0055667736 | M63: =VALUE(SUBSTITUTE(H63,",","")) -> 9331650
A64: 45597 | B64: 1333.05 | C64: 1341.95 | D64: 1333 | E64: 1332.05 | F64: 1338.65 | G64: 1338.89 | H64: 21,27,335 | I64: 2,84,82,64,119.80 | J64: 1,27,374 | K64: 0.004954769 | L64: 0.0040900049 | M64: =VALUE(SUBSTITUTE(H64,",","")) -> 2127335
A65: 45600 | B65: 1337.85 | C65: 1340 | D65: 1285.1 | E65: 1338.65 | F65: 1302.15 | G65: 1301.44 | H65: 1,97,96,890 | I65: 25,76,44,50,096.55 | J65: 5,54,958 | K65: -0.027266276 | L65: -0.012713773 | M65: =VALUE(SUBSTITUTE(H65,",","")) -> 19796890
A66: 45601 | B66: 1293 | C66: 1309.55 | D66: 1286.15 | E66: 1302.15 | F66: 1305.3 | G66: 1297.87 | H66: 1,62,67,479 | I66: 21,11,31,19,455.50 | J66: 3,71,758 | K66: 0.0024190761 | L66: 0.0090830098 | M66: =VALUE(SUBSTITUTE(H66,",","")) -> 16267479
A67: 45602 | B67: 1310 | C67: 1328.3 | D67: 1300.2 | E67: 1305.3 | F67: 1325.35 | G67: 1315.57 | H67: 2,16,25,209 | I67: 28,44,95,04,045.35 | J67: 3,49,627 | K67: 0.015360454 | L67: 0.011181871 | M67: =VALUE(SUBSTITUTE(H67,",","")) -> 21625209
A68: 45603 | B68: 1324 | C68: 1324 | D68: 1302.6 | E68: 1325.35 | F68: 1305.65 | G68: 1308.97 | H68: 96,11,974 | I68: 12,58,18,00,339.00 | J68: 2,61,277 | K68: -0.014863998 | L68: -0.011627978 | M68: =VALUE(SUBSTITUTE(H68,",","")) -> 9611974
A69: 45604 | B69: 1297.65 | C69: 1301.65 | D69: 1275 | E69: 1305.65 | F69: 1283.75 | G69: 1284.01 | H69: 1,98,14,406 | I69: 25,44,19,00,935.60 | J69: 4,77,001 | K69: -0.016773255 | L69: -0.0021136931 | M69: =VALUE(SUBSTITUTE(H69,",","")) -> 19814406
A70: 45607 | B70: 1278.95 | C70: 1286 | D70: 1267 | E70: 1283.75 | F70: 1272.7 | G70: 1275.44 | H70: 90,56,552 | I70: 11,55,10,68,872.50 | J70: 2,86,019 | K70: -0.0086075949 | L70: -0.00028573558 | M70: =VALUE(SUBSTITUTE(H70,",","")) -> 9056552
A71: 45608 | B71: 1275.55 | C71: 1289.3 | D71: 1267.5 | E71: 1272.7 | F71: 1274.25 | G71: 1277.82 | H71: 1,06,71,091 | I71: 13,63,56,94,812.30 | J71: 2,99,780 | K71: 0.0012178832 | L71: -0.010680866 | M71: =VALUE(SUBSTITUTE(H71,",","")) -> 10671091
A72: 45609 | B72: 1270.25 | C72: 1275.45 | D72: 1249.5 | E72: 1274.25 | F72: 1252.05 | G72: 1258.62 | H72: 1,46,33,633 | I72: 18,41,82,08,535.90 | J72: 4,69,215 | K72: -0.017422013 | L72: -0.013582627 | M72: =VALUE(SUBSTITUTE(H72,",","")) -> 14633633
... A303: 45950 | B303: 1440 | C303: 1473.8 | D303: 1433.3 | E303: 1416.8 | F303: 1466.8 | G303: 1461.76 | H303: 2,47,21,978 | I303: 36,13,76,73,257.50 | J303: 5,12,798 | K303: 0.035290796 | L303: 0.0051847833 | M303: =VALUE(SUBSTITUTE(H303,",","")) -> 24721978
A304: 45951 | B304: 1468 | C304: 1474 | D304: 1460 | E304: 1466.8 | F304: 1465.2 | G304: 1467.87 | H304: 20,66,169 | I304: 3,03,28,61,642.80 | J304: 86819 | K304: -0.0010908099 | L304: 0.00098478707 | M304: =VALUE(SUBSTITUTE(H304,",","")) -> 2066169
A305: 45953 | B305: 1475 | C305: 1482.9 | D305: 1444.6 | E305: 1465.2 | F305: 1448.4 | G305: 1464.71 | H305: 1,87,07,090 | I305: 27,40,03,74,842.50 | J305: 3,76,220 | K305: -0.011466011 | L305: 0.00088137742 | M305: =VALUE(SUBSTITUTE(H305,",","")) -> 18707090
A306: 45954 | B306: 1450 | C306: 1459.8 | D306: 1441 | E306: 1448.4 | F306: 1451.6 | G306: 1450.25 | H306: 97,00,837 | I306: 14,06,86,22,023.20 | J306: 2,21,258 | K306: 0.0022093344 | L306: -0.0037174506 | M306: =VALUE(SUBSTITUTE(H306,",","")) -> 9700837
A307: 45957 | B307: 1463 | C307: 1485 | D307: 1458 | E307: 1451.6 | F307: 1484.1 | G307: 1480.24 | H307: 1,41,13,867 | I307: 20,89,18,82,342.50 | J307: 2,74,839 | K307: 0.022389088 | L307: 0.0066252765 | M307: =VALUE(SUBSTITUTE(H307,",","")) -> 14113867
A308: 45958 | B308: 1484.1 | C308: 1492 | D308: 1477.6 | E308: 1484.1 | F308: 1486.9 | G308: 1484.96 | H308: 1,76,31,577 | I308: 26,18,22,48,923.90 | J308: 3,14,894 | K308: 0.0018866653 | L308: -0.001149578 | M308: =VALUE(SUBSTITUTE(H308,",","")) -> 17631577
A309: 45959 | B309: 1490 | C309: 1508.3 | D309: 1488.1 | E309: 1486.9 | F309: 1504.2 | G309: 1502.67 | H309: 1,18,84,745 | I309: 17,85,88,00,582.60 | J309: 2,19,504 | K309: 0.011634945 | L309: 0.0045380588 | M309: =VALUE(SUBSTITUTE(H309,",","")) -> 11884745
A310: 45960 | B310: 1500 | C310: 1503.1 | D310: 1484 | E310: 1504.2 | F310: 1488.5 | G310: 1492.27 | H310: 93,18,663 | I310: 13,90,59,20,959.90 | J310: 2,76,397 | K310: -0.010437442 | L310: -0.0067571458 | M310: =VALUE(SUBSTITUTE(H310,",","")) -> 9318663
A311: 45961 | B311: 1490.4 | C311: 1497.5 | D311: 1482.3 | E311: 1488.5 | F311: 1486.4 | G311: 1487.8 | H311: 87,58,053 | I311: 13,03,02,57,785.30 | J311: 2,06,898 | K311: -0.0014108163 | L311: -0.0060186607 | M311: =VALUE(SUBSTITUTE(H311,",","")) -> 8758053
A312: 45964 | B312: 1486 | C312: 1495 | D312: 1479.3 | E312: 1486.4 | F312: 1484.7 | G312: 1488.29 | H312: 84,52,085 | I312: 12,57,91,61,982.90 | J312: 2,45,664 | K312: -0.0011437029 | L312: 0.0016036793 | M312: =VALUE(SUBSTITUTE(H312,",","")) -> 8452085
A313: 45965 | B313: 1483.9 | C313: 1492.8 | D313: 1470.1 | E313: 1484.7 | F313: 1473.1 | G313: 1480.96 | H313: 1,00,07,806 | I313: 14,82,11,44,472.70 | J313: 2,18,103 | K313: -0.0078130262 | L313: -0.006431617 | M313: =VALUE(SUBSTITUTE(H313,",","")) -> 10007806
A314: 45967 | B314: 1484 | C314: 1501.6 | D314: 1476.2 | E314: 1473.1 | F314: 1496.1 | G314: 1494.08 | H314: 1,67,72,678 | I314: 25,05,96,56,533.30 | J314: 2,69,902 | K314: 0.015613332 | L314: -0.0034358623 | M314: =VALUE(SUBSTITUTE(H314,",","")) -> 16772678
A315: 45968 | B315: 1494.6 | C315: 1498.4 | D315: 1475.9 | E315: 1496.1 | F315: 1478 | G315: 1486.71 | H315: 78,21,765 | I315: 11,62,87,33,264.10 | J315: 1,39,608 | K315: -0.012098122 | L315: -0.00068209348 | M315: =VALUE(SUBSTITUTE(H315,",","")) -> 7821765
A316: 45971 | B316: 1477.9 | C316: 1501 | D316: 1475.5 | E316: 1478 | F316: 1489.3 | G316: 1492.69 | H316: 70,68,438 | I316: 10,55,09,78,254.30 | J316: 1,54,602 | K316: 0.0076454668 | L316: 0.003218619 | M316: =VALUE(SUBSTITUTE(H316,",","")) -> 7068438
... A348: 46015 | B348: 1572.7 | C348: 1575.7 | D348: 1553.6 | E348: 1570.7 | F348: 1558.2 | G348: 1559.55 | H348: 88,15,745 | I348: 13,74,86,00,530.90 | J348: 2,43,970 | K348: -0.0079582352 | L348: -0.001338954 | M348: =VALUE(SUBSTITUTE(H348,",","")) -> 8815745
A349: 46017 | B349: 1554.7 | C349: 1561 | D349: 1554.3 | E349: 1558.2 | F349: 1559.2 | G349: 1558.05 | H349: 23,11,495 | I349: 3,60,14,35,338.70 | J349: 81976 | K349: 0.00064176614 | L349: -0.0038175969 | M349: =VALUE(SUBSTITUTE(H349,",","")) -> 2311495
A350: 46020 | B350: 1554.9 | C350: 1558.1 | D350: 1543.6 | E350: 1559.2 | F350: 1545.6 | G350: 1547.8 | H350: 59,72,105 | I350: 9,24,36,16,142.30 | J350: 1,58,162 | K350: -0.0087224218 | L350: -0.0038475864 | M350: =VALUE(SUBSTITUTE(H350,",","")) -> 5972105
A351: 46021 | B351: 1547 | C351: 1553.6 | D351: 1537.8 | E351: 1545.6 | F351: 1539.8 | G351: 1543.21 | H351: 88,15,884 | I351: 13,60,47,45,435.00 | J351: 1,99,428 | K351: -0.003752588 | L351: -0.00012527899 | M351: =VALUE(SUBSTITUTE(H351,",","")) -> 8815884
A352: 46022 | B352: 1541 | C352: 1577 | D352: 1541 | E352: 1539.8 | F352: 1570.4 | G352: 1566.86 | H352: 57,71,830 | I352: 9,04,36,50,348.50 | J352: 1,41,792 | K352: 0.019872711 | L352: 0.0073538341 | M352: =VALUE(SUBSTITUTE(H352,",","")) -> 5771830
A353: 46023 | B353: 1573.7 | C353: 1592.5 | D353: 1571.1 | E353: 1570.4 | F353: 1575.6 | G353: 1578.67 | H353: 64,08,128 | I353: 10,11,63,46,867.10 | J353: 1,34,062 | K353: 0.0033112583 | L353: 0.00064868961 | M353: =VALUE(SUBSTITUTE(H353,",","")) -> 6408128
A354: 46024 | B354: 1580 | C354: 1594.6 | D354: 1578.2 | E354: 1575.6 | F354: 1592.3 | G354: 1589.16 | H354: 66,02,230 | I354: 10,49,19,99,169.40 | J354: 1,56,023 | K354: 0.010599137 | L354: 0.0069607654 | M354: =VALUE(SUBSTITUTE(H354,",","")) -> 6602230
A355: 46027 | B355: 1593 | C355: 1611.8 | D355: 1575.3 | E355: 1592.3 | F355: 1578.1 | G355: 1589.36 | H355: 87,04,973 | I355: 13,83,53,33,400.10 | J355: 2,27,204 | K355: -0.0089179175 | L355: -0.0029720588 | M355: =VALUE(SUBSTITUTE(H355,",","")) -> 8704973
A356: 46028 | B356: 1569 | C356: 1569 | D356: 1496.3 | E356: 1578.1 | F356: 1507.6 | G356: 1516.17 | H356: 2,74,17,125 | I356: 41,56,90,80,602.20 | J356: 5,83,917 | K356: -0.044673975 | L356: -0.0027275879 | M356: =VALUE(SUBSTITUTE(H356,",","")) -> 27417125
A357: 46029 | B357: 1510 | C357: 1520 | D357: 1498 | E357: 1507.6 | F357: 1504.2 | G357: 1506.81 | H357: 1,11,99,340 | I357: 16,87,52,53,099.50 | J357: 3,02,077 | K357: -0.0022552401 | L357: -0.0014496518 | M357: =VALUE(SUBSTITUTE(H357,",","")) -> 11199340
A358: 46030 | B358: 1500 | C358: 1503.9 | D358: 1468.8 | E358: 1504.2 | F358: 1470.6 | G358: 1477.72 | H358: 1,65,18,684 | I358: 24,41,00,37,550.10 | J358: 4,43,727 | K358: -0.022337455 | L358: -0.010095349 | M358: =VALUE(SUBSTITUTE(H358,",","")) -> 16518684
A359: 46031 | B359: 1465 | C359: 1479.9 | D359: 1465 | E359: 1470.6 | F359: 1475.3 | G359: 1472.13 | H359: 83,35,311 | I359: 12,27,06,72,520.90 | J359: 2,37,412 | K359: 0.0031959744 | L359: -0.0074796585 | M359: =VALUE(SUBSTITUTE(H359,",","")) -> 8335311
A360: 46034 | B360: 1475.3 | C360: 1485.3 | D360: 1451 | E360: 1475.3 | F360: 1483.2 | G360: 1469.79 | H360: 88,83,745 | I360: 13,05,72,59,395.40 | J360: 2,36,827 | K360: 0.0053548431 | L360: 0.0041641845 | M360: =VALUE(SUBSTITUTE(H360,",","")) -> 8883745
A361: 46035 | B361: 1485 | C361: 1485.8 | D361: 1444.7 | E361: 1483.2 | F361: 1452.8 | G361: 1457.67 | H361: 1,34,99,760 | I361: 19,67,81,31,155.40 | J361: 2,89,198 | K361: -0.020496224 | L361: -0.0022469732 | M361: =VALUE(SUBSTITUTE(H361,",","")) -> 13499760
... A496: 46237 | B496: 1315.2 | C496: 1319 | D496: 1306 | E496: 1307.8 | F496: 1319 | G496: 1311.09 | H496: 75,08,023 | I496: 9,84,36,85,449.40 | J496: 1,58,782 | K496: 0.0085640006 | L496: 0.016023065 | M496: =VALUE(SUBSTITUTE(H496,",","")) -> 7508023

Sheet TCS
A1: DATE | B1: OPEN | C1: HIGH | D1: LOW | E1: LTP | F1: CLOSE | G1: VWAP | H1: VOLUME | I1: VALUE | J1: NO. OF TRADES | K1: DAILY RETURN | L1: NIFTY RETURN
A2: 45509 | B2: 4239 | C2: 4239 | D2: 4110.5 | E2: 4160 | F2: 4155.05 | G2: 4165.25 | H2: 27,87,771 | I2: 11,61,17,60,562.20 | J2: 1,69,844 | M2: =VALUE(SUBSTITUTE(H2,",","")) -> 2787771
A3: 45510 | B3: 4170.95 | C3: 4258.25 | D3: 4160.8 | E3: 4175.1 | F3: 4171.2 | G3: 4193.98 | H3: 22,03,067 | I3: 9,23,96,08,320.05 | J3: 1,34,281 | K3: =(F3-F2)/F2 -> 0.0038868365 | L3: -0.0026210113 | M3: =VALUE(SUBSTITUTE(H3,",","")) -> 2203067
A4: 45511 | B4: 4228 | C4: 4244.95 | D4: 4180.3 | E4: 4201 | F4: 4200.45 | G4: 4201.58 | H4: 12,37,666 | I4: 5,20,01,50,778.85 | J4: 1,02,627 | K4: =(F4-F3)/F3 -> 0.0070123705 | L4: 0.012710195 | M4: =VALUE(SUBSTITUTE(H4,",","")) -> 1237666
A5: 45512 | B5: 4181 | C5: 4232 | D5: 4160 | E5: 4174 | F5: 4172.55 | G5: 4190.47 | H5: 24,41,283 | I5: 10,23,01,19,942.80 | J5: 1,20,490 | K5: =(F5-F4)/F4 -> -0.0066421455 | L5: -0.0074287478 | M5: =VALUE(SUBSTITUTE(H5,",","")) -> 2441283
A6: 45513 | B6: 4217 | C6: 4253.65 | D6: 4205.55 | E6: 4220 | F6: 4228.75 | G6: 4233.82 | H6: 13,02,536 | I6: 5,51,47,05,150.35 | J6: 79876 | K6: =(F6-F5)/F5 -> 0.013468982 | L6: 0.010386864 | M6: =VALUE(SUBSTITUTE(H6,",","")) -> 1302536
A7: 45516 | B7: 4230 | C7: 4239 | D7: 4186.35 | E7: 4193.1 | F7: 4195.65 | G7: 4210.62 | H7: 9,36,912 | I7: 3,94,49,78,151.60 | J7: 86028 | K7: =(F7-F6)/F6 -> -0.0078273722 | L7: -0.0008412845 | M7: =VALUE(SUBSTITUTE(H7,",","")) -> 936912
A8: 45517 | B8: 4213 | C8: 4234 | D8: 4183 | E8: 4197 | F8: 4196.95 | G8: 4209.09 | H8: 14,95,593 | I8: 6,29,50,91,175.55 | J8: 99105 | K8: =(F8-F7)/F7 -> 0.00030984472 | L8: -0.008543147 | M8: =VALUE(SUBSTITUTE(H8,",","")) -> 1495593
A9: 45518 | B9: 4209 | C9: 4306.2 | D9: 4188.15 | E9: 4293 | F9: 4295.25 | G9: 4265.75 | H9: 32,26,545 | I9: 13,76,36,19,690.80 | J9: 1,82,461 | K9: =(F9-F8)/F8 -> 0.023421771 | L9: 0.000196777 | M9: =VALUE(SUBSTITUTE(H9,",","")) -> 3226545
A10: 45520 | B10: 4350 | C10: 4427 | D10: 4325.1 | E10: 4414.2 | F10: 4416.05 | G10: 4395.48 | H10: 34,57,058 | I10: 15,19,54,30,172.75 | J10: 2,33,969 | K10: =(F10-F9)/F9 -> 0.028124091 | L10: 0.016459746 | M10: =VALUE(SUBSTITUTE(H10,",","")) -> 3457058
A11: 45523 | B11: 4421 | C11: 4494.25 | D11: 4390.35 | E11: 4490 | F11: 4490 | G11: 4459.62 | H11: 20,55,210 | I11: 9,16,54,57,457.55 | J11: 1,18,736 | K11: =(F11-F10)/F10 -> 0.016745734 | L11: 0.0012835584 | M11: =VALUE(SUBSTITUTE(H11,",","")) -> 2055210
A12: 45524 | B12: 4505 | C12: 4565 | D12: 4500 | E12: 4505 | F12: 4523.3 | G12: 4529.5 | H12: 22,12,298 | I12: 10,02,06,13,301.75 | J12: 1,28,019 | K12: =(F12-F11)/F11 -> 0.0074164811 | L12: 0.0051357912 | M12: =VALUE(SUBSTITUTE(H12,",","")) -> 2212298
A13: 45525 | B13: 4518 | C13: 4560 | D13: 4492.55 | E13: 4550 | F13: 4551.5 | G13: 4529.61 | H13: 18,96,990 | I13: 8,59,26,17,038.50 | J13: 1,15,023 | K13: =(F13-F12)/F12 -> 0.0062343864 | L13: 0.0028887985 | M13: =VALUE(SUBSTITUTE(H13,",","")) -> 1896990
A14: 45526 | B14: 4560 | C14: 4560.95 | D14: 4497.2 | E14: 4502 | F14: 4502 | G14: 4515.52 | H14: 18,29,872 | I14: 8,26,28,19,007.85 | J14: 1,14,303 | K14: =(F14-F13)/F13 -> -0.010875536 | L14: 0.0016673261 | M14: =VALUE(SUBSTITUTE(H14,",","")) -> 1829872
A15: 45527 | B15: 4500 | C15: 4506 | D15: 4455 | E15: 4473.05 | F15: 4463.9 | G15: 4469.04 | H15: 18,09,253 | I15: 8,08,56,19,687.40 | J15: 1,01,893 | K15: =(F15-F14)/F14 -> -0.0084629054 | L15: 0.00046954033 | M15: =VALUE(SUBSTITUTE(H15,",","")) -> 1809253
A16: 45530 | B16: 4489 | C16: 4552.15 | D16: 4485 | E16: 4506.6 | F16: 4502.45 | G16: 4517.26 | H16: 18,44,164 | I16: 8,33,05,71,610.15 | J16: 1,18,509 | K16: =(F16-F15)/F15 -> 0.0086359461 | L16: 0.0075514187 | M16: =VALUE(SUBSTITUTE(H16,",","")) -> 1844164
A17: 45531 | B17: 4505 | C17: 4510 | D17: 4486.8 | E17: 4491 | F17: 4497.15 | G17: 4496.77 | H17: 9,30,697 | I17: 4,18,51,34,647.00 | J17: 65265 | K17: =(F17-F16)/F16 -> -0.0011771369 | L17: 0.00028587879 | M17: =VALUE(SUBSTITUTE(H17,",","")) -> 930697
A18: 45532 | B18: 4498.75 | C18: 4562.5 | D18: 4457.3 | E18: 4513 | F18: 4506.05 | G18: 4515.24 | H18: 18,48,058 | I18: 8,34,44,30,539.80 | J18: 1,27,744 | K18: =(F18-F17)/F17 -> 0.0019790312 | L18: 0.0013830181 | M18: =VALUE(SUBSTITUTE(H18,",","")) -> 1848058
A19: 45533 | B19: 4460 | C19: 4556 | D19: 4460 | E19: 4507 | F19: 4511.8 | G19: 4515.71 | H19: 21,33,641 | I19: 9,63,48,99,513.20 | J19: 1,38,513 | K19: =(F19-F18)/F18 -> 0.0012760622 | L19: 0.0039756749 | M19: =VALUE(SUBSTITUTE(H19,",","")) -> 2133641
A20: 45534 | B20: 4500 | C20: 4592.25 | D20: 4487.8 | E20: 4562.7 | F20: 4553.75 | G20: 4545.75 | H20: 36,37,222 | I20: 16,53,39,15,087.45 | J20: 1,55,239 | K20: =(F20-F19)/F19 -> 0.0092978412 | L20: 0.0033377134 | M20: =VALUE(SUBSTITUTE(H20,",","")) -> 3637222
A21: 45537 | B21: 4576 | C21: 4588 | D21: 4512 | E21: 4526.4 | F21: 4521.05 | G21: 4545.25 | H21: 12,16,500 | I21: 5,52,92,99,899.10 | J21: 1,09,365 | K21: =(F21-F20)/F20 -> -0.0071808949 | L21: 0.0016959966 | M21: =VALUE(SUBSTITUTE(H21,",","")) -> 1216500
A22: 45538 | B22: 4521.05 | C22: 4555.9 | D22: 4495.9 | E22: 4512.65 | F22: 4512.35 | G22: 4523.6 | H22: 17,17,263 | I22: 7,76,82,15,760.70 | J22: 1,17,744 | K22: =(F22-F21)/F21 -> -0.0019243317 | L22: 4.5492846e-05 | M22: =VALUE(SUBSTITUTE(H22,",","")) -> 1717263
A23: 45539 | B23: 4476.95 | C23: 4487 | D23: 4436.7 | E23: 4484 | F23: 4479.25 | G23: 4468.96 | H23: 12,65,505 | I23: 5,65,54,96,454.35 | J23: 1,23,447 | K23: =(F23-F22)/F22 -> -0.0073354239 | L23: -0.0032100665 | M23: =VALUE(SUBSTITUTE(H23,",","")) -> 1265505
A24: 45540 | B24: 4481 | C24: 4499 | D24: 4454.15 | E24: 4490 | F24: 4475.95 | G24: 4469.15 | H24: 16,88,793 | I24: 7,54,74,77,632.90 | J24: 1,05,236 | K24: =(F24-F23)/F23 -> -0.00073673048 | L24: -0.0021270939 | M24: =VALUE(SUBSTITUTE(H24,",","")) -> 1688793
A25: 45541 | B25: 4473.95 | C25: 4518.95 | D25: 4440 | E25: 4460.5 | F25: 4456.75 | G25: 4466.8 | H25: 16,49,179 | I25: 7,36,65,46,120.25 | J25: 1,48,566 | K25: =(F25-F24)/F24 -> -0.0042895922 | L25: -0.011650381 | M25: =VALUE(SUBSTITUTE(H25,",","")) -> 1649179
A26: 45544 | B26: 4455 | C26: 4490.25 | D26: 4430.5 | E26: 4458 | F26: 4449.55 | G26: 4459.58 | H26: 11,84,938 | I26: 5,28,43,28,321.15 | J26: 92569 | K26: =(F26-F25)/F25 -> -0.001615527 | L26: 0.0033900487 | M26: =VALUE(SUBSTITUTE(H26,",","")) -> 1184938
A27: 45545 | B27: 4442.45 | C27: 4539.95 | D27: 4440.45 | E27: 4510 | F27: 4507.85 | G27: 4499.44 | H27: 13,85,591 | I27: 6,23,43,77,452.20 | J27: 1,25,535 | K27: =(F27-F26)/F26 -> 0.013102449 | L27: 0.0041986814 | M27: =VALUE(SUBSTITUTE(H27,",","")) -> 1385591
A28: 45546 | B28: 4521.45 | C28: 4549.35 | D28: 4471.25 | E28: 4495.5 | F28: 4479.35 | G28: 4504.96 | H28: 13,25,919 | I28: 5,97,32,12,660.05 | J28: 1,27,870 | K28: =(F28-F27)/F27 -> -0.0063223044 | L28: -0.0048979478 | M28: =VALUE(SUBSTITUTE(H28,",","")) -> 1325919
A29: 45547 | B29: 4510.25 | C29: 4532.6 | D29: 4431.3 | E29: 4495.3 | F29: 4517.7 | G29: 4485.01 | H29: 27,42,216 | I29: 12,29,88,52,603.60 | J29: 1,79,765 | K29: =(F29-F28)/F28 -> 0.00856151 | L29: 0.018879585 | M29: =VALUE(SUBSTITUTE(H29,",","")) -> 2742216
A30: 45548 | B30: 4530 | C30: 4547 | D30: 4505 | E30: 4521.75 | F30: 4522.6 | G30: 4526.87 | H30: 14,58,786 | I30: 6,60,37,40,972.90 | J30: 78892 | K30: =(F30-F29)/F29 -> 0.0010846227 | L30: -0.0012761482 | M30: =VALUE(SUBSTITUTE(H30,",","")) -> 1458786
A31: 45551 | B31: 4527 | C31: 4546.05 | D31: 4494.45 | E31: 4509 | F31: 4513.25 | G31: 4516.51 | H31: 11,55,120 | I31: 5,21,71,13,716.25 | J31: 61456 | K31: =(F31-F30)/F30 -> -0.0020673949 | L31: 0.0010746751 | M31: =VALUE(SUBSTITUTE(H31,",","")) -> 1155120
A32: 45552 | B32: 4513.25 | C32: 4535.8 | D32: 4466 | E32: 4511 | F32: 4505.65 | G32: 4505.75 | H32: 16,99,364 | I32: 7,65,69,02,882.20 | J32: 88562 | K32: =(F32-F31)/F31 -> -0.0016839306 | L32: 0.0013709558 | M32: =VALUE(SUBSTITUTE(H32,",","")) -> 1699364
A33: 45553 | B33: 4497.05 | C33: 4497.05 | D33: 4321 | E33: 4347.9 | F33: 4346.15 | G33: 4370.07 | H33: 29,61,779 | I33: 12,94,31,88,817.60 | J33: 2,44,673 | K33: =(F33-F32)/F32 -> -0.035399998 | L33: -0.0016129952 | M33: =VALUE(SUBSTITUTE(H33,",","")) -> 2961779
A34: 45554 | B34: 4390.05 | C34: 4422.2 | D34: 4281.8 | E34: 4307 | F34: 4296.15 | G34: 4321.08 | H34: 29,27,551 | I34: 12,65,01,87,150.25 | J34: 2,32,656 | K34: =(F34-F33)/F33 -> -0.011504435 | L34: 0.0015072377 | M34: =VALUE(SUBSTITUTE(H34,",","")) -> 2927551
A35: 45555 | B35: 4316.9 | C35: 4330.7 | D35: 4227.5 | E35: 4295 | F35: 4284.9 | G35: 4278.76 | H35: 54,47,908 | I35: 23,31,03,16,503.10 | J35: 2,91,115 | K35: =(F35-F34)/F34 -> -0.0026186237 | L35: 0.014760503 | M35: =VALUE(SUBSTITUTE(H35,",","")) -> 5447908
A36: 45558 | B36: 4300 | C36: 4309.4 | D36: 4253 | E36: 4266.05 | F36: 4268.5 | G36: 4270.4 | H36: 17,02,319 | I36: 7,26,95,88,108.95 | J36: 1,69,788 | K36: =(F36-F35)/F35 -> -0.0038273939 | L36: 0.0057423243 | M36: =VALUE(SUBSTITUTE(H36,",","")) -> 1702319
A37: 45559 | B37: 4251.65 | C37: 4291 | D37: 4240 | E37: 4282 | F37: 4271.3 | G37: 4265.03 | H37: 30,12,026 | I37: 12,84,63,72,402.70 | J37: 1,40,428 | K37: =(F37-F36)/F36 -> 0.00065596814 | L37: 5.2045083e-05 | M37: =VALUE(SUBSTITUTE(H37,",","")) -> 3012026
A38: 45560 | B38: 4252.35 | C38: 4289.6 | D38: 4240 | E38: 4275.35 | F38: 4274.75 | G38: 4263.61 | H38: 27,13,073 | I38: 11,56,74,83,701.95 | J38: 1,53,942 | K38: =(F38-F37)/F37 -> 0.00080771662 | L38: 0.0024575566 | M38: =VALUE(SUBSTITUTE(H38,",","")) -> 2713073
A39: 45561 | B39: 4260 | C39: 4316.8 | D39: 4260 | E39: 4295 | F39: 4292.5 | G39: 4288.28 | H39: 39,64,251 | I39: 16,99,98,20,745.85 | J39: 1,85,888 | K39: =(F39-F38)/F38 -> 0.0041522896 | L39: 0.0081486993 | M39: =VALUE(SUBSTITUTE(H39,",","")) -> 3964251
A40: 45562 | B40: 4335 | C40: 4378 | D40: 4300.05 | E40: 4305 | F40: 4308.7 | G40: 4327.38 | H40: 30,12,477 | I40: 13,03,61,44,375.45 | J40: 2,31,071 | K40: =(F40-F39)/F39 -> 0.0037740245 | L40: -0.0014151636 | M40: =VALUE(SUBSTITUTE(H40,",","")) -> 3012477
A41: 45565 | B41: 4286.9 | C41: 4298.75 | D41: 4260.05 | E41: 4271 | F41: 4268.5 | G41: 4272.29 | H41: 25,03,416 | I41: 10,69,53,20,177.30 | J41: 2,12,084 | K41: =(F41-F40)/F40 -> -0.0093299603 | L41: -0.014060915 | M41: =VALUE(SUBSTITUTE(H41,",","")) -> 2503416
A42: 45566 | B42: 4255.55 | C42: 4295.75 | D42: 4242.95 | E42: 4283.25 | F42: 4287.9 | G42: 4271.73 | H42: 18,23,365 | I42: 7,78,89,15,830.70 | J42: 1,21,772 | K42: =(F42-F41)/F41 -> 0.0045449221 | L42: -0.00054047038 | M42: =VALUE(SUBSTITUTE(H42,",","")) -> 1823365
A43: 45568 | B43: 4262.6 | C43: 4279 | D43: 4210 | E43: 4232.5 | F43: 4232.75 | G43: 4233.39 | H43: 33,50,119 | I43: 14,18,23,64,569.60 | J43: 1,68,212 | K43: =(F43-F42)/F42 -> -0.012861774 | L43: -0.021196345 | M43: =VALUE(SUBSTITUTE(H43,",","")) -> 3350119
A44: 45569 | B44: 4225 | C44: 4298 | D44: 4224.05 | E44: 4251.9 | F44: 4252.25 | G44: 4256.15 | H44: 29,65,463 | I44: 12,62,14,65,329.55 | J44: 1,94,588 | K44: =(F44-F43)/F43 -> 0.004606934 | L44: -0.0093266957 | M44: =VALUE(SUBSTITUTE(H44,",","")) -> 2965463
... A59: 45590 | B59: 4057.05 | C59: 4092 | D59: 4032.7 | E59: 4060 | F59: 4057.55 | G59: 4063.37 | H59: 17,59,676 | I59: 7,15,02,08,882.35 | J59: 1,32,353 | K59: =(F59-F58)/F58 -> 0.0023839522 | L59: -0.0089592367 | M59: =VALUE(SUBSTITUTE(H59,",","")) -> 1759676
A60: 45593 | B60: 4068.95 | C60: 4134 | D60: 4051 | E60: 4090.05 | F60: 4090.85 | G60: 4092.04 | H60: 15,32,534 | I60: 6,27,11,97,563.70 | J60: 95406 | K60: =(F60-F59)/F59 -> 0.0082069229 | L60: 0.006548584 | M60: =VALUE(SUBSTITUTE(H60,",","")) -> 1532534
A61: 45594 | B61: 4095.85 | C61: 4103.5 | D61: 4060.1 | E61: 4080 | F61: 4075.25 | G61: 4075.78 | H61: 14,45,885 | I61: 5,89,31,06,996.85 | J61: 1,01,205 | K61: =(F61-F60)/F60 -> -0.0038133884 | L61: 0.005246691 | M61: =VALUE(SUBSTITUTE(H61,",","")) -> 1445885
A62: 45595 | B62: 4075 | C62: 4107 | D62: 4060.05 | E62: 4071.2 | F62: 4084.65 | G62: 4093.47 | H62: 19,35,002 | I62: 7,92,08,76,293.30 | J62: 1,09,837 | K62: =(F62-F61)/F61 -> 0.002306607 | L62: -0.0051498252 | M62: =VALUE(SUBSTITUTE(H62,",","")) -> 1935002
A63: 45596 | B63: 4070 | C63: 4078.3 | D63: 3960 | E63: 3975 | F63: 3968.45 | G63: 3980.19 | H63: 37,40,372 | I63: 14,88,73,81,076.25 | J63: 2,48,757 | K63: =(F63-F62)/F62 -> -0.02844797 | L63: -0.0055667736 | M63: =VALUE(SUBSTITUTE(H63,",","")) -> 3740372
A64: 45597 | B64: 3989.85 | C64: 3998.95 | D64: 3976.05 | E64: 3983.05 | F64: 3984.2 | G64: 3987.41 | H64: 1,54,895 | I64: 61,76,30,511.60 | J64: 18588 | K64: =(F64-F63)/F63 -> 0.0039688039 | L64: 0.0040900049 | M64: =VALUE(SUBSTITUTE(H64,",","")) -> 154895
A65: 45600 | B65: 3966.3 | C65: 3991.9 | D65: 3913.25 | E65: 3967 | F65: 3964.15 | G65: 3950.51 | H65: 22,69,192 | I65: 8,96,44,63,071.95 | J65: 1,99,030 | K65: =(F65-F64)/F64 -> -0.0050323779 | L65: -0.012713773 | M65: =VALUE(SUBSTITUTE(H65,",","")) -> 2269192
A66: 45601 | B66: 3941.1 | C66: 3986 | D66: 3941.1 | E66: 3971.55 | F66: 3971.35 | G66: 3969.47 | H66: 9,67,590 | I66: 3,84,08,20,731.70 | J66: 92042 | K66: =(F66-F65)/F65 -> 0.0018162784 | L66: 0.0090830098 | M66: =VALUE(SUBSTITUTE(H66,",","")) -> 967590
A67: 45602 | B67: 4003.6 | C67: 4149.8 | D67: 3975.25 | E67: 4143 | F67: 4139.65 | G67: 4102.32 | H67: 37,92,017 | I67: 15,55,60,64,937.35 | J67: 2,33,333 | K67: =(F67-F66)/F66 -> 0.042378536 | L67: 0.011181871 | M67: =VALUE(SUBSTITUTE(H67,",","")) -> 3792017
A68: 45603 | B68: 4169.7 | C68: 4205.8 | D68: 4085.05 | E68: 4146 | F68: 4150.9 | G68: 4144.54 | H68: 37,24,349 | I68: 15,43,57,05,018.25 | J68: 1,89,460 | K68: =(F68-F67)/F67 -> 0.0027176211 | L68: -0.011627978 | M68: =VALUE(SUBSTITUTE(H68,",","")) -> 3724349
A69: 45604 | B69: 4155 | C69: 4169.75 | D69: 4117.65 | E69: 4135.65 | F69: 4147 | G69: 4141.5 | H69: 16,48,039 | I69: 6,82,53,48,802.40 | J69: 1,39,776 | K69: =(F69-F68)/F68 -> -0.00093955528 | L69: -0.0021136931 | M69: =VALUE(SUBSTITUTE(H69,",","")) -> 1648039
A70: 45607 | B70: 4128.2 | C70: 4234.3 | D70: 4117.65 | E70: 4186.5 | F70: 4198.7 | G70: 4195.46 | H70: 14,06,487 | I70: 5,90,08,64,157.10 | J70: 1,49,144 | K70: =(F70-F69)/F69 -> 0.012466843 | L70: -0.00028573558 | M70: =VALUE(SUBSTITUTE(H70,",","")) -> 1406487
A71: 45608 | B71: 4216 | C71: 4218 | D71: 4164.35 | E71: 4180 | F71: 4197.4 | G71: 4195.93 | H71: 15,87,640 | I71: 6,66,16,21,166.75 | J71: 1,02,025 | K71: =(F71-F70)/F70 -> -0.00030961964 | L71: -0.010680866 | M71: =VALUE(SUBSTITUTE(H71,",","")) -> 1587640
A72: 45609 | B72: 4178.1 | C72: 4196.75 | D72: 4131.05 | E72: 4151.65 | F72: 4150.35 | G72: 4155.05 | H72: 10,98,813 | I72: 4,56,56,28,216.20 | J72: 1,14,945 | K72: =(F72-F71)/F71 -> -0.01120932 | L72: -0.013582627 | M72: =VALUE(SUBSTITUTE(H72,",","")) -> 1098813
A73: 45610 | B73: 4135 | C73: 4160 | D73: 4116.45 | E73: 4148 | F73: 4145.9 | G73: 4142.32 | H73: 18,25,432 | I73: 7,56,15,31,479.90 | J73: 1,65,379 | K73: =(F73-F72)/F72 -> -0.0010721987 | L73: -0.0011184662 | M73: =VALUE(SUBSTITUTE(H73,",","")) -> 1825432
A74: 45614 | B74: 4213 | C74: 4213 | D74: 3990.2 | E74: 4017.15 | F74: 4019.5 | G74: 4071.97 | H74: 33,13,944 | I74: 13,49,42,96,959.70 | J74: 1,78,320 | K74: =(F74-F73)/F73 -> -0.030487952 | L74: -0.0033527814 | M74: =VALUE(SUBSTITUTE(H74,",","")) -> 3313944
A75: 45615 | B75: 4019.9 | C75: 4132.15 | D75: 4014.1 | E75: 4042 | F75: 4039.55 | G75: 4080.53 | H75: 17,76,233 | I75: 7,24,79,68,687.60 | J75: 1,33,137 | K75: =(F75-F74)/F74 -> 0.0049881826 | L75: 0.0027586148 | M75: =VALUE(SUBSTITUTE(H75,",","")) -> 1776233
A76: 45617 | B76: 4044.9 | C76: 4092.45 | D76: 4024 | E76: 4068 | F76: 4072.85 | G76: 4058.28 | H76: 23,84,347 | I76: 9,67,63,46,995.65 | J76: 1,58,009 | K76: =(F76-F75)/F75 -> 0.0082434925 | L76: -0.0071688245 | M76: =VALUE(SUBSTITUTE(H76,",","")) -> 2384347
A77: 45618 | B77: 4071 | C77: 4254.95 | D77: 4054 | E77: 4221.95 | F77: 4244.6 | G77: 4186.15 | H77: 30,96,553 | I77: 12,96,26,40,957.15 | J77: 1,63,715 | K77: =(F77-F76)/F76 -> 0.042169488 | L77: 0.023869481 | M77: =VALUE(SUBSTITUTE(H77,",","")) -> 3096553
A78: 45621 | B78: 4280 | C78: 4328.1 | D78: 4252.2 | E78: 4320 | F78: 4315.1 | G78: 4303.42 | H78: 40,52,167 | I78: 17,43,81,78,815.15 | J78: 1,54,060 | K78: =(F78-F77)/F77 -> 0.016609339 | L78: 0.01316128 | M78: =VALUE(SUBSTITUTE(H78,",","")) -> 4052167
... A98: 45649 | B98: 4200.05 | C98: 4217 | D98: 4114.9 | E98: 4157.05 | F98: 4158.3 | G98: 4150.99 | H98: 21,95,338 | I98: 9,11,28,20,726.95 | J98: 1,49,845 | K98: =(F98-F97)/F97 -> -0.0028774908 | L98: 0.0070355061 | M98: =VALUE(SUBSTITUTE(H98,",","")) -> 2195338
A99: 45650 | B99: 4158.3 | C99: 4218 | D99: 4158.3 | E99: 4182 | F99: 4179.5 | G99: 4186.17 | H99: 11,81,886 | I99: 4,94,75,71,708.95 | J99: 77609 | K99: =(F99-F98)/F98 -> 0.0050982373 | L99: -0.001086158 | M99: =VALUE(SUBSTITUTE(H99,",","")) -> 1181886
A100: 45652 | B100: 4179.5 | C100: 4199.95 | D100: 4143.15 | E100: 4170 | F100: 4169.1 | G100: 4163.43 | H100: 12,08,464 | I100: 5,03,13,52,687.20 | J100: 1,06,756 | K100: =(F100-F99)/F99 -> -0.0024883359 | L100: 0.00095036803 | M100: =VALUE(SUBSTITUTE(H100,",","")) -> 1208464
A101: 45653 | B101: 4163 | C101: 4180.95 | D101: 4147.25 | E101: 4157.1 | F101: 4164.85 | G101: 4163.19 | H101: 8,58,100 | I101: 3,57,24,37,410.85 | J101: 88194 | K101: =(F101-F100)/F100 -> -0.0010194047 | L101: 0.0026610302 | M101: =VALUE(SUBSTITUTE(H101,",","")) -> 858100
A102: 45656 | B102: 4151 | C102: 4199.3 | D102: 4112 | E102: 4150 | F102: 4158.8 | G102: 4152.08 | H102: 15,27,169 | I102: 6,34,09,28,576.30 | J102: 1,16,250 | K102: =(F102-F101)/F101 -> -0.0014526333 | L102: -0.0070758481 | M102: =VALUE(SUBSTITUTE(H102,",","")) -> 1527169
A103: 45657 | B103: 4135 | C103: 4139.95 | D103: 4032.05 | E103: 4106 | F103: 4094.8 | G103: 4079.71 | H103: 15,55,429 | I103: 6,34,57,00,031.05 | J103: 1,62,877 | K103: =(F103-F102)/F102 -> -0.015389055 | L103: -4.2292418e-06 | M103: =VALUE(SUBSTITUTE(H103,",","")) -> 1555429
A104: 45658 | B104: 4094.4 | C104: 4134 | D104: 4085.45 | E104: 4112 | F104: 4112.45 | G104: 4112.75 | H104: 7,63,161 | I104: 3,13,86,92,117.15 | J104: 99498 | K104: =(F104-F103)/F103 -> 0.0043103448 | L104: 0.0041489038 | M104: =VALUE(SUBSTITUTE(H104,",","")) -> 763161
A105: 45659 | B105: 4120 | C105: 4183 | D105: 4096.95 | E105: 4166 | F105: 4175.75 | G105: 4159.77 | H105: 17,20,835 | I105: 7,15,82,73,705.25 | J105: 1,24,549 | K105: =(F105-F104)/F104 -> 0.015392284 | L105: 0.018774034 | M105: =VALUE(SUBSTITUTE(H105,",","")) -> 1720835
A106: 45660 | B106: 4179.95 | C106: 4179.95 | D106: 4092.3 | E106: 4097 | F106: 4099.9 | G106: 4114.17 | H106: 17,91,953 | I106: 7,37,24,04,407.85 | J106: 1,25,354 | K106: =(F106-F105)/F105 -> -0.018164402 | L106: -0.0076027393 | M106: =VALUE(SUBSTITUTE(H106,",","")) -> 1791953
A107: 45663 | B107: 4105.5 | C107: 4149.65 | D107: 4066.4 | E107: 4090 | F107: 4095 | G107: 4107.14 | H107: 20,85,593 | I107: 8,56,58,22,653.70 | J107: 1,58,660 | K107: =(F107-F106)/F106 -> -0.0011951511 | L107: -0.016192629 | M107: =VALUE(SUBSTITUTE(H107,",","")) -> 2085593
A108: 45664 | B108: 4114.95 | C108: 4140.35 | D108: 4011.55 | E108: 4031 | F108: 4028.3 | G108: 4045.86 | H108: 26,69,054 | I108: 10,79,86,29,271.20 | J108: 1,77,825 | K108: =(F108-F107)/F107 -> -0.016288156 | L108: 0.0038893041 | M108: =VALUE(SUBSTITUTE(H108,",","")) -> 2669054
A109: 45665 | B109: 4034.9 | C109: 4126 | D109: 4017.75 | E109: 4095.05 | F109: 4108.4 | G109: 4056.18 | H109: 21,81,277 | I109: 8,84,76,52,251.50 | J109: 1,80,073 | K109: =(F109-F108)/F108 -> 0.019884318 | L109: -0.00079931162 | M109: =VALUE(SUBSTITUTE(H109,",","")) -> 2181277
A110: 45666 | B110: 4101 | C110: 4137.75 | D110: 4025.3 | E110: 4044 | F110: 4038.85 | G110: 4073.67 | H110: 23,92,472 | I110: 9,74,61,49,398.35 | J110: 1,83,446 | K110: =(F110-F109)/F109 -> -0.016928731 | L110: -0.0068576277 | M110: =VALUE(SUBSTITUTE(H110,",","")) -> 2392472
A111: 45667 | B111: 4200 | C111: 4297 | D111: 4170 | E111: 4265 | F111: 4265.65 | G111: 4240.63 | H111: 78,94,300 | I111: 33,47,68,09,439.65 | J111: 4,36,975 | K111: =(F111-F110)/F110 -> 0.056154598 | L111: -0.0040379997 | M111: =VALUE(SUBSTITUTE(H111,",","")) -> 7894300
A112: 45670 | B112: 4245 | C112: 4322.95 | D112: 4227.4 | E112: 4299 | F112: 4291.1 | G112: 4294.04 | H112: 40,03,771 | I112: 17,19,23,53,666.25 | J112: 2,70,932 | K112: =(F112-F111)/F111 -> 0.0059662654 | L112: -0.014747242 | M112: =VALUE(SUBSTITUTE(H112,",","")) -> 4003771
A113: 45671 | B113: 4302 | C113: 4313.9 | D113: 4219.05 | E113: 4241.15 | F113: 4233.05 | G113: 4252.06 | H113: 34,41,709 | I113: 14,63,43,69,218.50 | J113: 1,80,842 | K113: =(F113-F112)/F112 -> -0.013528 | L113: 0.0039028067 | M113: =VALUE(SUBSTITUTE(H113,",","")) -> 3441709
A114: 45672 | B114: 4218 | C114: 4256.45 | D114: 4207.45 | E114: 4255.4 | F114: 4249.6 | G114: 4229.68 | H114: 16,53,474 | I114: 6,99,36,67,215.60 | J114: 1,30,857 | K114: =(F114-F113)/F113 -> 0.0039097105 | L114: 0.0016029479 | M114: =VALUE(SUBSTITUTE(H114,",","")) -> 1653474
A115: 45673 | B115: 4260 | C115: 4294 | D115: 4191.85 | E115: 4215 | F115: 4206.3 | G115: 4212.91 | H115: 26,37,705 | I115: 11,11,24,18,871.40 | J115: 1,76,306 | K115: =(F115-F114)/F114 -> -0.010189194 | L115: 0.0042475833 | M115: =VALUE(SUBSTITUTE(H115,",","")) -> 2637705
A116: 45674 | B116: 4159.9 | C116: 4160.6 | D116: 4100.05 | E116: 4130 | F116: 4124.3 | G116: 4132.6 | H116: 17,61,466 | I116: 7,27,94,36,408.25 | J116: 1,57,671 | K116: =(F116-F115)/F115 -> -0.019494568 | L116: -0.0046585849 | M116: =VALUE(SUBSTITUTE(H116,",","")) -> 1761466
... A120: 45680 | B120: 4168 | C120: 4191.35 | D120: 4140.05 | E120: 4148 | F120: 4145.45 | G120: 4161.12 | H120: 18,22,998 | I120: 7,58,57,18,475.40 | J120: 1,39,860 | K120: =(F120-F119)/F119 -> -0.0026824809 | L120: 0.0021593282 | M120: =VALUE(SUBSTITUTE(H120,",","")) -> 1822998
A121: 45681 | B121: 4104 | C121: 4178 | D121: 4104 | E121: 4153.1 | F121: 4152.35 | G121: 4155.62 | H121: 19,10,099 | I121: 7,93,76,40,859.20 | J121: 99760 | K121: =(F121-F120)/F120 -> 0.0016644755 | L121: -0.0048760307 | M121: =VALUE(SUBSTITUTE(H121,",","")) -> 1910099
A122: 45684 | B122: 4102 | C122: 4156.35 | D122: 4041.05 | E122: 4067 | F122: 4065.15 | G122: 4088.62 | H122: 15,51,782 | I122: 6,34,46,44,149.25 | J122: 1,43,859 | K122: =(F122-F121)/F121 -> -0.021000157 | L122: -0.011391292 | M122: =VALUE(SUBSTITUTE(H122,",","")) -> 1551782
A123: 45685 | B123: 4070.8 | C123: 4102 | D123: 4028.3 | E123: 4040 | F123: 4040.3 | G123: 4057.3 | H123: 24,68,272 | I123: 10,01,45,14,674.15 | J123: 1,50,121 | K123: =(F123-F122)/F122 -> -0.0061129356 | L123: 0.005611247 | M123: =VALUE(SUBSTITUTE(H123,",","")) -> 2468272
A124: 45686 | B124: 4054 | C124: 4107.85 | D124: 4054 | E124: 4105 | F124: 4099.8 | G124: 4091.12 | H124: 12,17,089 | I124: 4,97,92,53,773.00 | J124: 1,08,284 | K124: =(F124-F123)/F123 -> 0.014726629 | L124: 0.0089666663 | M124: =VALUE(SUBSTITUTE(H124,",","")) -> 1217089
A125: 45687 | B125: 4099.9 | C125: 4129.9 | D125: 4058.5 | E125: 4100 | F125: 4100.05 | G125: 4098.87 | H125: 15,31,251 | I125: 6,27,64,04,777.90 | J125: 97767 | K125: =(F125-F124)/F124 -> 6.0978584e-05 | L125: 0.0037300707 | M125: =VALUE(SUBSTITUTE(H125,",","")) -> 1531251
A126: 45688 | B126: 4110 | C126: 4128.45 | D126: 4085.25 | E126: 4114.15 | F126: 4112.4 | G126: 4106.05 | H126: 14,92,943 | I126: 6,13,01,03,902.20 | J126: 1,21,858 | K126: =(F126-F125)/F125 -> 0.0030121584 | L126: 0.011135723 | M126: =VALUE(SUBSTITUTE(H126,",","")) -> 1492943
A127: 45689 | B127: 4113 | C127: 4135.9 | D127: 4056 | E127: 4073 | F127: 4073.15 | G127: 4082.48 | H127: 4,37,172 | I127: 1,78,47,47,121.10 | J127: 49186 | K127: =(F127-F126)/F126 -> -0.009544305 | L127: -0.0011166221 | M127: =VALUE(SUBSTITUTE(H127,",","")) -> 437172
A128: 45691 | B128: 4030.9 | C128: 4077 | D128: 3998.7 | E128: 4064 | F128: 4068.65 | G128: 4045.97 | H128: 12,65,713 | I128: 5,12,10,41,211.00 | J128: 1,55,134 | K128: =(F128-F127)/F127 -> -0.001104796 | L128: -0.0051571087 | M128: =VALUE(SUBSTITUTE(H128,",","")) -> 1265713
A129: 45692 | B129: 4083.7 | C129: 4118.85 | D129: 4066.05 | E129: 4105.15 | F129: 4107.05 | G129: 4098 | H129: 25,47,132 | I129: 10,43,81,41,551.80 | J129: 1,41,942 | K129: =(F129-F128)/F128 -> 0.00943802 | L129: 0.016189341 | M129: =VALUE(SUBSTITUTE(H129,",","")) -> 2547132
A130: 45693 | B130: 4150 | C130: 4150 | D130: 4076 | E130: 4086 | F130: 4091.1 | G130: 4096.29 | H130: 16,93,912 | I130: 6,93,87,52,665.75 | J130: 1,30,235 | K130: =(F130-F129)/F129 -> -0.0038835661 | L130: -0.00180924 | M130: =VALUE(SUBSTITUTE(H130,",","")) -> 1693912
A131: 45694 | B131: 4105.4 | C131: 4139.5 | D131: 4051.55 | E131: 4087 | F131: 4082.75 | G131: 4080.65 | H131: 22,84,536 | I131: 9,32,23,89,842.50 | J131: 1,83,903 | K131: =(F131-F130)/F130 -> -0.0020410159 | L131: -0.0039225533 | M131: =VALUE(SUBSTITUTE(H131,",","")) -> 2284536
A132: 45695 | B132: 4090 | C132: 4090 | D132: 4008 | E132: 4032 | F132: 4029.4 | G132: 4033.06 | H132: 15,48,940 | I132: 6,24,69,65,406.40 | J132: 1,77,110 | K132: =(F132-F131)/F131 -> -0.013067173 | L132: -0.001838722 | M132: =VALUE(SUBSTITUTE(H132,",","")) -> 1548940
A133: 45698 | B133: 4040 | C133: 4052 | D133: 4014.35 | E133: 4034 | F133: 4036.95 | G133: 4035.26 | H133: 13,39,511 | I133: 5,40,52,79,190.45 | J133: 1,33,697 | K133: =(F133-F132)/F132 -> 0.0018737281 | L133: -0.00757005 | M133: =VALUE(SUBSTITUTE(H133,",","")) -> 1339511
A134: 45699 | B134: 4018.4 | C134: 4040 | D134: 3955 | E134: 3967 | F134: 3963.55 | G134: 3989.58 | H134: 18,10,908 | I134: 7,22,47,58,107.05 | J134: 1,21,478 | K134: =(F134-F133)/F133 -> -0.018182043 | L134: -0.013249735 | M134: =VALUE(SUBSTITUTE(H134,",","")) -> 1810908
A135: 45700 | B135: 3971.1 | C135: 4021.75 | D135: 3940.15 | E135: 3956.25 | F135: 3950.15 | G135: 3978.32 | H135: 16,78,002 | I135: 6,67,56,28,781.95 | J135: 1,28,576 | K135: =(F135-F134)/F134 -> -0.0033808076 | L135: -0.0011507555 | M135: =VALUE(SUBSTITUTE(H135,",","")) -> 1678002
A136: 45701 | B136: 3968 | C136: 3984.45 | D136: 3902.25 | E136: 3920 | F136: 3910.15 | G136: 3930.8 | H136: 22,77,310 | I136: 8,95,16,39,767.60 | J136: 1,63,030 | K136: =(F136-F135)/F135 -> -0.010126198 | L136: -0.00060099153 | M136: =VALUE(SUBSTITUTE(H136,",","")) -> 2277310
...

Sheet INFY
A1: DATE | B1: OPEN | C1: HIGH | D1: LOW | E1: PREV. CLOSE | F1: CLOSE | G1: VWAP | H1: VOLUME | I1: VALUE | J1: NO. OF TRADES | K1: DAILY RETURN | L1: NIFTY RETURN
A2: 45509 | B2: 1784.95 | C2: 1797.5 | D2: 1718.55 | E2: 1821.2 | F2: 1751.9 | G2: 1748.15 | H2: 1,07,36,703 | I2: 18,76,93,78,971.85 | J2: 3,57,150 | M2: =VALUE(SUBSTITUTE(H2,",","")) -> 10736703
A3: 45510 | B3: 1760.2 | C3: 1796.95 | D3: 1744.85 | E3: 1751.9 | F3: 1751.1 | G3: 1762.7 | H3: 76,90,163 | I3: 13,55,54,53,181.95 | J3: 2,29,956 | K3: =(F3-F2)/F2 -> -0.00045664707 | L3: -0.0026210113 | M3: =VALUE(SUBSTITUTE(H3,",","")) -> 7690163
A4: 45511 | B4: 1796 | C4: 1797.9 | D4: 1762.1 | E4: 1751.1 | F4: 1791.65 | G4: 1782.2 | H4: 50,94,329 | I4: 9,07,91,19,381.90 | J4: 1,89,924 | K4: =(F4-F3)/F3 -> 0.023156873 | L4: 0.012710195 | M4: =VALUE(SUBSTITUTE(H4,",","")) -> 5094329
A5: 45512 | B5: 1779.95 | C5: 1779.95 | D5: 1727.1 | E5: 1791.65 | F5: 1743.15 | G5: 1748.61 | H5: 62,27,910 | I5: 10,89,02,09,220.55 | J5: 2,37,457 | K5: =(F5-F4)/F4 -> -0.027070019 | L5: -0.0074287478 | M5: =VALUE(SUBSTITUTE(H5,",","")) -> 6227910
A6: 45513 | B6: 1771.25 | C6: 1780.75 | D6: 1756 | E6: 1743.15 | F6: 1770.75 | G6: 1766.78 | H6: 42,58,524 | I6: 7,52,38,90,127.90 | J6: 1,30,511 | K6: =(F6-F5)/F5 -> 0.015833405 | L6: 0.010386864 | M6: =VALUE(SUBSTITUTE(H6,",","")) -> 4258524
A7: 45516 | B7: 1773.05 | C7: 1803.5 | D7: 1768.1 | E7: 1770.75 | F7: 1797.4 | G7: 1793.12 | H7: 43,15,329 | I7: 7,73,79,16,018.35 | J7: 1,38,899 | K7: =(F7-F6)/F6 -> 0.01505012 | L7: -0.0008412845 | M7: =VALUE(SUBSTITUTE(H7,",","")) -> 4315329
A8: 45517 | B8: 1810 | C8: 1810 | D8: 1789.05 | E8: 1797.4 | F8: 1797.45 | G8: 1799.3 | H8: 41,76,918 | I8: 7,51,55,36,069.05 | J8: 1,52,390 | K8: =(F8-F7)/F7 -> 2.7817959e-05 | L8: -0.008543147 | M8: =VALUE(SUBSTITUTE(H8,",","")) -> 4176918
A9: 45518 | B9: 1802 | C9: 1825 | D9: 1797.45 | E9: 1797.45 | F9: 1823.25 | G9: 1813.72 | H9: 74,50,718 | I9: 13,51,35,04,750.80 | J9: 1,95,413 | K9: =(F9-F8)/F8 -> 0.014353668 | L9: 0.000196777 | M9: =VALUE(SUBSTITUTE(H9,",","")) -> 7450718
A10: 45520 | B10: 1850 | C10: 1861.85 | D10: 1829.5 | E10: 1823.25 | F10: 1858.95 | G10: 1844.85 | H10: 73,35,657 | I10: 13,53,31,80,793.15 | J10: 2,18,353 | K10: =(F10-F9)/F9 -> 0.01958042 | L10: 0.016459746 | M10: =VALUE(SUBSTITUTE(H10,",","")) -> 7335657
A11: 45523 | B11: 1860 | C11: 1867.55 | D11: 1849.2 | E11: 1858.95 | F11: 1864.8 | G11: 1862.3 | H11: 25,85,989 | I11: 4,81,58,90,949.80 | J11: 1,40,168 | K11: =(F11-F10)/F10 -> 0.0031469378 | L11: 0.0012835584 | M11: =VALUE(SUBSTITUTE(H11,",","")) -> 2585989
A12: 45524 | B12: 1880 | C12: 1885.7 | D12: 1868.2 | E12: 1864.8 | F12: 1872.2 | G12: 1875.2 | H12: 38,70,333 | I12: 7,25,76,35,525.75 | J12: 1,41,879 | K12: =(F12-F11)/F11 -> 0.003968254 | L12: 0.0051357912 | M12: =VALUE(SUBSTITUTE(H12,",","")) -> 3870333
A13: 45525 | B13: 1875.1 | C13: 1879 | D13: 1867.1 | E13: 1872.2 | F13: 1872.7 | G13: 1871.57 | H13: 19,66,902 | I13: 3,68,11,87,613.50 | J13: 1,16,979 | K13: =(F13-F12)/F12 -> 0.00026706548 | L13: 0.0028887985 | M13: =VALUE(SUBSTITUTE(H13,",","")) -> 1966902
A14: 45526 | B14: 1884 | C14: 1893.65 | D14: 1869.7 | E14: 1872.7 | F14: 1880.25 | G14: 1880.39 | H14: 43,00,287 | I14: 8,08,62,21,002.75 | J14: 1,85,241 | K14: =(F14-F13)/F13 -> 0.0040316121 | L14: 0.0016673261 | M14: =VALUE(SUBSTITUTE(H14,",","")) -> 4300287
... A30: 45548 | B30: 1950.45 | C30: 1958.6 | D30: 1935.65 | E30: 1950.45 | F30: 1944.1 | G30: 1948.85 | H30: 38,43,127 | I30: 7,48,96,65,426.75 | J30: 1,20,139 | K30: =(F30-F29)/F29 -> -0.0032556589 | L30: -0.0012761482 | M30: =VALUE(SUBSTITUTE(H30,",","")) -> 3843127
A31: 45551 | B31: 1945.75 | C31: 1952 | D31: 1933.05 | E31: 1944.1 | F31: 1950.25 | G31: 1943.67 | H31: 15,70,181 | I31: 3,05,19,12,524.40 | J31: 72563 | K31: =(F31-F30)/F30 -> 0.0031634175 | L31: 0.0010746751 | M31: =VALUE(SUBSTITUTE(H31,",","")) -> 1570181
A32: 45552 | B32: 1947.75 | C32: 1958.45 | D32: 1942.15 | E32: 1950.25 | F32: 1952.55 | G32: 1951.76 | H32: 27,93,127 | I32: 5,45,15,01,004.50 | J32: 1,42,203 | K32: =(F32-F31)/F31 -> 0.001179336 | L32: 0.0013709558 | M32: =VALUE(SUBSTITUTE(H32,",","")) -> 2793127
A33: 45553 | B33: 1938.75 | C33: 1938.75 | D33: 1881.3 | E33: 1952.55 | F33: 1892.15 | G33: 1898.2 | H33: 63,85,468 | I33: 12,12,08,91,191.90 | J33: 2,52,266 | K33: =(F33-F32)/F32 -> -0.030933907 | L33: -0.0016129952 | M33: =VALUE(SUBSTITUTE(H33,",","")) -> 6385468
A34: 45554 | B34: 1910.6 | C34: 1924.9 | D34: 1878.8 | E34: 1892.15 | F34: 1894.2 | G34: 1894.84 | H34: 79,76,570 | I34: 15,11,43,09,893.55 | J34: 2,19,801 | K34: =(F34-F33)/F33 -> 0.0010834236 | L34: 0.0015072377 | M34: =VALUE(SUBSTITUTE(H34,",","")) -> 7976570
A35: 45555 | B35: 1905 | C35: 1915 | D35: 1867.4 | E35: 1894.2 | F35: 1905.75 | G35: 1902.04 | H35: 1,52,42,974 | I35: 28,99,27,78,817.95 | J35: 3,46,786 | K35: =(F35-F34)/F34 -> 0.006097561 | L35: 0.014760503 | M35: =VALUE(SUBSTITUTE(H35,",","")) -> 15242974
A36: 45558 | B36: 1909 | C36: 1918.9 | D36: 1878.45 | E36: 1905.75 | F36: 1896.45 | G36: 1890.26 | H36: 36,36,672 | I36: 6,87,42,60,634.45 | J36: 1,33,793 | K36: =(F36-F35)/F35 -> -0.0048799685 | L36: 0.0057423243 | M36: =VALUE(SUBSTITUTE(H36,",","")) -> 3636672
A37: 45559 | B37: 1888 | C37: 1910.9 | D37: 1871.4 | E37: 1896.45 | F37: 1898.6 | G37: 1888.94 | H37: 72,77,616 | I37: 13,74,69,48,535.65 | J37: 1,81,532 | K37: =(F37-F36)/F36 -> 0.0011336972 | L37: 5.2045083e-05 | M37: =VALUE(SUBSTITUTE(H37,",","")) -> 7277616
A38: 45560 | B38: 1886.35 | C38: 1901.6 | D38: 1876.8 | E38: 1898.6 | F38: 1895.3 | G38: 1889.52 | H38: 42,68,341 | I38: 8,06,51,07,237.85 | J38: 1,73,033 | K38: =(F38-F37)/F37 -> -0.0017381228 | L38: 0.0024575566 | M38: =VALUE(SUBSTITUTE(H38,",","")) -> 4268341
A39: 45561 | B39: 1897.8 | C39: 1917.95 | D39: 1893 | E39: 1895.3 | F39: 1900.25 | G39: 1902.94 | H39: 89,52,803 | I39: 17,03,66,13,838.85 | J39: 2,04,902 | K39: =(F39-F38)/F38 -> 0.0026117237 | L39: 0.0081486993 | M39: =VALUE(SUBSTITUTE(H39,",","")) -> 8952803
A40: 45562 | B40: 1932.1 | C40: 1974.6 | D40: 1903.3 | E40: 1900.25 | F40: 1906.75 | G40: 1926.62 | H40: 1,49,08,931 | I40: 28,72,38,92,455.00 | J40: 3,01,305 | K40: =(F40-F39)/F39 -> 0.0034206026 | L40: -0.0014151636 | M40: =VALUE(SUBSTITUTE(H40,",","")) -> 14908931
A41: 45565 | B41: 1880 | C41: 1901.25 | D41: 1870.5 | E41: 1906.75 | F41: 1875.6 | G41: 1881.3 | H41: 69,86,955 | I41: 13,14,45,82,073.90 | J41: 2,25,929 | K41: =(F41-F40)/F40 -> -0.016336699 | L41: -0.014060915 | M41: =VALUE(SUBSTITUTE(H41,",","")) -> 6986955
A42: 45566 | B42: 1875 | C42: 1908.95 | D42: 1875 | E42: 1875.6 | F42: 1904.35 | G42: 1898.99 | H42: 40,29,072 | I42: 7,65,11,53,333.05 | J42: 1,53,975 | K42: =(F42-F41)/F41 -> 0.015328428 | L42: -0.00054047038 | M42: =VALUE(SUBSTITUTE(H42,",","")) -> 4029072
A43: 45568 | B43: 1889.5 | C43: 1911.85 | D43: 1881 | E43: 1904.35 | F43: 1893.4 | G43: 1895.02 | H43: 75,03,887 | I43: 14,22,00,32,273.75 | J43: 2,79,836 | K43: =(F43-F42)/F42 -> -0.0057499934 | L43: -0.021196345 | M43: =VALUE(SUBSTITUTE(H43,",","")) -> 7503887
... A63: 45596 | B63: 1787.9 | C63: 1787.9 | D63: 1746.5 | E63: 1802.1 | F63: 1757.25 | G63: 1759.11 | H63: 73,95,236 | I63: 13,00,90,50,347.40 | J63: 2,83,103 | K63: =(F63-F62)/F62 -> -0.024887631 | L63: -0.0055667736 | M63: =VALUE(SUBSTITUTE(H63,",","")) -> 7395236
A64: 45597 | B64: 1764.5 | C64: 1766 | D64: 1752.05 | E64: 1757.25 | F64: 1760.85 | G64: 1761.68 | H64: 3,71,966 | I64: 65,52,84,656.85 | J64: 29613 | K64: =(F64-F63)/F63 -> 0.0020486556 | L64: 0.0040900049 | M64: =VALUE(SUBSTITUTE(H64,",","")) -> 371966
A65: 45600 | B65: 1724.5 | C65: 1767 | D65: 1718 | E65: 1760.85 | F65: 1763.65 | G65: 1742.2 | H65: 73,36,722 | I65: 12,78,20,53,575.35 | J65: 2,37,541 | K65: =(F65-F64)/F64 -> 0.0015901411 | L65: -0.012713773 | M65: =VALUE(SUBSTITUTE(H65,",","")) -> 7336722
A66: 45601 | B66: 1760 | C66: 1768.45 | D66: 1745 | E66: 1763.65 | F66: 1754.2 | G66: 1754.19 | H66: 31,60,880 | I66: 5,54,47,81,198.40 | J66: 1,68,160 | K66: =(F66-F65)/F65 -> -0.005358206 | L66: 0.0090830098 | M66: =VALUE(SUBSTITUTE(H66,",","")) -> 3160880
A67: 45602 | B67: 1764 | C67: 1827.2 | D67: 1762.65 | E67: 1754.2 | F67: 1823.7 | G67: 1809.14 | H67: 1,04,21,494 | I67: 18,85,39,55,667.25 | J67: 3,05,870 | K67: =(F67-F66)/F66 -> 0.0396192 | L67: 0.011181871 | M67: =VALUE(SUBSTITUTE(H67,",","")) -> 10421494
A68: 45603 | B68: 1812.95 | C68: 1825.7 | D68: 1787 | E68: 1823.7 | F68: 1803.05 | G68: 1802.49 | H68: 45,50,965 | I68: 8,20,30,53,863.70 | J68: 2,74,916 | K68: =(F68-F67)/F67 -> -0.011323134 | L68: -0.011627978 | M68: =VALUE(SUBSTITUTE(H68,",","")) -> 4550965
A69: 45604 | B69: 1818 | C69: 1840.6 | D69: 1813.15 | E69: 1803.05 | F69: 1829.95 | G69: 1832.23 | H69: 42,10,960 | I69: 7,71,54,46,613.70 | J69: 1,99,379 | K69: =(F69-F68)/F68 -> 0.014919165 | L69: -0.0021136931 | M69: =VALUE(SUBSTITUTE(H69,",","")) -> 4210960
A70: 45607 | B70: 1829 | C70: 1868 | D70: 1822.55 | E70: 1829.95 | F70: 1860.1 | G70: 1855.73 | H70: 38,04,234 | I70: 7,05,96,43,882.45 | J70: 2,40,025 | K70: =(F70-F69)/F69 -> 0.01647586 | L70: -0.00028573558 | M70: =VALUE(SUBSTITUTE(H70,",","")) -> 3804234
A71: 45608 | B71: 1871.1 | C71: 1881 | D71: 1861 | E71: 1860.1 | F71: 1868.8 | G71: 1871.65 | H71: 50,12,450 | I71: 9,38,15,50,004.50 | J71: 1,82,346 | K71: =(F71-F70)/F70 -> 0.0046771679 | L71: -0.010680866 | M71: =VALUE(SUBSTITUTE(H71,",","")) -> 5012450
A72: 45609 | B72: 1861.1 | C72: 1873.2 | D72: 1856.3 | E72: 1868.8 | F72: 1868.4 | G72: 1866.77 | H72: 42,57,495 | I72: 7,94,77,52,333.85 | J72: 1,87,205 | K72: =(F72-F71)/F71 -> -0.0002140411 | L72: -0.013582627 | M72: =VALUE(SUBSTITUTE(H72,",","")) -> 4257495
A73: 45610 | B73: 1865.6 | C73: 1876 | D73: 1856 | E73: 1868.4 | F73: 1864.55 | G73: 1865.97 | H73: 43,11,431 | I73: 8,04,50,09,313.65 | J73: 2,06,703 | K73: =(F73-F72)/F72 -> -0.0020605866 | L73: -0.0011184662 | M73: =VALUE(SUBSTITUTE(H73,",","")) -> 4311431
A74: 45614 | B74: 1849.2 | C74: 1849.2 | D74: 1795 | E74: 1864.55 | F74: 1811.45 | G74: 1813.82 | H74: 48,39,244 | I74: 8,77,75,30,199.20 | J74: 2,07,559 | K74: =(F74-F73)/F73 -> -0.028478721 | L74: -0.0033527814 | M74: =VALUE(SUBSTITUTE(H74,",","")) -> 4839244
A75: 45615 | B75: 1825.5 | C75: 1859.7 | D75: 1820.55 | E75: 1811.45 | F75: 1824.75 | G75: 1839.98 | H75: 46,69,769 | I75: 8,59,22,82,283.60 | J75: 1,42,990 | K75: =(F75-F74)/F74 -> 0.0073421844 | L75: 0.0027586148 | M75: =VALUE(SUBSTITUTE(H75,",","")) -> 4669769
A76: 45617 | B76: 1842 | C76: 1867 | D76: 1820.6 | E76: 1824.75 | F76: 1834.05 | G76: 1836.76 | H76: 54,36,504 | I76: 9,98,55,80,026.60 | J76: 2,32,740 | K76: =(F76-F75)/F75 -> 0.0050965886 | L76: -0.0071688245 | M76: =VALUE(SUBSTITUTE(H76,",","")) -> 5436504
... A98: 45649 | B98: 1930.05 | C98: 1940 | D98: 1909 | E98: 1922.15 | F98: 1924.3 | G98: 1923.61 | H98: 27,81,793 | I98: 5,35,10,92,778.15 | J98: 1,27,723 | K98: =(F98-F97)/F97 -> 0.0011185391 | L98: 0.0070355061 | M98: =VALUE(SUBSTITUTE(H98,",","")) -> 2781793
A99: 45650 | B99: 1927.05 | C99: 1942 | D99: 1840 | E99: 1924.3 | F99: 1909.05 | G99: 1918.59 | H99: 23,60,544 | I99: 4,52,89,21,027.25 | J99: 93412 | K99: =(F99-F98)/F98 -> -0.0079249597 | L99: -0.001086158 | M99: =VALUE(SUBSTITUTE(H99,",","")) -> 2360544
A100: 45652 | B100: 1909.05 | C100: 1919.75 | D100: 1902.3 | E100: 1909.05 | F100: 1907.4 | G100: 1908.04 | H100: 36,23,321 | I100: 6,91,34,42,832.95 | J100: 1,23,979 | K100: =(F100-F99)/F99 -> -0.00086430424 | L100: 0.00095036803 | M100: =VALUE(SUBSTITUTE(H100,",","")) -> 3623321
A101: 45653 | B101: 1909.4 | C101: 1924.15 | D101: 1903.9 | E101: 1907.4 | F101: 1916.75 | G101: 1912.07 | H101: 39,37,500 | I101: 7,52,87,76,747.25 | J101: 1,08,688 | K101: =(F101-F100)/F100 -> 0.0049019608 | L101: 0.0026610302 | M101: =VALUE(SUBSTITUTE(H101,",","")) -> 3937500
A102: 45656 | B102: 1915.7 | C102: 1916 | D102: 1886.5 | E102: 1916.75 | F102: 1906 | G102: 1903.27 | H102: 77,89,055 | I102: 14,82,47,04,664.65 | J102: 1,80,342 | K102: =(F102-F101)/F101 -> -0.0056084518 | L102: -0.0070758481 | M102: =VALUE(SUBSTITUTE(H102,",","")) -> 7789055
A103: 45657 | B103: 1892.3 | C103: 1897 | D103: 1845.05 | E103: 1906 | F103: 1880 | G103: 1872.77 | H103: 36,13,063 | I103: 6,76,64,28,350.50 | J103: 1,50,014 | K103: =(F103-F102)/F102 -> -0.013641133 | L103: -4.2292418e-06 | M103: =VALUE(SUBSTITUTE(H103,",","")) -> 3613063
A104: 45658 | B104: 1874 | C104: 1892.95 | D104: 1874 | E104: 1880 | F104: 1882.5 | G104: 1884.95 | H104: 18,38,368 | I104: 3,46,52,23,831.85 | J104: 69020 | K104: =(F104-F103)/F103 -> 0.0013297872 | L104: 0.0041489038 | M104: =VALUE(SUBSTITUTE(H104,",","")) -> 1838368
A105: 45659 | B105: 1887 | C105: 1962.65 | D105: 1885.3 | E105: 1882.5 | F105: 1957.85 | G105: 1944.51 | H105: 70,83,645 | I105: 13,77,42,39,233.15 | J105: 2,39,506 | K105: =(F105-F104)/F104 -> 0.04002656 | L105: 0.018774034 | M105: =VALUE(SUBSTITUTE(H105,",","")) -> 7083645
A106: 45660 | B106: 1952.95 | C106: 1952.95 | D106: 1922 | E106: 1957.85 | F106: 1938.75 | G106: 1936.53 | H106: 62,18,003 | I106: 12,04,13,66,929.80 | J106: 2,26,724 | K106: =(F106-F105)/F105 -> -0.0097555993 | L106: -0.0076027393 | M106: =VALUE(SUBSTITUTE(H106,",","")) -> 6218003
A107: 45663 | B107: 1952 | C107: 1973 | D107: 1928 | E107: 1938.75 | F107: 1937.85 | G107: 1943.77 | H107: 71,64,403 | I107: 13,92,59,86,567.85 | J107: 2,47,931 | K107: =(F107-F106)/F106 -> -0.00046421663 | L107: -0.016192629 | M107: =VALUE(SUBSTITUTE(H107,",","")) -> 7164403
A108: 45664 | B108: 1945 | C108: 1958.55 | D108: 1923.65 | E108: 1937.85 | F108: 1930.85 | G108: 1936.28 | H108: 42,94,832 | I108: 8,31,59,96,332.75 | J108: 2,50,125 | K108: =(F108-F107)/F107 -> -0.0036122507 | L108: 0.0038893041 | M108: =VALUE(SUBSTITUTE(H108,",","")) -> 4294832
A109: 45665 | B109: 1930 | C109: 1938.6 | D109: 1888.75 | E109: 1930.85 | F109: 1933.15 | G109: 1916.14 | H109: 54,82,050 | I109: 10,50,43,91,305.45 | J109: 2,10,525 | K109: =(F109-F108)/F108 -> 0.0011911852 | L109: -0.00079931162 | M109: =VALUE(SUBSTITUTE(H109,",","")) -> 5482050
A110: 45666 | B110: 1934.05 | C110: 1951.85 | D110: 1910.55 | E110: 1933.15 | F110: 1917.3 | G110: 1928.12 | H110: 68,33,503 | I110: 13,17,58,34,552.90 | J110: 2,28,829 | K110: =(F110-F109)/F109 -> -0.0081990534 | L110: -0.0068576277 | M110: =VALUE(SUBSTITUTE(H110,",","")) -> 6833503
A111: 45667 | B111: 1937 | C111: 1977.8 | D111: 1932.25 | E111: 1917.3 | F111: 1966.95 | G111: 1961.18 | H111: 80,36,913 | I111: 15,76,18,35,256.95 | J111: 3,51,137 | K111: =(F111-F110)/F110 -> 0.025895791 | L111: -0.0040379997 | M111: =VALUE(SUBSTITUTE(H111,",","")) -> 8036913
A112: 45670 | B112: 1956 | C112: 1982.8 | D112: 1949 | E112: 1966.95 | F112: 1962.2 | G112: 1965.87 | H112: 58,04,152 | I112: 11,41,01,82,349.85 | J112: 2,24,017 | K112: =(F112-F111)/F111 -> -0.0024149063 | L112: -0.014747242 | M112: =VALUE(SUBSTITUTE(H112,",","")) -> 5804152
A113: 45671 | B113: 1968.85 | C113: 1971.8 | D113: 1931.1 | E113: 1962.2 | F113: 1940.05 | G113: 1943.92 | H113: 57,92,162 | I113: 11,25,94,72,879.00 | J113: 2,67,855 | K113: =(F113-F112)/F112 -> -0.01128835 | L113: 0.0039028067 | M113: =VALUE(SUBSTITUTE(H113,",","")) -> 5792162
A114: 45672 | B114: 1947 | C114: 1958.05 | D114: 1937.1 | E114: 1940.05 | F114: 1949.65 | G114: 1949.16 | H114: 29,85,439 | I114: 5,81,90,96,239.50 | J114: 1,53,629 | K114: =(F114-F113)/F113 -> 0.0049483261 | L114: 0.0016029479 | M114: =VALUE(SUBSTITUTE(H114,",","")) -> 2985439
A115: 45673 | B115: 1965.95 | C115: 1966.95 | D115: 1916.85 | E115: 1949.65 | F115: 1928.45 | G115: 1939.38 | H115: 75,33,579 | I115: 14,61,04,85,616.25 | J115: 2,33,848 | K115: =(F115-F114)/F114 -> -0.010873747 | L115: 0.0042475833 | M115: =VALUE(SUBSTITUTE(H115,",","")) -> 7533579
A116: 45674 | B116: 1851 | C116: 1858 | D116: 1812 | E116: 1928.45 | F116: 1815.45 | G116: 1824.17 | H116: 1,64,09,953 | I116: 29,93,46,01,377.85 | J116: 5,03,030 | K116: =(F116-F115)/F115 -> -0.058596282 | L116: -0.0046585849 | M116: =VALUE(SUBSTITUTE(H116,",","")) -> 16409953
... A126: 45688 | B126: 1871 | C126: 1897.45 | D126: 1871 | E126: 1859.95 | F126: 1879.8 | G126: 1881.49 | H126: 58,20,470 | I126: 10,95,11,49,690.20 | J126: 1,81,998 | K126: =(F126-F125)/F125 -> 0.01067233 | L126: 0.011135723 | M126: =VALUE(SUBSTITUTE(H126,",","")) -> 5820470
A127: 45689 | B127: 1880.3 | C127: 1890.6 | D127: 1846 | E127: 1879.8 | F127: 1851.35 | G127: 1862.44 | H127: 17,01,402 | I127: 3,16,87,63,954.00 | J127: 70335 | K127: =(F127-F126)/F126 -> -0.015134589 | L127: -0.0011166221 | M127: =VALUE(SUBSTITUTE(H127,",","")) -> 1701402
A128: 45691 | B128: 1836 | C128: 1876.55 | D128: 1832.4 | E128: 1851.35 | F128: 1863.3 | G128: 1858.62 | H128: 48,23,228 | I128: 8,96,45,53,565.40 | J128: 1,77,156 | K128: =(F128-F127)/F127 -> 0.0064547492 | L128: -0.0051571087 | M128: =VALUE(SUBSTITUTE(H128,",","")) -> 4823228
A129: 45692 | B129: 1889 | C129: 1911.2 | D129: 1875 | E129: 1863.3 | F129: 1898.8 | G129: 1892.32 | H129: 73,34,787 | I129: 13,87,97,56,408.55 | J129: 2,54,137 | K129: =(F129-F128)/F128 -> 0.019052219 | L129: 0.016189341 | M129: =VALUE(SUBSTITUTE(H129,",","")) -> 7334787
A130: 45693 | B130: 1906 | C130: 1919.7 | D130: 1894.3 | E130: 1898.8 | F130: 1897.05 | G130: 1901.79 | H130: 49,96,744 | I130: 9,50,27,54,311.35 | J130: 1,70,651 | K130: =(F130-F129)/F129 -> -0.00092163472 | L130: -0.00180924 | M130: =VALUE(SUBSTITUTE(H130,",","")) -> 4996744
A131: 45694 | B131: 1917 | C131: 1924 | D131: 1900 | E131: 1897.05 | F131: 1915.65 | G131: 1910.66 | H131: 47,65,255 | I131: 9,10,47,91,357.40 | J131: 1,51,924 | K131: =(F131-F130)/F130 -> 0.0098046968 | L131: -0.0039225533 | M131: =VALUE(SUBSTITUTE(H131,",","")) -> 4765255
A132: 45695 | B132: 1919.3 | C132: 1923.7 | D132: 1889.45 | E132: 1915.65 | F132: 1903.65 | G132: 1902.44 | H132: 41,26,260 | I132: 7,84,99,62,358.05 | J132: 1,55,494 | K132: =(F132-F131)/F131 -> -0.0062641923 | L132: -0.001838722 | M132: =VALUE(SUBSTITUTE(H132,",","")) -> 4126260
A133: 45698 | B133: 1905 | C133: 1905 | D133: 1878.6 | E133: 1903.65 | F133: 1880.3 | G133: 1885.89 | H133: 38,28,734 | I133: 7,22,05,70,924.25 | J133: 1,51,607 | K133: =(F133-F132)/F132 -> -0.01226591 | L133: -0.00757005 | M133: =VALUE(SUBSTITUTE(H133,",","")) -> 3828734
A134: 45699 | B134: 1883.1 | C134: 1903 | D134: 1870 | E134: 1880.3 | F134: 1875.65 | G134: 1883.68 | H134: 44,11,601 | I134: 8,31,00,66,406.30 | J134: 1,60,934 | K134: =(F134-F133)/F133 -> -0.0024730096 | L134: -0.013249735 | M134: =VALUE(SUBSTITUTE(H134,",","")) -> 4411601
A135: 45700 | B135: 1885 | C135: 1894.6 | D135: 1847 | E135: 1875.65 | F135: 1863.15 | G135: 1866.72 | H135: 56,33,947 | I135: 10,51,69,84,029.10 | J135: 2,22,006 | K135: =(F135-F134)/F134 -> -0.0066643564 | L135: -0.0011507555 | M135: =VALUE(SUBSTITUTE(H135,",","")) -> 5633947
A136: 45701 | B136: 1868.5 | C136: 1873.5 | D136: 1835.65 | E136: 1863.15 | F136: 1843.25 | G136: 1851.21 | H136: 52,37,744 | I136: 9,69,61,50,378.65 | J136: 1,92,119 | K136: =(F136-F135)/F135 -> -0.010680836 | L136: -0.00060099153 | M136: =VALUE(SUBSTITUTE(H136,",","")) -> 5237744
A137: 45702 | B137: 1854 | C137: 1859.3 | D137: 1828.35 | E137: 1843.25 | F137: 1856.4 | G137: 1845.06 | H137: 52,92,961 | I137: 9,76,58,18,737.55 | J137: 1,79,989 | K137: =(F137-F136)/F136 -> 0.0071341381 | L137: -0.0044352493 | M137: =VALUE(SUBSTITUTE(H137,",","")) -> 5292961
A138: 45705 | B138: 1838.55 | C138: 1852.75 | D138: 1822.15 | E138: 1856.4 | F138: 1842.3 | G138: 1838.63 | H138: 44,28,956 | I138: 8,14,32,13,452.30 | J138: 1,49,656 | K138: =(F138-F137)/F137 -> -0.0075953458 | L138: 0.0013192756 | M138: =VALUE(SUBSTITUTE(H138,",","")) -> 4428956
A139: 45706 | B139: 1842.3 | C139: 1861.65 | D139: 1837.6 | E139: 1842.3 | F139: 1851.95 | G139: 1848.81 | H139: 43,65,260 | I139: 8,07,05,46,827.05 | J139: 1,00,362 | K139: =(F139-F138)/F138 -> 0.0052380177 | L139: -0.00061848037 | M139: =VALUE(SUBSTITUTE(H139,",","")) -> 4365260
... A200: 45800 | B200: 1550 | C200: 1587.2 | D200: 1550 | E200: 1547.5 | F200: 1564.8 | G200: 1573.82 | H200: 50,38,421 | I200: 7,92,95,81,517.50 | J200: 1,19,392 | K200: =(F200-F199)/F199 -> 0.011179321 | L200: 0.0098924408 | M200: =VALUE(SUBSTITUTE(H200,",","")) -> 5038421
A201: 45803 | B201: 1566.6 | C201: 1583.8 | D201: 1562.7 | E201: 1564.8 | F201: 1580.5 | G201: 1577.54 | H201: 31,70,102 | I201: 5,00,09,73,812.70 | J201: 84853 | K201: =(F201-F200)/F200 -> 0.010033231 | L201: 0.0059549795 | M201: =VALUE(SUBSTITUTE(H201,",","")) -> 3170102
A202: 45804 | B202: 1579.9 | C202: 1582.9 | D202: 1556.4 | E202: 1580.5 | F202: 1570.1 | G202: 1567.8 | H202: 77,75,714 | I202: 12,19,07,51,506.20 | J202: 2,06,543 | K202: =(F202-F201)/F201 -> -0.0065801961 | L202: -0.0069976781 | M202: =VALUE(SUBSTITUTE(H202,",","")) -> 7775714
A203: 45805 | B203: 1581 | C203: 1587.7 | D203: 1570 | E203: 1570.1 | F203: 1571.8 | G203: 1576.59 | H203: 36,23,370 | I203: 5,71,25,74,459.00 | J203: 1,36,660 | K203: =(F203-F202)/F202 -> 0.0010827336 | L203: -0.002970652 | M203: =VALUE(SUBSTITUTE(H203,",","")) -> 3623370
A204: 45806 | B204: 1589 | C204: 1608.9 | D204: 1576.6 | E204: 1571.8 | F204: 1585.6 | G204: 1588.46 | H204: 86,09,500 | I204: 13,67,58,17,253.90 | J204: 1,94,291 | K204: =(F204-F203)/F203 -> 0.008779743 | L204: 0.0032784633 | M204: =VALUE(SUBSTITUTE(H204,",","")) -> 8609500
A205: 45807 | B205: 1571 | C205: 1572 | D205: 1555.1 | E205: 1585.6 | F205: 1562.7 | G205: 1563.06 | H205: 1,31,48,092 | I205: 20,55,12,63,119.00 | J205: 1,67,400 | K205: =(F205-F204)/F204 -> -0.014442482 | L205: -0.0033382192 | M205: =VALUE(SUBSTITUTE(H205,",","")) -> 13148092
A206: 45810 | B206: 1560 | C206: 1560 | D206: 1539 | E206: 1562.7 | F206: 1553.8 | G206: 1550.25 | H206: 43,74,509 | I206: 6,78,15,87,274.00 | J206: 1,31,906 | K206: =(F206-F205)/F205 -> -0.005695271 | L206: -0.0013777388 | M206: =VALUE(SUBSTITUTE(H206,",","")) -> 4374509
A207: 45811 | B207: 1559 | C207: 1567.3 | D207: 1535.6 | E207: 1553.8 | F207: 1543 | G207: 1546.37 | H207: 68,53,403 | I207: 10,59,78,70,232.10 | J207: 1,95,003 | K207: =(F207-F206)/F206 -> -0.0069507015 | L207: -0.0070438491 | M207: =VALUE(SUBSTITUTE(H207,",","")) -> 6853403
A208: 45812 | B208: 1543 | C208: 1557.3 | D208: 1541.4 | E208: 1543 | F208: 1551.2 | G208: 1550.49 | H208: 45,48,307 | I208: 7,05,21,04,860.60 | J208: 1,18,648 | K208: =(F208-F207)/F207 -> 0.0053143227 | L208: 0.0031659366 | M208: =VALUE(SUBSTITUTE(H208,",","")) -> 4548307
A209: 45813 | B209: 1547.9 | C209: 1567.7 | D209: 1541.6 | E209: 1551.2 | F209: 1554.3 | G209: 1554.78 | H209: 69,48,539 | I209: 10,80,34,74,457.10 | J209: 1,28,309 | K209: =(F209-F208)/F208 -> 0.0019984528 | L209: 0.005308649 | M209: =VALUE(SUBSTITUTE(H209,",","")) -> 6948539
A210: 45814 | B210: 1554.7 | C210: 1568.9 | D210: 1543.1 | E210: 1554.3 | F210: 1563.8 | G210: 1557.14 | H210: 39,60,020 | I210: 6,16,62,93,295.00 | J210: 90826 | K210: =(F210-F209)/F209 -> 0.0061120762 | L210: 0.010187508 | M210: =VALUE(SUBSTITUTE(H210,",","")) -> 3960020
A211: 45817 | B211: 1578 | C211: 1588 | D211: 1571 | E211: 1563.8 | F211: 1572.9 | G211: 1577.22 | H211: 29,03,202 | I211: 4,57,89,75,981.40 | J211: 1,13,233 | K211: =(F211-F210)/F210 -> 0.0058191585 | L211: 0.0040055113 | M211: =VALUE(SUBSTITUTE(H211,",","")) -> 2903202
A212: 45818 | B212: 1584 | C212: 1607.5 | D212: 1577.5 | E212: 1572.9 | F212: 1596 | G212: 1595.07 | H212: 85,91,925 | I212: 13,70,46,98,707.80 | J212: 2,22,769 | K212: =(F212-F211)/F211 -> 0.014686248 | L212: 4.1827337e-05 | M212: =VALUE(SUBSTITUTE(H212,",","")) -> 8591925
A213: 45819 | B213: 1590.1 | C213: 1634.6 | D213: 1590.1 | E213: 1596 | F213: 1631.1 | G213: 1617.71 | H213: 1,05,97,410 | I213: 17,14,35,54,884.60 | J213: 2,19,452 | K213: =(F213-F212)/F212 -> 0.021992481 | L213: 0.0014798291 | M213: =VALUE(SUBSTITUTE(H213,",","")) -> 10597410
A214: 45820 | B214: 1617 | C214: 1628 | D214: 1598.1 | E214: 1631.1 | F214: 1608.6 | G214: 1612.28 | H214: 1,04,83,574 | I214: 16,90,24,14,982.00 | J214: 3,16,383 | K214: =(F214-F213)/F213 -> -0.013794372 | L214: -0.010071038 | M214: =VALUE(SUBSTITUTE(H214,",","")) -> 10483574
A215: 45821 | B215: 1576 | C215: 1609 | D215: 1570.2 | E215: 1608.6 | F215: 1602 | G215: 1598.18 | H215: 69,68,315 | I215: 11,13,66,53,004.60 | J215: 2,16,576 | K215: =(F215-F214)/F214 -> -0.0041029467 | L215: -0.0068144743 | M215: =VALUE(SUBSTITUTE(H215,",","")) -> 6968315
A216: 45824 | B216: 1600 | C216: 1634.8 | D216: 1597.1 | E216: 1602 | F216: 1623.8 | G216: 1621.63 | H216: 55,91,842 | I216: 9,06,79,22,727.70 | J216: 1,38,140 | K216: =(F216-F215)/F215 -> 0.01360799 | L216: 0.0092197778 | M216: =VALUE(SUBSTITUTE(H216,",","")) -> 5591842
A217: 45825 | B217: 1620.7 | C217: 1647.4 | D217: 1615.6 | E217: 1623.8 | F217: 1639.9 | G217: 1637.98 | H217: 76,22,083 | I217: 12,48,48,37,334.90 | J217: 2,12,796 | K217: =(F217-F216)/F216 -> 0.0099150142 | L217: -0.0037319865 | M217: =VALUE(SUBSTITUTE(H217,",","")) -> 7622083
A218: 45826 | B218: 1621 | C218: 1644.7 | D218: 1621 | E218: 1639.9 | F218: 1632.9 | G218: 1631.66 | H218: 56,29,707 | I218: 9,18,57,42,882.60 | J218: 1,40,846 | K218: =(F218-F217)/F217 -> -0.004268553 | L218: -0.0016637563 | M218: =VALUE(SUBSTITUTE(H218,",","")) -> 5629707
A219: 45827 | B219: 1623.9 | C219: 1630 | D219: 1611.5 | E219: 1632.9 | F219: 1618.4 | G219: 1618.85 | H219: 51,47,760 | I219: 8,33,34,49,709.60 | J219: 1,62,048 | K219: =(F219-F218)/F218 -> -0.0088799069 | L219: -0.00075769636 | M219: =VALUE(SUBSTITUTE(H219,",","")) -> 5147760
A220: 45828 | B220: 1619 | C220: 1630.7 | D220: 1608.9 | E220: 1618.4 | F220: 1622.9 | G220: 1621.3 | H220: 92,02,821 | I220: 14,92,05,07,153.70 | J220: 1,35,603 | K220: =(F220-F219)/F219 -> 0.002780524 | L220: 0.012872455 | M220: =VALUE(SUBSTITUTE(H220,",","")) -> 9202821
A221: 45831 | B221: 1601 | C221: 1601 | D221: 1575.4 | E221: 1622.9 | F221: 1584 | G221: 1585.78 | H221: 79,43,676 | I221: 12,59,69,45,674.40 | J221: 2,06,475 | K221: =(F221-F220)/F220 -> -0.023969437 | L221: -0.0055948456 | M221: =VALUE(SUBSTITUTE(H221,",","")) -> 7943676
A222: 45832 | B222: 1601 | C222: 1609 | D222: 1576.6 | E222: 1584 | F222: 1581.6 | G222: 1590.26 | H222: 80,83,992 | I222: 12,85,56,08,766.60 | J222: 1,57,878 | K222: =(F222-F221)/F221 -> -0.0015151515 | L222: 0.002901261 | M222: =VALUE(SUBSTITUTE(H222,",","")) -> 8083992
... A303: 45950 | B303: 1453.7 | C303: 1467 | D303: 1450 | E303: 1441.1 | F303: 1460.9 | G303: 1460.15 | H303: 69,94,246 | I303: 10,21,26,38,243.40 | J303: 2,18,283 | K303: =(F303-F302)/F302 -> 0.013739505 | L303: 0.0051847833 | M303: =VALUE(SUBSTITUTE(H303,",","")) -> 6994246
A304: 45951 | B304: 1478 | C304: 1486 | D304: 1470 | E304: 1460.9 | F304: 1472.4 | G304: 1476.04 | H304: 16,98,704 | I304: 2,50,73,52,685.60 | J304: 42723 | K304: =(F304-F303)/F303 -> 0.0078718598 | L304: 0.00098478707 | M304: =VALUE(SUBSTITUTE(H304,",","")) -> 1698704
...

Sheet HDFCBANK
A1: DATE | B1: OPEN | C1: HIGH | D1: LOW | E1: PREV. CLOSE | F1: CLOSE | G1: VWAP | H1: VOLUME | I1: VALUE | J1: NO. OF TRADES | K1: DAILY RETURN | L1: NIFTY RETURN
A2: 45509 | B2: 1640.1 | C2: 1646 | D2: 1601 | E2: 1659.15 | F2: 1615.75 | G2: 1622.77 | H2: 2,06,66,817 | I2: 33,53,74,31,288.70 | J2: 4,64,696 | M2: =VALUE(SUBSTITUTE(H2,",","")) -> 20666817
A3: 45510 | B3: 1630 | C3: 1632.95 | D3: 1593.3 | E3: 1615.75 | F3: 1601.2 | G3: 1608.02 | H3: 2,25,58,025 | I3: 36,27,38,37,922.85 | J3: 3,88,854 | K3: =(F3-F2)/F2 -> -0.009005106 | L3: -0.0026210113 | M3: =VALUE(SUBSTITUTE(H3,",","")) -> 22558025
A4: 45511 | B4: 1617 | C4: 1630 | D4: 1602.2 | E4: 1601.2 | F4: 1623.5 | G4: 1617.23 | H4: 2,11,73,132 | I4: 34,24,18,47,264.50 | J4: 3,37,720 | K4: =(F4-F3)/F3 -> 0.013927055 | L4: 0.012710195 | M4: =VALUE(SUBSTITUTE(H4,",","")) -> 21173132
A5: 45512 | B5: 1624 | C5: 1653.3 | D5: 1619.25 | E5: 1623.5 | F5: 1642.7 | G5: 1638.73 | H5: 1,69,88,475 | I5: 27,83,95,62,575.60 | J5: 3,27,468 | K5: =(F5-F4)/F4 -> 0.011826301 | L5: -0.0074287478 | M5: =VALUE(SUBSTITUTE(H5,",","")) -> 16988475
A6: 45513 | B6: 1652 | C6: 1662.55 | D6: 1645.8 | E6: 1642.7 | F6: 1650.2 | G6: 1655.58 | H6: 1,33,22,309 | I6: 22,05,61,57,155.50 | J6: 2,91,916 | K6: =(F6-F5)/F5 -> 0.0045656541 | L6: 0.010386864 | M6: =VALUE(SUBSTITUTE(H6,",","")) -> 13322309
A7: 45516 | B7: 1652 | C7: 1675.95 | D7: 1647.35 | E7: 1650.2 | F7: 1660.1 | G7: 1664.63 | H7: 1,96,58,098 | I7: 32,72,35,06,965.00 | J7: 3,63,538 | K7: =(F7-F6)/F6 -> 0.0059992728 | L7: -0.0008412845 | M7: =VALUE(SUBSTITUTE(H7,",","")) -> 19658098
A8: 45517 | B8: 1628 | C8: 1632.4 | D8: 1601.15 | E8: 1660.1 | F8: 1603.2 | G8: 1613.32 | H8: 2,70,27,521 | I8: 43,60,41,63,966.10 | J8: 6,01,558 | K8: =(F8-F7)/F7 -> -0.034275044 | L8: -0.008543147 | M8: =VALUE(SUBSTITUTE(H8,",","")) -> 27027521
A9: 45518 | B9: 1606.5 | C9: 1613.7 | D9: 1603.2 | E9: 1603.2 | F9: 1607.8 | G9: 1607.97 | H9: 1,61,67,214 | I9: 25,99,64,12,110.40 | J9: 2,59,067 | K9: =(F9-F8)/F8 -> 0.0028692615 | L9: 0.000196777 | M9: =VALUE(SUBSTITUTE(H9,",","")) -> 16167214
A10: 45520 | B10: 1628.5 | C10: 1634.15 | D10: 1611 | E10: 1607.8 | F10: 1632.1 | G10: 1624.71 | H10: 1,39,24,623 | I10: 22,62,34,79,529.55 | J10: 3,02,506 | K10: =(F10-F9)/F9 -> 0.01511382 | L10: 0.016459746 | M10: =VALUE(SUBSTITUTE(H10,",","")) -> 13924623
A11: 45523 | B11: 1637.65 | C11: 1637.65 | D11: 1623.7 | E11: 1632.1 | F11: 1631.55 | G11: 1628.46 | H11: 97,51,082 | I11: 15,87,92,78,800.80 | J11: 1,66,314 | K11: =(F11-F10)/F10 -> -0.00033698916 | L11: 0.0012835584 | M11: =VALUE(SUBSTITUTE(H11,",","")) -> 9751082
A12: 45524 | B12: 1627.45 | C12: 1646 | D12: 1627.45 | E12: 1631.55 | F12: 1637.7 | G12: 1639.14 | H12: 1,55,67,247 | I12: 25,51,69,52,644.85 | J12: 2,40,802 | K12: =(F12-F11)/F11 -> 0.0037694217 | L12: 0.0051357912 | M12: =VALUE(SUBSTITUTE(H12,",","")) -> 15567247
A13: 45525 | B13: 1628.1 | C13: 1634.55 | D13: 1617.8 | E13: 1637.7 | F13: 1625.8 | G13: 1624.85 | H13: 2,38,15,452 | I13: 38,69,65,27,016.25 | J13: 3,23,415 | K13: =(F13-F12)/F12 -> -0.0072662881 | L13: 0.0028887985 | M13: =VALUE(SUBSTITUTE(H13,",","")) -> 23815452
A14: 45526 | B14: 1632 | C14: 1638.3 | D14: 1628 | E14: 1625.8 | F14: 1631.3 | G14: 1632.58 | H14: 1,06,50,319 | I14: 17,38,75,21,802.75 | J14: 2,72,441 | K14: =(F14-F13)/F13 -> 0.0033829499 | L14: 0.0016673261 | M14: =VALUE(SUBSTITUTE(H14,",","")) -> 10650319
... A63: 45596 | B63: 1728 | C63: 1738.9 | D63: 1719.4 | E63: 1734.6 | F63: 1735.7 | G63: 1731.49 | H63: 1,14,47,956 | I63: 19,82,20,46,508.90 | J63: 2,77,300 | K63: =(F63-F62)/F62 -> 0.00063415197 | L63: -0.0055667736 | M63: =VALUE(SUBSTITUTE(H63,",","")) -> 11447956
A64: 45597 | B64: 1733 | C64: 1744.1 | D64: 1726.1 | E64: 1735.7 | F64: 1737.3 | G64: 1738.79 | H64: 8,79,846 | I64: 1,52,98,70,165.60 | J64: 69860 | K64: =(F64-F63)/F63 -> 0.00092181829 | L64: 0.0040900049 | M64: =VALUE(SUBSTITUTE(H64,",","")) -> 879846
A65: 45600 | B65: 1745 | C65: 1745 | D65: 1710.9 | E65: 1737.3 | F65: 1714.1 | G65: 1723.47 | H65: 1,40,44,624 | I65: 24,20,55,13,156.95 | J65: 3,42,162 | K65: =(F65-F64)/F64 -> -0.013354055 | L65: -0.012713773 | M65: =VALUE(SUBSTITUTE(H65,",","")) -> 14044624
A66: 45601 | B66: 1703 | C66: 1762.7 | D66: 1697.9 | E66: 1714.1 | F66: 1757.85 | G66: 1736.4 | H66: 2,21,16,203 | I66: 38,40,25,43,188.05 | J66: 3,62,395 | K66: =(F66-F65)/F65 -> 0.025523598 | L66: 0.0090830098 | M66: =VALUE(SUBSTITUTE(H66,",","")) -> 22116203
A67: 45602 | B67: 1771.5 | C67: 1771.5 | D67: 1745.35 | E67: 1757.85 | F67: 1755.25 | G67: 1753.58 | H67: 1,38,93,955 | I67: 24,36,42,01,740.05 | J67: 2,49,677 | K67: =(F67-F66)/F66 -> -0.0014790796 | L67: 0.011181871 | M67: =VALUE(SUBSTITUTE(H67,",","")) -> 13893955
A68: 45603 | B68: 1744.3 | C68: 1760.95 | D68: 1738 | E68: 1755.25 | F68: 1746.55 | G68: 1746.6 | H68: 94,47,728 | I68: 16,50,13,84,112.80 | J68: 3,15,964 | K68: =(F68-F67)/F67 -> -0.0049565589 | L68: -0.011627978 | M68: =VALUE(SUBSTITUTE(H68,",","")) -> 9447728
A69: 45604 | B69: 1752 | C69: 1761.8 | D69: 1745.85 | E69: 1746.55 | F69: 1754.45 | G69: 1754.62 | H69: 99,51,493 | I69: 17,46,10,70,459.45 | J69: 2,53,333 | K69: =(F69-F68)/F68 -> 0.0045232029 | L69: -0.0021136931 | M69: =VALUE(SUBSTITUTE(H69,",","")) -> 9951493
A70: 45607 | B70: 1754.55 | C70: 1782.8 | D70: 1751.2 | E70: 1754.45 | F70: 1766.3 | G70: 1768.85 | H70: 1,22,82,681 | I70: 21,72,62,35,735.65 | J70: 3,66,875 | K70: =(F70-F69)/F69 -> 0.0067542535 | L70: -0.00028573558 | M70: =VALUE(SUBSTITUTE(H70,",","")) -> 12282681
A71: 45608 | B71: 1772 | C71: 1775 | D71: 1708.65 | E71: 1766.3 | F71: 1718.2 | G71: 1731.71 | H71: 1,56,97,703 | I71: 27,18,38,31,491.15 | J71: 4,10,691 | K71: =(F71-F70)/F70 -> -0.027232067 | L71: -0.010680866 | M71: =VALUE(SUBSTITUTE(H71,",","")) -> 15697703
A72: 45609 | B72: 1716.75 | C72: 1729.4 | D72: 1673 | E72: 1718.2 | F72: 1681.35 | G72: 1699.7 | H72: 1,78,64,250 | I72: 30,36,39,47,641.30 | J72: 3,84,592 | K72: =(F72-F71)/F71 -> -0.021446863 | L72: -0.013582627 | M72: =VALUE(SUBSTITUTE(H72,",","")) -> 17864250
A73: 45610 | B73: 1673.1 | C73: 1704.85 | D73: 1672.1 | E73: 1681.35 | F73: 1692.75 | G73: 1692.96 | H73: 1,35,73,235 | I73: 22,97,89,07,908.45 | J73: 3,31,159 | K73: =(F73-F72)/F72 -> 0.0067802659 | L73: -0.0011184662 | M73: =VALUE(SUBSTITUTE(H73,",","")) -> 13573235
A74: 45614 | B74: 1700 | C74: 1718.9 | D74: 1695 | E74: 1692.75 | F74: 1705.1 | G74: 1707.94 | H74: 1,35,40,984 | I74: 23,12,71,23,855.10 | J74: 2,91,631 | K74: =(F74-F73)/F73 -> 0.0072958204 | L74: -0.0033527814 | M74: =VALUE(SUBSTITUTE(H74,",","")) -> 13540984
A75: 45615 | B75: 1714 | C75: 1753.75 | D75: 1702.7 | E75: 1705.1 | F75: 1742.25 | G75: 1739.1 | H75: 2,54,90,636 | I75: 44,33,08,62,947.85 | J75: 4,58,303 | K75: =(F75-F74)/F74 -> 0.021787578 | L75: 0.0027586148 | M75: =VALUE(SUBSTITUTE(H75,",","")) -> 25490636
A76: 45617 | B76: 1749.4 | C76: 1759 | D76: 1734.2 | E76: 1742.25 | F76: 1741.2 | G76: 1743.63 | H76: 1,78,58,256 | I76: 31,13,81,62,734.40 | J76: 3,68,837 | K76: =(F76-F75)/F75 -> -0.00060266896 | L76: -0.0071688245 | M76: =VALUE(SUBSTITUTE(H76,",","")) -> 17858256
... A126: 45688 | B126: 1687.25 | C126: 1704.7 | D126: 1683.95 | E126: 1691.5 | F126: 1698.75 | G126: 1696.52 | H126: 79,10,843 | I126: 13,42,08,73,179.40 | J126: 2,15,938 | K126: =(F126-F125)/F125 -> 0.0042861366 | L126: 0.011135723 | M126: =VALUE(SUBSTITUTE(H126,",","")) -> 7910843
A127: 45689 | B127: 1697.5 | C127: 1713 | D127: 1676.05 | E127: 1698.75 | F127: 1690.95 | G127: 1694.22 | H127: 27,93,764 | I127: 4,73,32,38,897.95 | J127: 88839 | K127: =(F127-F126)/F126 -> -0.0045916115 | L127: -0.0011166221 | M127: =VALUE(SUBSTITUTE(H127,",","")) -> 2793764
A128: 45691 | B128: 1670 | C128: 1686.8 | D128: 1663.45 | E128: 1690.95 | F128: 1678 | G128: 1679.49 | H128: 1,01,38,270 | I128: 17,02,70,93,333.70 | J128: 2,30,780 | K128: =(F128-F127)/F127 -> -0.0076584169 | L128: -0.0051571087 | M128: =VALUE(SUBSTITUTE(H128,",","")) -> 10138270
A129: 45692 | B129: 1688.7 | C129: 1725.8 | D129: 1680.05 | E129: 1678 | F129: 1720.9 | G129: 1710.93 | H129: 1,43,08,251 | I129: 24,48,03,95,914.25 | J129: 3,42,091 | K129: =(F129-F128)/F128 -> 0.02556615 | L129: 0.016189341 | M129: =VALUE(SUBSTITUTE(H129,",","")) -> 14308251
A130: 45693 | B130: 1733 | C130: 1744.2 | D130: 1718.9 | E130: 1720.9 | F130: 1737.8 | G130: 1733.84 | H130: 1,18,37,753 | I130: 20,52,47,85,237.35 | J130: 2,75,185 | K130: =(F130-F129)/F129 -> 0.0098204428 | L130: -0.00180924 | M130: =VALUE(SUBSTITUTE(H130,",","")) -> 11837753
A131: 45694 | B131: 1735.5 | C131: 1749 | D131: 1724 | E131: 1737.8 | F131: 1743.85 | G131: 1735.75 | H131: 1,33,80,358 | I131: 23,22,50,08,521.55 | J131: 2,25,108 | K131: =(F131-F130)/F130 -> 0.0034814133 | L131: -0.0039225533 | M131: =VALUE(SUBSTITUTE(H131,",","")) -> 13380358
A132: 45695 | B132: 1750 | C132: 1767 | D132: 1725 | E132: 1743.85 | F132: 1732.75 | G132: 1744.99 | H132: 1,17,54,800 | I132: 20,51,20,07,682.55 | J132: 3,26,327 | K132: =(F132-F131)/F131 -> -0.0063652264 | L132: -0.001838722 | M132: =VALUE(SUBSTITUTE(H132,",","")) -> 11754800
A133: 45698 | B133: 1717.3 | C133: 1723.45 | D133: 1708.5 | E133: 1732.75 | F133: 1715.75 | G133: 1715.57 | H133: 85,97,975 | I133: 14,75,03,90,095.15 | J133: 1,75,150 | K133: =(F133-F132)/F132 -> -0.0098109941 | L133: -0.00757005 | M133: =VALUE(SUBSTITUTE(H133,",","")) -> 8597975
A134: 45699 | B134: 1703 | C134: 1711 | D134: 1688.7 | E134: 1715.75 | F134: 1701.4 | G134: 1700.06 | H134: 1,13,62,352 | I134: 19,31,66,30,388.15 | J134: 1,82,730 | K134: =(F134-F133)/F133 -> -0.0083636893 | L134: -0.013249735 | M134: =VALUE(SUBSTITUTE(H134,",","")) -> 11362352
A135: 45700 | B135: 1693 | C135: 1712 | D135: 1681.2 | E135: 1701.4 | F135: 1706.8 | G135: 1696.59 | H135: 1,14,04,785 | I135: 19,34,92,71,431.55 | J135: 2,86,053 | K135: =(F135-F134)/F134 -> 0.0031738568 | L135: -0.0011507555 | M135: =VALUE(SUBSTITUTE(H135,",","")) -> 11404785
A136: 45701 | B136: 1699 | C136: 1714.25 | D136: 1693.55 | E136: 1706.8 | F136: 1697.7 | G136: 1702.88 | H136: 63,01,217 | I136: 10,73,02,16,799.15 | J136: 2,00,278 | K136: =(F136-F135)/F135 -> -0.0053316147 | L136: -0.00060099153 | M136: =VALUE(SUBSTITUTE(H136,",","")) -> 6301217
A137: 45702 | B137: 1701.9 | C137: 1701.9 | D137: 1680 | E137: 1697.7 | F137: 1694.85 | G137: 1690.46 | H137: 99,79,946 | I137: 16,87,06,60,139.45 | J137: 3,09,031 | K137: =(F137-F136)/F136 -> -0.0016787418 | L137: -0.0044352493 | M137: =VALUE(SUBSTITUTE(H137,",","")) -> 9979946
A138: 45705 | B138: 1685.2 | C138: 1720 | D138: 1681.25 | E138: 1694.85 | F138: 1717.35 | G138: 1702.14 | H138: 64,69,473 | I138: 11,01,19,75,039.00 | J138: 2,62,946 | K138: =(F138-F137)/F137 -> 0.013275511 | L138: 0.0013192756 | M138: =VALUE(SUBSTITUTE(H138,",","")) -> 6469473
A139: 45706 | B139: 1713.05 | C139: 1731.55 | D139: 1706.15 | E139: 1717.35 | F139: 1723.05 | G139: 1721.09 | H139: 81,75,455 | I139: 14,07,06,71,116.40 | J139: 3,22,226 | K139: =(F139-F138)/F138 -> 0.0033190672 | L139: -0.00061848037 | M139: =VALUE(SUBSTITUTE(H139,",","")) -> 8175455
... A303: 45950 | B303: 997 | C303: 1020 | D303: 997 | E303: 1002.55 | F303: 1002.95 | G303: 1005.08 | H303: 2,21,95,202 | I303: 22,30,79,32,790.70 | J303: 4,16,206 | K303: =(F303-F302)/F302 -> 0.00039898259 | L303: 0.0051847833 | M303: =VALUE(SUBSTITUTE(H303,",","")) -> 22195202
A304: 45951 | B304: 1006 | C304: 1010 | D304: 1004 | E304: 1002.95 | F304: 1007.7 | G304: 1008.15 | H304: 34,71,600 | I304: 3,49,99,06,215.35 | J304: 88749 | K304: =(F304-F303)/F303 -> 0.0047360287 | L304: 0.00098478707 | M304: =VALUE(SUBSTITUTE(H304,",","")) -> 3471600
A305: 45953 | B305: 1016 | C305: 1020.5 | D305: 1006 | E305: 1007.7 | F305: 1008.8 | G305: 1013.19 | H305: 4,35,26,526 | I305: 44,10,04,30,667.15 | J305: 5,18,216 | K305: =(F305-F304)/F304 -> 0.0010915947 | L305: 0.00088137742 | M305: =VALUE(SUBSTITUTE(H305,",","")) -> 43526526
A306: 45954 | B306: 1011 | C306: 1011.95 | D306: 991.3 | E306: 1008.8 | F306: 994.75 | G306: 999.4 | H306: 1,77,07,768 | I306: 17,69,70,89,817.30 | J306: 3,62,016 | K306: =(F306-F305)/F305 -> -0.013927439 | L306: -0.0037174506 | M306: =VALUE(SUBSTITUTE(H306,",","")) -> 17707768
A307: 45957 | B307: 996.5 | C307: 1009.05 | D307: 996.2 | E307: 994.75 | F307: 1002.95 | G307: 1003.92 | H307: 1,57,00,796 | I307: 15,76,22,65,430.25 | J307: 2,97,938 | K307: =(F307-F306)/F306 -> 0.0082432772 | L307: 0.0066252765 | M307: =VALUE(SUBSTITUTE(H307,",","")) -> 15700796
A308: 45958 | B308: 997.65 | C308: 1008 | D308: 995 | E308: 1002.95 | F308: 1003.55 | G308: 1001.18 | H308: 3,39,04,289 | I308: 33,94,41,77,651.40 | J308: 4,23,621 | K308: =(F308-F307)/F307 -> 0.00059823521 | L308: -0.001149578 | M308: =VALUE(SUBSTITUTE(H308,",","")) -> 33904289
A309: 45959 | B309: 1004.9 | C309: 1012.5 | D309: 1000 | E309: 1003.55 | F309: 1007.85 | G309: 1007.89 | H309: 1,77,69,445 | I309: 17,90,96,76,109.65 | J309: 2,81,715 | K309: =(F309-F308)/F308 -> 0.004284789 | L309: 0.0045380588 | M309: =VALUE(SUBSTITUTE(H309,",","")) -> 17769445
A310: 45960 | B310: 1000 | C310: 1009.5 | D310: 997.1 | E310: 1007.85 | F310: 998.15 | G310: 1001.53 | H310: 1,99,62,917 | I310: 19,99,35,06,579.25 | J310: 3,65,104 | K310: =(F310-F309)/F309 -> -0.0096244481 | L310: -0.0067571458 | M310: =VALUE(SUBSTITUTE(H310,",","")) -> 19962917
A311: 45961 | B311: 994 | C311: 1004.45 | D311: 981.15 | E311: 998.15 | F311: 987.3 | G311: 989.37 | H311: 2,32,21,330 | I311: 22,97,45,58,984.15 | J311: 4,54,775 | K311: =(F311-F310)/F310 -> -0.01087011 | L311: -0.0060186607 | M311: =VALUE(SUBSTITUTE(H311,",","")) -> 23221330
A312: 45964 | B312: 985 | C312: 994.55 | D312: 983.3 | E312: 987.3 | F312: 992.65 | G312: 991.15 | H312: 1,66,07,180 | I312: 16,46,02,36,700.55 | J312: 2,88,032 | K312: =(F312-F311)/F311 -> 0.005418819 | L312: 0.0016036793 | M312: =VALUE(SUBSTITUTE(H312,",","")) -> 16607180
A313: 45965 | B313: 987 | C313: 997 | D313: 983.7 | E313: 992.65 | F313: 985.25 | G313: 990.21 | H313: 2,00,24,544 | I313: 19,82,85,27,608.75 | J313: 3,02,828 | K313: =(F313-F312)/F312 -> -0.0074547927 | L313: -0.006431617 | M313: =VALUE(SUBSTITUTE(H313,",","")) -> 20024544
A314: 45967 | B314: 981 | C314: 991.05 | D314: 974 | E314: 985.25 | F314: 984.65 | G314: 984.48 | H314: 2,22,79,516 | I314: 21,93,38,18,395.90 | J314: 2,78,532 | K314: =(F314-F313)/F313 -> -0.00060898249 | L314: -0.0034358623 | M314: =VALUE(SUBSTITUTE(H314,",","")) -> 22279516
A315: 45968 | B315: 980 | C315: 984.9 | D315: 974.75 | E315: 984.65 | F315: 982.3 | G315: 979.96 | H315: 1,50,04,568 | I315: 14,70,38,32,279.80 | J315: 3,15,369 | K315: =(F315-F314)/F314 -> -0.0023866348 | L315: -0.00068209348 | M315: =VALUE(SUBSTITUTE(H315,",","")) -> 15004568
A316: 45971 | B316: 982.3 | C316: 990.95 | D316: 980.2 | E316: 982.3 | F316: 984.5 | G316: 986.19 | H316: 1,59,88,262 | I316: 15,76,73,86,584.00 | J316: 3,73,004 | K316: =(F316-F315)/F315 -> 0.0022396417 | L316: 0.003218619 | M316: =VALUE(SUBSTITUTE(H316,",","")) -> 15988262
... A496: 46237 | B496: 753.05 | C496: 756.85 | D496: 750.05 | E496: 748.15 | F496: 753 | G496: 752.96 | H496: 1,48,27,841 | I496: 11,16,47,88,358.50 | J496: 3,92,396 | K496: =(F496-F495)/F495 -> 0.0064826572 | L496: 0.016023065 | M496: =VALUE(SUBSTITUTE(H496,",","")) -> 14827841

Sheet ICICIBANK
A1: DATE | B1: OPEN | C1: HIGH | D1: LOW | E1: PREV. CLOSE | F1: CLOSE | G1: VWAP | H1: VOLUME | I1: VALUE | J1: NO. OF TRADES | K1: DAILY RETURN | L1: NIFTY RETURN
A2: 45509 | B2: 1182 | C2: 1188.9 | D2: 1167 | E2: 1196.55 | F2: 1172.6 | G2: 1173.69 | H2: 1,43,06,771 | I2: 16,79,16,69,195.40 | J2: 3,03,083 | M2: =VALUE(SUBSTITUTE(H2,",","")) -> 14306771
A3: 45510 | B3: 1175 | C3: 1187.7 | D3: 1161.5 | E3: 1172.6 | F3: 1166.85 | G3: 1169.06 | H3: 1,35,75,619 | I3: 15,87,07,78,423.20 | J3: 2,69,178 | K3: =(F3-F2)/F2 -> -0.004903633 | L3: -0.0026210113 | M3: =VALUE(SUBSTITUTE(H3,",","")) -> 13575619
A4: 45511 | B4: 1178.95 | C4: 1179.8 | D4: 1161.6 | E4: 1166.85 | F4: 1172.45 | G4: 1170.37 | H4: 1,57,53,644 | I4: 18,43,75,24,153.20 | J4: 2,68,848 | K4: =(F4-F3)/F3 -> 0.0047992458 | L4: 0.012710195 | M4: =VALUE(SUBSTITUTE(H4,",","")) -> 15753644
A5: 45512 | B5: 1166.95 | C5: 1174.4 | D5: 1158.9 | E5: 1172.45 | F5: 1164.6 | G5: 1166.37 | H5: 1,08,06,438 | I5: 12,60,42,62,739.90 | J5: 2,40,108 | K5: =(F5-F4)/F4 -> -0.0066953815 | L5: -0.0074287478 | M5: =VALUE(SUBSTITUTE(H5,",","")) -> 10806438
A6: 45513 | B6: 1176.55 | C6: 1180.95 | D6: 1169 | E6: 1164.6 | F6: 1171.6 | G6: 1173.65 | H6: 86,87,307 | I6: 10,19,58,33,284.65 | J6: 1,61,291 | K6: =(F6-F5)/F5 -> 0.0060106474 | L6: 0.010386864 | M6: =VALUE(SUBSTITUTE(H6,",","")) -> 8687307
A7: 45516 | B7: 1171 | C7: 1178.25 | D7: 1156 | E7: 1171.6 | F7: 1172.8 | G7: 1170.54 | H7: 1,08,60,455 | I7: 12,71,26,20,911.40 | J7: 2,06,013 | K7: =(F7-F6)/F6 -> 0.0010242404 | L7: -0.0008412845 | M7: =VALUE(SUBSTITUTE(H7,",","")) -> 10860455
A8: 45517 | B8: 1183.2 | C8: 1189.25 | D8: 1163.6 | E8: 1172.8 | F8: 1168.35 | G8: 1172.48 | H8: 1,31,17,927 | I8: 15,38,04,95,808.30 | J8: 2,60,022 | K8: =(F8-F7)/F7 -> -0.0037943383 | L8: -0.008543147 | M8: =VALUE(SUBSTITUTE(H8,",","")) -> 13117927
A9: 45518 | B9: 1167 | C9: 1170.05 | D9: 1153 | E9: 1168.35 | F9: 1161.65 | G9: 1159.56 | H9: 1,34,31,801 | I9: 15,57,50,00,780.50 | J9: 2,32,399 | K9: =(F9-F8)/F8 -> -0.005734583 | L9: 0.000196777 | M9: =VALUE(SUBSTITUTE(H9,",","")) -> 13431801
A10: 45520 | B10: 1170 | C10: 1193 | D10: 1165.65 | E10: 1161.65 | F10: 1187.25 | G10: 1181.45 | H10: 1,09,61,370 | I10: 12,95,03,02,290.60 | J10: 2,33,289 | K10: =(F10-F9)/F9 -> 0.022037619 | L10: 0.016459746 | M10: =VALUE(SUBSTITUTE(H10,",","")) -> 10961370
A11: 45523 | B11: 1191 | C11: 1195.75 | D11: 1173.3 | E11: 1187.25 | F11: 1175.9 | G11: 1181.33 | H11: 66,86,394 | I11: 7,89,88,45,446.25 | J11: 1,23,110 | K11: =(F11-F10)/F10 -> -0.0095599073 | L11: 0.0012835584 | M11: =VALUE(SUBSTITUTE(H11,",","")) -> 6686394
A12: 45524 | B12: 1174.2 | C12: 1189.8 | D12: 1170 | E12: 1175.9 | F12: 1179.45 | G12: 1181.26 | H12: 1,04,27,061 | I12: 12,31,71,05,974.95 | J12: 1,79,266 | K12: =(F12-F11)/F11 -> 0.0030189642 | L12: 0.0051357912 | M12: =VALUE(SUBSTITUTE(H12,",","")) -> 10427061
A13: 45525 | B13: 1177 | C13: 1178.65 | D13: 1165.1 | E13: 1179.45 | F13: 1174.85 | G13: 1172.27 | H13: 1,72,34,142 | I13: 20,20,31,11,541.65 | J13: 2,32,318 | K13: =(F13-F12)/F12 -> -0.0039001229 | L13: 0.0028887985 | M13: =VALUE(SUBSTITUTE(H13,",","")) -> 17234142
A14: 45526 | B14: 1182 | C14: 1192.6 | D14: 1176.6 | E14: 1174.85 | F14: 1191.1 | G14: 1187.45 | H14: 85,64,142 | I14: 10,16,94,62,494.05 | J14: 2,48,029 | K14: =(F14-F13)/F13 -> 0.013831553 | L14: 0.0016673261 | M14: =VALUE(SUBSTITUTE(H14,",","")) -> 8564142
... A63: 45596 | B63: 1307.25 | C63: 1318.95 | D63: 1288.55 | E63: 1312.15 | F63: 1292.25 | G63: 1296.28 | H63: 2,34,97,314 | I63: 30,45,90,66,088.40 | J63: 2,50,950 | K63: =(F63-F62)/F62 -> -0.015165949 | L63: -0.0055667736 | M63: =VALUE(SUBSTITUTE(H63,",","")) -> 23497314
A64: 45597 | B64: 1289.95 | C64: 1296.2 | D64: 1286.25 | E64: 1292.25 | F64: 1291.8 | G64: 1292.11 | H64: 10,07,022 | I64: 1,30,11,80,367.65 | J64: 40161 | K64: =(F64-F63)/F63 -> -0.00034822983 | L64: 0.0040900049 | M64: =VALUE(SUBSTITUTE(H64,",","")) -> 1007022
A65: 45600 | B65: 1290.1 | C65: 1291.8 | D65: 1270.05 | E65: 1291.8 | F65: 1277.2 | G65: 1276.5 | H65: 1,43,09,121 | I65: 18,26,56,49,923.80 | J65: 2,68,956 | K65: =(F65-F64)/F64 -> -0.011302059 | L65: -0.012713773 | M65: =VALUE(SUBSTITUTE(H65,",","")) -> 14309121
A66: 45601 | B66: 1273 | C66: 1301.3 | D66: 1263.1 | E66: 1277.2 | F66: 1296.7 | G66: 1284.33 | H66: 1,64,31,920 | I66: 21,10,40,80,468.90 | J66: 2,62,702 | K66: =(F66-F65)/F65 -> 0.015267773 | L66: 0.0090830098 | M66: =VALUE(SUBSTITUTE(H66,",","")) -> 16431920
A67: 45602 | B67: 1300.25 | C67: 1315 | D67: 1292.7 | E67: 1296.7 | F67: 1302.35 | G67: 1306.97 | H67: 1,20,37,405 | I67: 15,73,25,82,044.35 | J67: 2,01,411 | K67: =(F67-F66)/F66 -> 0.0043572145 | L67: 0.011181871 | M67: =VALUE(SUBSTITUTE(H67,",","")) -> 12037405
A68: 45603 | B68: 1297.15 | C68: 1302.8 | D68: 1275.25 | E68: 1302.35 | F68: 1278.7 | G68: 1282.48 | H68: 99,09,035 | I68: 12,70,81,18,911.40 | J68: 1,85,720 | K68: =(F68-F67)/F67 -> -0.018159481 | L68: -0.011627978 | M68: =VALUE(SUBSTITUTE(H68,",","")) -> 9909035
A69: 45604 | B69: 1270 | C69: 1275 | D69: 1252.7 | E69: 1278.7 | F69: 1258.85 | G69: 1260.33 | H69: 1,11,95,808 | I69: 14,11,04,19,237.85 | J69: 2,33,807 | K69: =(F69-F68)/F68 -> -0.015523579 | L69: -0.0021136931 | M69: =VALUE(SUBSTITUTE(H69,",","")) -> 11195808
A70: 45607 | B70: 1262 | C70: 1275.9 | D70: 1246.65 | E70: 1258.85 | F70: 1269.3 | G70: 1266.04 | H70: 83,87,780 | I70: 10,61,92,76,125.00 | J70: 1,93,310 | K70: =(F70-F69)/F69 -> 0.0083012273 | L70: -0.00028573558 | M70: =VALUE(SUBSTITUTE(H70,",","")) -> 8387780
A71: 45608 | B71: 1276.15 | C71: 1295 | D71: 1264.5 | E71: 1269.3 | F71: 1270.6 | G71: 1276.01 | H71: 1,34,86,168 | I71: 17,20,84,86,809.70 | J71: 2,51,685 | K71: =(F71-F70)/F70 -> 0.0010241866 | L71: -0.010680866 | M71: =VALUE(SUBSTITUTE(H71,",","")) -> 13486168
A72: 45609 | B72: 1270.6 | C72: 1276.25 | D72: 1250 | E72: 1270.6 | F72: 1253.7 | G72: 1261.05 | H72: 1,22,60,404 | I72: 15,46,09,65,858.00 | J72: 2,58,070 | K72: =(F72-F71)/F71 -> -0.013300803 | L72: -0.013582627 | M72: =VALUE(SUBSTITUTE(H72,",","")) -> 12260404
A73: 45610 | B73: 1253.75 | C73: 1267.7 | D73: 1243.05 | E73: 1253.7 | F73: 1256.95 | G73: 1255.26 | H73: 95,06,892 | I73: 11,93,35,98,279.70 | J73: 2,24,597 | K73: =(F73-F72)/F72 -> 0.0025923267 | L73: -0.0011184662 | M73: =VALUE(SUBSTITUTE(H73,",","")) -> 9506892
A74: 45614 | B74: 1260 | C74: 1262.6 | D74: 1249.4 | E74: 1256.95 | F74: 1253.45 | G74: 1254.62 | H74: 61,95,554 | I74: 7,77,30,53,428.25 | J74: 2,04,301 | K74: =(F74-F73)/F73 -> -0.0027845181 | L74: -0.0033527814 | M74: =VALUE(SUBSTITUTE(H74,",","")) -> 6195554
A75: 45615 | B75: 1257.05 | C75: 1261 | D75: 1240.85 | E75: 1253.45 | F75: 1249.1 | G75: 1251.54 | H75: 1,15,37,317 | I75: 14,43,94,01,407.20 | J75: 2,33,269 | K75: =(F75-F74)/F74 -> -0.0034704216 | L75: 0.0027586148 | M75: =VALUE(SUBSTITUTE(H75,",","")) -> 11537317
A76: 45617 | B76: 1248.55 | C76: 1256.9 | D76: 1232.55 | E76: 1249.1 | F76: 1250.55 | G76: 1247.38 | H76: 95,93,870 | I76: 11,96,71,89,179.00 | J76: 2,09,109 | K76: =(F76-F75)/F75 -> 0.0011608358 | L76: -0.0071688245 | M76: =VALUE(SUBSTITUTE(H76,",","")) -> 9593870
... A126: 45688 | B126: 1254.5 | C126: 1256 | D126: 1239.1 | E126: 1255.6 | F126: 1252.8 | G126: 1247.43 | H126: 1,01,95,417 | I126: 12,71,80,79,791.90 | J126: 2,09,906 | K126: =(F126-F125)/F125 -> -0.0022300096 | L126: 0.011135723 | M126: =VALUE(SUBSTITUTE(H126,",","")) -> 10195417
A127: 45689 | B127: 1251.15 | C127: 1261.35 | D127: 1233.8 | E127: 1252.8 | F127: 1255.55 | G127: 1250.34 | H127: 30,11,914 | I127: 3,76,59,27,780.55 | J127: 91971 | K127: =(F127-F126)/F126 -> 0.002195083 | L127: -0.0011166221 | M127: =VALUE(SUBSTITUTE(H127,",","")) -> 3011914
A128: 45691 | B128: 1246.85 | C128: 1260 | D128: 1237.8 | E128: 1255.55 | F128: 1253 | G128: 1250.06 | H128: 61,76,831 | I128: 7,72,14,38,599.85 | J128: 1,65,087 | K128: =(F128-F127)/F127 -> -0.0020309824 | L128: -0.0051571087 | M128: =VALUE(SUBSTITUTE(H128,",","")) -> 6176831
A129: 45692 | B129: 1262.8 | C129: 1280.5 | D129: 1260 | E129: 1253 | F129: 1268.2 | G129: 1270.45 | H129: 1,48,39,077 | I129: 18,85,23,69,674.65 | J129: 2,59,371 | K129: =(F129-F128)/F128 -> 0.012130886 | L129: 0.016189341 | M129: =VALUE(SUBSTITUTE(H129,",","")) -> 14839077
A130: 45693 | B130: 1270.2 | C130: 1277.75 | D130: 1265.15 | E130: 1268.2 | F130: 1267.7 | G130: 1270.65 | H130: 68,40,709 | I130: 8,69,21,68,613.10 | J130: 1,83,398 | K130: =(F130-F129)/F129 -> -0.00039425958 | L130: -0.00180924 | M130: =VALUE(SUBSTITUTE(H130,",","")) -> 6840709
A131: 45694 | B131: 1275 | C131: 1279 | D131: 1263.2 | E131: 1267.7 | F131: 1272.4 | G131: 1270.57 | H131: 83,96,554 | I131: 10,66,84,40,486.05 | J131: 2,26,596 | K131: =(F131-F130)/F130 -> 0.0037075018 | L131: -0.0039225533 | M131: =VALUE(SUBSTITUTE(H131,",","")) -> 8396554
A132: 45695 | B132: 1272 | C132: 1275 | D132: 1249.55 | E132: 1272.4 | F132: 1256.9 | G132: 1258.99 | H132: 73,82,039 | I132: 9,29,38,77,445.05 | J132: 1,91,355 | K132: =(F132-F131)/F131 -> -0.012181704 | L132: -0.001838722 | M132: =VALUE(SUBSTITUTE(H132,",","")) -> 7382039
A133: 45698 | B133: 1257.2 | C133: 1265 | D133: 1249.35 | E133: 1256.9 | F133: 1262.6 | G133: 1257.56 | H133: 57,40,361 | I133: 7,21,88,36,541.20 | J133: 1,80,650 | K133: =(F133-F132)/F132 -> 0.004534967 | L133: -0.00757005 | M133: =VALUE(SUBSTITUTE(H133,",","")) -> 5740361
A134: 45699 | B134: 1255.85 | C134: 1261.85 | D134: 1248.4 | E134: 1262.6 | F134: 1252.75 | G134: 1254.67 | H134: 65,86,627 | I134: 8,26,40,43,638.70 | J134: 1,74,408 | K134: =(F134-F133)/F133 -> -0.0078013623 | L134: -0.013249735 | M134: =VALUE(SUBSTITUTE(H134,",","")) -> 6586627
A135: 45700 | B135: 1257.2 | C135: 1269.75 | D135: 1244.65 | E135: 1252.75 | F135: 1251.8 | G135: 1252.33 | H135: 88,09,352 | I135: 11,03,22,00,057.65 | J135: 3,20,587 | K135: =(F135-F134)/F134 -> -0.00075833167 | L135: -0.0011507555 | M135: =VALUE(SUBSTITUTE(H135,",","")) -> 8809352
A136: 45701 | B136: 1252.55 | C136: 1266 | D136: 1245.9 | E136: 1251.8 | F136: 1248.9 | G136: 1254.61 | H136: 72,63,785 | I136: 9,11,32,47,793.40 | J136: 2,61,567 | K136: =(F136-F135)/F135 -> -0.002316664 | L136: -0.00060099153 | M136: =VALUE(SUBSTITUTE(H136,",","")) -> 7263785
A137: 45702 | B137: 1252.1 | C137: 1263.5 | D137: 1244.45 | E137: 1248.9 | F137: 1260.1 | G137: 1254.48 | H137: 1,03,68,438 | I137: 13,00,69,59,974.75 | J137: 2,89,728 | K137: =(F137-F136)/F136 -> 0.0089678917 | L137: -0.0044352493 | M137: =VALUE(SUBSTITUTE(H137,",","")) -> 10368438
A138: 45705 | B138: 1251.15 | C138: 1258.15 | D138: 1233.25 | E138: 1260.1 | F138: 1251.15 | G138: 1244.89 | H138: 83,86,151 | I138: 10,43,98,44,806.35 | J138: 2,94,062 | K138: =(F138-F137)/F137 -> -0.0071026109 | L138: 0.0013192756 | M138: =VALUE(SUBSTITUTE(H138,",","")) -> 8386151
A139: 45706 | B139: 1252.9 | C139: 1257.6 | D139: 1237.05 | E139: 1251.15 | F139: 1243.05 | G139: 1242.37 | H139: 81,35,042 | I139: 10,10,67,08,536.60 | J139: 2,57,996 | K139: =(F139-F138)/F138 -> -0.0064740439 | L139: -0.00061848037 | M139: =VALUE(SUBSTITUTE(H139,",","")) -> 8135042
... A215: 45821 | B215: 1403.6 | C215: 1421.5 | D215: 1403.6 | E215: 1425.2 | F215: 1416.1 | G215: 1413.67 | H215: 75,73,103 | I215: 10,70,58,43,818.30 | J215: 1,88,584 | K215: =(F215-F214)/F214 -> -0.0063850688 | L215: -0.0068144743 | M215: =VALUE(SUBSTITUTE(H215,",","")) -> 7573103
A216: 45824 | B216: 1416.6 | C216: 1429 | D216: 1414.2 | E216: 1416.1 | F216: 1426.9 | G216: 1423.44 | H216: 54,51,137 | I216: 7,75,93,40,748.40 | J216: 89237 | K216: =(F216-F215)/F215 -> 0.00762658 | L216: 0.0092197778 | M216: =VALUE(SUBSTITUTE(H216,",","")) -> 5451137
A217: 45825 | B217: 1426.9 | C217: 1429.8 | D217: 1417.8 | E217: 1426.9 | F217: 1423.2 | G217: 1423.27 | H217: 69,70,098 | I217: 9,92,02,98,395.00 | J217: 1,93,761 | K217: =(F217-F216)/F216 -> -0.0025930338 | L217: -0.0037319865 | M217: =VALUE(SUBSTITUTE(H217,",","")) -> 6970098
A218: 45826 | B218: 1417 | C218: 1432 | D218: 1410.2 | E218: 1423.2 | F218: 1412.6 | G218: 1415.55 | H218: 67,51,745 | I218: 9,55,74,44,212.10 | J218: 1,62,388 | K218: =(F218-F217)/F217 -> -0.0074480045 | L218: -0.0016637563 | M218: =VALUE(SUBSTITUTE(H218,",","")) -> 6751745
A219: 45827 | B219: 1408 | C219: 1414.7 | D219: 1404.7 | E219: 1412.6 | F219: 1411.3 | G219: 1409.62 | H219: 88,49,883 | I219: 12,47,49,98,015.50 | J219: 3,42,983 | K219: =(F219-F218)/F218 -> -0.00092028883 | L219: -0.00075769636 | M219: =VALUE(SUBSTITUTE(H219,",","")) -> 8849883
A220: 45828 | B220: 1411.3 | C220: 1433.3 | D220: 1410.2 | E220: 1411.3 | F220: 1427.1 | G220: 1426.55 | H220: 1,24,08,178 | I220: 17,70,08,87,653.80 | J220: 1,60,865 | K220: =(F220-F219)/F219 -> 0.011195352 | L220: 0.012872455 | M220: =VALUE(SUBSTITUTE(H220,",","")) -> 12408178
A221: 45831 | B221: 1417 | C221: 1423.2 | D221: 1411.9 | E221: 1427.1 | F221: 1420.1 | G221: 1417.98 | H221: 55,14,384 | I221: 7,81,93,02,210.20 | J221: 1,60,229 | K221: =(F221-F220)/F220 -> -0.0049050522 | L221: -0.0055948456 | M221: =VALUE(SUBSTITUTE(H221,",","")) -> 5514384
A222: 45832 | B222: 1427.7 | C222: 1435.9 | D222: 1416.5 | E222: 1420.1 | F222: 1424.1 | G222: 1425.61 | H222: 1,11,88,438 | I222: 15,95,03,52,718.80 | J222: 1,88,014 | K222: =(F222-F221)/F221 -> 0.002816703 | L222: 0.002901261 | M222: =VALUE(SUBSTITUTE(H222,",","")) -> 11188438
A223: 45833 | B223: 1422 | C223: 1428.9 | D223: 1415.3 | E223: 1424.1 | F223: 1425.8 | G223: 1423.08 | H223: 75,27,388 | I223: 10,71,20,47,350.90 | J223: 1,47,548 | K223: =(F223-F222)/F222 -> 0.0011937364 | L223: 0.0080018048 | M223: =VALUE(SUBSTITUTE(H223,",","")) -> 7527388
A224: 45834 | B224: 1424.8 | C224: 1447.5 | D224: 1421.7 | E224: 1425.8 | F224: 1439.1 | G224: 1436.85 | H224: 1,36,17,435 | I224: 19,56,62,10,028.90 | J224: 2,20,490 | K224: =(F224-F223)/F223 -> 0.0093280965 | L224: 0.012052011 | M224: =VALUE(SUBSTITUTE(H224,",","")) -> 13617435
A225: 45835 | B225: 1438.9 | C225: 1466 | D225: 1437.1 | E225: 1439.1 | F225: 1462.2 | G225: 1457.56 | H225: 2,25,32,899 | I225: 32,84,30,85,618.20 | J225: 2,17,058 | K225: =(F225-F224)/F224 -> 0.016051699 | L225: 0.0034756742 | M225: =VALUE(SUBSTITUTE(H225,",","")) -> 22532899
A226: 45838 | B226: 1461.8 | C226: 1461.9 | D226: 1442.3 | E226: 1462.2 | F226: 1445.8 | G226: 1449.97 | H226: 63,25,073 | I226: 9,17,11,82,603.20 | J226: 1,87,773 | K226: =(F226-F225)/F225 -> -0.011215976 | L226: -0.0047098425 | M226: =VALUE(SUBSTITUTE(H226,",","")) -> 6325073
A227: 45839 | B227: 1445.7 | C227: 1447.6 | D227: 1429.6 | E227: 1445.8 | F227: 1432 | G227: 1435.52 | H227: 77,61,449 | I227: 11,14,17,35,649.70 | J227: 1,85,345 | K227: =(F227-F226)/F226 -> -0.0095448886 | L227: 0.00096993971 | M227: =VALUE(SUBSTITUTE(H227,",","")) -> 7761449
A228: 45840 | B228: 1432.2 | C228: 1451 | D228: 1422.6 | E228: 1432 | F228: 1427.8 | G228: 1430.58 | H228: 1,33,72,280 | I228: 19,13,01,57,807.70 | J228: 2,13,176 | K228: =(F228-F227)/F227 -> -0.0029329609 | L228: -0.0034609934 | M228: =VALUE(SUBSTITUTE(H228,",","")) -> 13372280
... A303: 45950 | B303: 1442 | C303: 1445 | D303: 1389.2 | E303: 1436.6 | F303: 1390.3 | G303: 1401.64 | H303: 2,33,30,227 | I303: 32,70,04,79,176.40 | J303: 6,70,783 | K303: =(F303-F302)/F302 -> -0.032228874 | L303: 0.0051847833 | M303: =VALUE(SUBSTITUTE(H303,",","")) -> 23330227
A304: 45951 | B304: 1384.5 | C304: 1387.6 | D304: 1375.9 | E304: 1390.3 | F304: 1382 | G304: 1383.19 | H304: 34,15,560 | I304: 4,72,43,55,077.40 | J304: 93955 | K304: =(F304-F303)/F303 -> -0.0059699345 | L304: 0.00098478707 | M304: =VALUE(SUBSTITUTE(H304,",","")) -> 3415560
A305: 45953 | B305: 1385 | C305: 1389.8 | D305: 1360.1 | E305: 1382 | F305: 1363.7 | G305: 1375.57 | H305: 2,11,24,942 | I305: 29,05,87,72,536.50 | J305: 4,01,439 | K305: =(F305-F304)/F304 -> -0.013241679 | L305: 0.00088137742 | M305: =VALUE(SUBSTITUTE(H305,",","")) -> 21124942
A306: 45954 | B306: 1368.1 | C306: 1381.6 | D306: 1368.1 | E306: 1363.7 | F306: 1377.7 | G306: 1376.15 | H306: 1,05,70,263 | I306: 14,54,62,56,446.30 | J306: 2,54,633 | K306: =(F306-F305)/F305 -> 0.010266188 | L306: -0.0037174506 | M306: =VALUE(SUBSTITUTE(H306,",","")) -> 10570263
A307: 45957 | B307: 1382.1 | C307: 1386.8 | D307: 1374 | E307: 1377.7 | F307: 1377.6 | G307: 1379.13 | H307: 1,14,99,836 | I307: 15,85,97,16,513.70 | J307: 2,96,317 | K307: =(F307-F306)/F306 -> -7.2584743e-05 | L307: 0.0066252765 | M307: =VALUE(SUBSTITUTE(H307,",","")) -> 11499836
A308: 45958 | B308: 1373 | C308: 1375.8 | D308: 1356.2 | E308: 1377.6 | F308: 1363.1 | G308: 1361.81 | H308: 2,64,77,914 | I308: 36,05,79,49,499.50 | J308: 4,80,704 | K308: =(F308-F307)/F307 -> -0.010525552 | L308: -0.001149578 | M308: =VALUE(SUBSTITUTE(H308,",","")) -> 26477914
A309: 45959 | B309: 1364.6 | C309: 1371.7 | D309: 1358.4 | E309: 1363.1 | F309: 1370.4 | G309: 1365.15 | H309: 1,61,29,382 | I309: 22,01,90,31,340.90 | J309: 3,53,776 | K309: =(F309-F308)/F308 -> 0.0053554398 | L309: 0.0045380588 | M309: =VALUE(SUBSTITUTE(H309,",","")) -> 16129382
A310: 45960 | B310: 1362.4 | C310: 1370.2 | D310: 1361.3 | E310: 1370.4 | F310: 1362.4 | G310: 1364.23 | H310: 93,24,401 | I310: 12,72,06,37,741.30 | J310: 3,01,933 | K310: =(F310-F309)/F309 -> -0.0058377116 | L310: -0.0067571458 | M310: =VALUE(SUBSTITUTE(H310,",","")) -> 9324401
A311: 45961 | B311: 1357 | C311: 1362 | D311: 1343.3 | E311: 1362.4 | F311: 1345.3 | G311: 1349.3 | H311: 1,59,26,798 | I311: 21,48,99,88,727.80 | J311: 3,09,384 | K311: =(F311-F310)/F310 -> -0.01255138 | L311: -0.0060186607 | M311: =VALUE(SUBSTITUTE(H311,",","")) -> 15926798
A312: 45964 | B312: 1340.5 | C312: 1351.6 | D312: 1337.9 | E312: 1345.3 | F312: 1346.4 | G312: 1344.89 | H312: 1,10,71,450 | I312: 14,88,99,21,391.00 | J312: 3,01,531 | K312: =(F312-F311)/F311 -> 0.00081766149 | L312: 0.0016036793 | M312: =VALUE(SUBSTITUTE(H312,",","")) -> 11071450
A313: 45965 | B313: 1342.6 | C313: 1349.8 | D313: 1333.2 | E313: 1346.4 | F313: 1336.9 | G313: 1337.49 | H313: 1,52,11,183 | I313: 20,34,48,38,007.00 | J313: 2,76,007 | K313: =(F313-F312)/F312 -> -0.0070558526 | L313: -0.006431617 | M313: =VALUE(SUBSTITUTE(H313,",","")) -> 15211183
A314: 45967 | B314: 1330 | C314: 1342.2 | D314: 1317.4 | E314: 1336.9 | F314: 1320.4 | G314: 1324.61 | H314: 2,42,21,853 | I314: 32,08,45,16,054.80 | J314: 3,68,806 | K314: =(F314-F313)/F313 -> -0.012341985 | L314: -0.0034358623 | M314: =VALUE(SUBSTITUTE(H314,",","")) -> 24221853
A315: 45968 | B315: 1320.4 | C315: 1344.3 | D315: 1318.6 | E315: 1320.4 | F315: 1343 | G315: 1337.7 | H315: 77,19,245 | I315: 10,32,60,29,497.00 | J315: 1,49,776 | K315: =(F315-F314)/F314 -> 0.017116025 | L315: -0.00068209348 | M315: =VALUE(SUBSTITUTE(H315,",","")) -> 7719245
A316: 45971 | B316: 1342.9 | C316: 1349.6 | D316: 1341 | E316: 1343 | F316: 1348 | G316: 1345.91 | H316: 85,42,340 | I316: 11,49,72,41,405.30 | J316: 1,55,442 | K316: =(F316-F315)/F315 -> 0.0037230082 | L316: 0.003218619 | M316: =VALUE(SUBSTITUTE(H316,",","")) -> 8542340
... A348: 46015 | B348: 1363.8 | C348: 1368.2 | D348: 1357.6 | E348: 1363 | F348: 1359.8 | G348: 1362.26 | H348: 89,55,140 | I348: 12,19,92,71,454.00 | J348: 1,63,168 | K348: =(F348-F347)/F347 -> -0.0023477623 | L348: -0.001338954 | M348: =VALUE(SUBSTITUTE(H348,",","")) -> 8955140
A349: 46017 | B349: 1356.5 | C349: 1362 | D349: 1348.5 | E349: 1359.8 | F349: 1350.4 | G349: 1353.25 | H349: 28,12,144 | I349: 3,80,55,33,190.00 | J349: 92194 | K349: =(F349-F348)/F348 -> -0.0069127813 | L349: -0.0038175969 | M349: =VALUE(SUBSTITUTE(H349,",","")) -> 2812144
A350: 46020 | B350: 1352.1 | C350: 1355.7 | D350: 1341.5 | E350: 1350.4 | F350: 1343.3 | G350: 1346.07 | H350: 60,57,201 | I350: 8,15,34,10,855.40 | J350: 1,45,962 | K350: =(F350-F349)/F349 -> -0.0052577014 | L350: -0.0038475864 | M350: =VALUE(SUBSTITUTE(H350,",","")) -> 6057201
A351: 46021 | B351: 1343.3 | C351: 1347.1 | D351: 1338.1 | E351: 1343.3 | F351: 1342.5 | G351: 1341.94 | H351: 1,86,21,277 | I351: 24,98,86,03,546.50 | J351: 2,61,375 | K351: =(F351-F350)/F350 -> -0.00059554828 | L351: -0.00012527899 | M351: =VALUE(SUBSTITUTE(H351,",","")) -> 18621277
A352: 46022 | B352: 1342.8 | C352: 1350 | D352: 1339.5 | E352: 1342.5 | F352: 1342.9 | G352: 1344.37 | H352: 61,50,634 | I352: 8,26,87,15,778.60 | J352: 1,33,779 | K352: =(F352-F351)/F351 -> 0.00029795158 | L352: 0.0073538341 | M352: =VALUE(SUBSTITUTE(H352,",","")) -> 6150634
A353: 46023 | B353: 1343.9 | C353: 1348.4 | D353: 1336 | E353: 1342.9 | F353: 1338 | G353: 1340.3 | H353: 41,79,311 | I353: 5,60,15,12,243.10 | J353: 92659 | K353: =(F353-F352)/F352 -> -0.0036488197 | L353: 0.00064868961 | M353: =VALUE(SUBSTITUTE(H353,",","")) -> 4179311
A354: 46024 | B354: 1338 | C354: 1356.9 | D354: 1336.3 | E354: 1338 | F354: 1355.4 | G354: 1348.97 | H354: 82,26,205 | I354: 11,09,68,63,710.80 | J354: 1,23,080 | K354: =(F354-F353)/F353 -> 0.013004484 | L354: 0.0069607654 | M354: =VALUE(SUBSTITUTE(H354,",","")) -> 8226205
A355: 46027 | B355: 1354.2 | C355: 1375.5 | D355: 1352.6 | E355: 1355.4 | F355: 1371.5 | G355: 1369.03 | H355: 69,20,565 | I355: 9,47,44,70,607.30 | J355: 2,51,280 | K355: =(F355-F354)/F354 -> 0.011878412 | L355: -0.0029720588 | M355: =VALUE(SUBSTITUTE(H355,",","")) -> 6920565
A356: 46028 | B356: 1372 | C356: 1413.6 | D356: 1366 | E356: 1371.5 | F356: 1411.2 | G356: 1404.16 | H356: 1,72,60,416 | I356: 24,23,63,60,970.10 | J356: 3,38,562 | K356: =(F356-F355)/F355 -> 0.028946409 | L356: -0.0027275879 | M356: =VALUE(SUBSTITUTE(H356,",","")) -> 17260416
A357: 46029 | B357: 1408 | C357: 1429.9 | D357: 1404.2 | E357: 1411.2 | F357: 1427.7 | G357: 1421.98 | H357: 1,58,13,795 | I357: 22,48,69,67,388.80 | J357: 2,63,196 | K357: =(F357-F356)/F356 -> 0.011692177 | L357: -0.0014496518 | M357: =VALUE(SUBSTITUTE(H357,",","")) -> 15813795
A358: 46030 | B358: 1429 | C358: 1442.2 | D358: 1423.3 | E358: 1427.7 | F358: 1435 | G358: 1435.94 | H358: 1,48,61,699 | I358: 21,34,04,84,627.50 | J358: 2,90,412 | K358: =(F358-F357)/F357 -> 0.005113119 | L358: -0.010095349 | M358: =VALUE(SUBSTITUTE(H358,",","")) -> 14861699
A359: 46031 | B359: 1427.1 | C359: 1429.5 | D359: 1401.5 | E359: 1435 | F359: 1404.3 | G359: 1407.82 | H359: 1,25,55,636 | I359: 17,67,60,64,959.30 | J359: 1,76,569 | K359: =(F359-F358)/F358 -> -0.021393728 | L359: -0.0074796585 | M359: =VALUE(SUBSTITUTE(H359,",","")) -> 12555636
A360: 46034 | B360: 1399.9 | C360: 1424.3 | D360: 1391.7 | E360: 1404.3 | F360: 1413.1 | G360: 1409.1 | H360: 1,09,23,811 | I360: 15,39,27,57,596.10 | J360: 2,13,429 | K360: =(F360-F359)/F359 -> 0.0062664673 | L360: 0.0041641845 | M360: =VALUE(SUBSTITUTE(H360,",","")) -> 10923811
A361: 46035 | B361: 1420 | C361: 1441.8 | D361: 1411.1 | E361: 1413.1 | F361: 1437 | G361: 1432.77 | H361: 1,42,95,581 | I361: 20,48,22,94,150.00 | J361: 3,24,654 | K361: =(F361-F360)/F360 -> 0.01691317 | L361: -0.0022469732 | M361: =VALUE(SUBSTITUTE(H361,",","")) -> 14295581
A362: 46036 | B362: 1425.6 | C362: 1443.9 | D362: 1414.9 | E362: 1437 | F362: 1418.4 | G362: 1425.59 | H362: 1,38,32,255 | I362: 19,71,90,79,329.90 | J362: 2,58,446 | K362: =(F362-F361)/F361 -> -0.012943633 | L362: -0.002592073 | M362: =VALUE(SUBSTITUTE(H362,",","")) -> 13832255
A363: 46038 | B363: 1417.9 | C363: 1429 | D363: 1400.2 | E363: 1418.4 | F363: 1410.8 | G363: 1413.4 | H363: 1,25,30,886 | I363: 17,71,11,65,102.70 | J363: 3,10,123 | K363: =(F363-F362)/F362 -> -0.00535815 | L363: 0.0011201764 | M363: =VALUE(SUBSTITUTE(H363,",","")) -> 12530886
A364: 46041 | B364: 1399.9 | C364: 1400 | D364: 1360 | E364: 1410.8 | F364: 1380.6 | G364: 1374.22 | H364: 2,33,02,883 | I364: 32,02,33,23,446.30 | J364: 4,43,246 | K364: =(F364-F363)/F363 -> -0.021406294 | L364: -0.0042363399 | M364: =VALUE(SUBSTITUTE(H364,",","")) -> 23302883
A365: 46042 | B365: 1374.7 | C365: 1387.8 | D365: 1371.5 | E365: 1380.6 | F365: 1375.8 | G365: 1380.38 | H365: 1,50,12,785 | I365: 20,72,33,99,138.70 | J365: 3,48,185 | K365: =(F365-F364)/F364 -> -0.0034767492 | L365: -0.013796877 | M365: =VALUE(SUBSTITUTE(H365,",","")) -> 15012785
... A372: 46052 | B372: 1368.2 | C372: 1381.9 | D372: 1353.2 | E372: 1383.6 | F372: 1355 | G372: 1365.39 | H372: 2,40,13,717 | I372: 32,78,80,49,343.30 | J372: 1,74,668 | K372: =(F372-F371)/F371 -> -0.020670714 | L372: -0.0038652341 | M372: =VALUE(SUBSTITUTE(H372,",","")) -> 24013717
A373: 46054 | B373: 1352 | C373: 1365.9 | D373: 1328.8 | E373: 1355 | F373: 1334.2 | G373: 1349.72 | H373: 49,69,610 | I373: 6,70,75,90,848.90 | J373: 73049 | K373: =(F373-F372)/F372 -> -0.015350554 | L373: -0.01955716 | M373: =VALUE(SUBSTITUTE(H373,",","")) -> 4969610
A374: 46055 | B374: 1329.9 | C374: 1354.4 | D374: 1329.1 | E374: 1334.2 | F374: 1352.8 | G374: 1345.43 | H374: 1,28,00,245 | I374: 17,22,18,71,131.70 | J374: 2,96,520 | K374: =(F374-F373)/F373 -> 0.013940938 | L374: 0.010591953 | M374: =VALUE(SUBSTITUTE(H374,",","")) -> 12800245
A375: 46056 | B375: 1412 | C375: 1417 | D375: 1373.4 | E375: 1352.8 | F375: 1389.7 | G375: 1391.76 | H375: 2,48,96,698 | I375: 34,65,02,22,974.70 | J375: 3,62,321 | K375: =(F375-F374)/F374 -> 0.027276759 | L375: 0.025475917 | M375: =VALUE(SUBSTITUTE(H375,",","")) -> 24896698
A376: 46057 | B376: 1387 | C376: 1414 | D376: 1386.9 | E376: 1389.7 | F376: 1408.4 | G376: 1406.84 | H376: 1,10,80,683 | I376: 15,58,87,50,561.40 | J376: 1,91,128 | K376: =(F376-F375)/F375 -> 0.013456142 | L376: 0.0018831953 | M376: =VALUE(SUBSTITUTE(H376,",","")) -> 11080683
A377: 46058 | B377: 1414 | C377: 1414 | D377: 1393.2 | E377: 1408.4 | F377: 1396.5 | G377: 1402.07 | H377: 89,82,761 | I377: 12,59,44,68,388.50 | J377: 1,79,749 | K377: =(F377-F376)/F376 -> -0.0084493042 | L377: -0.0051675978 | M377: =VALUE(SUBSTITUTE(H377,",","")) -> 8982761
A378: 46059 | B378: 1396.7 | C378: 1410.5 | D378: 1394.7 | E378: 1396.5 | F378: 1406.1 | G378: 1402.67 | H378: 1,08,51,190 | I378: 15,22,06,80,762.50 | J378: 1,67,764 | K378: =(F378-F377)/F377 -> 0.0068743287 | L378: 0.0019849626 | M378: =VALUE(SUBSTITUTE(H378,",","")) -> 10851190
A379: 46062 | B379: 1413.5 | C379: 1414 | D379: 1388.8 | E379: 1406.1 | F379: 1396.3 | G379: 1396.52 | H379: 78,89,742 | I379: 11,01,81,92,537.50 | J379: 2,01,425 | K379: =(F379-F378)/F378 -> -0.0069696323 | L379: 0.0067565201 | M379: =VALUE(SUBSTITUTE(H379,",","")) -> 7889742
A380: 46063 | B380: 1401 | C380: 1409.5 | D380: 1395.5 | E380: 1396.3 | F380: 1406.5 | G380: 1403.57 | H380: 1,64,97,628 | I380: 23,15,56,53,318.50 | J380: 2,90,456 | K380: =(F380-F379)/F379 -> 0.0073050204 | L380: 0.0026230028 | M380: =VALUE(SUBSTITUTE(H380,",","")) -> 16497628
A381: 46064 | B381: 1407.4 | C381: 1413 | D381: 1400.4 | E381: 1406.5 | F381: 1406.1 | G381: 1405.32 | H381: 85,51,341 | I381: 12,01,73,47,016.70 | J381: 2,33,720 | K381: =(F381-F380)/F380 -> -0.00028439389 | L381: 0.00072102918 | M381: =VALUE(SUBSTITUTE(H381,",","")) -> 8551341
A382: 46065 | B382: 1406.1 | C382: 1433 | D382: 1405.3 | E382: 1406.1 | F382: 1430 | G382: 1426.52 | H382: 1,96,46,265 | I382: 28,02,57,18,740.70 | J382: 3,59,078 | K382: =(F382-F381)/F381 -> 0.016997369 | L382: -0.0056504141 | M382: =VALUE(SUBSTITUTE(H382,",","")) -> 19646265
A383: 46066 | B383: 1425.3 | C383: 1434.4 | D383: 1410.7 | E383: 1430 | F383: 1414.6 | G383: 1417.7 | H383: 1,22,28,083 | I383: 17,33,58,09,677.40 | J383: 3,31,274 | K383: =(F383-F382)/F382 -> -0.010769231 | L383: -0.013023497 | M383: =VALUE(SUBSTITUTE(H383,",","")) -> 12228083
...

Sheet ITC
A1: DATE | B1: OPEN | C1: HIGH | D1: LOW | E1: PREV. CLOSE | F1: CLOSE | G1: VWAP | H1: VOLUME | I1: VALUE | J1: NO. OF TRADES | K1: DAILY RETURN | L1: NIFTY RETURN
A2: 45509 | B2: 480.05 | C2: 491.9 | D2: 479.55 | E2: 489.1 | F2: 486 | G2: 485.81 | H2: 2,40,94,139 | I2: 11,70,52,82,411.05 | J2: 2,40,878 | M2: =VALUE(SUBSTITUTE(H2,",","")) -> 24094139
A3: 45510 | B3: 486.25 | C3: 491.7 | D3: 484.05 | E3: 486 | F3: 486.3 | G3: 487.52 | H3: 1,37,22,855 | I3: 6,69,01,15,892.10 | J3: 1,65,576 | K3: =(F3-F2)/F2 -> 0.00061728395 | L3: -0.0026210113 | M3: =VALUE(SUBSTITUTE(H3,",","")) -> 13722855
A4: 45511 | B4: 490 | C4: 495.6 | D4: 488.1 | E4: 486.3 | F4: 492.65 | G4: 491.96 | H4: 1,09,00,585 | I4: 5,36,26,50,358.25 | J4: 1,73,490 | K4: =(F4-F3)/F3 -> 0.013057783 | L4: 0.012710195 | M4: =VALUE(SUBSTITUTE(H4,",","")) -> 10900585
A5: 45512 | B5: 494 | C5: 498 | D5: 492.5 | E5: 492.65 | F5: 494.75 | G5: 494.99 | H5: 2,05,58,134 | I5: 10,17,59,99,936.05 | J5: 2,50,724 | K5: =(F5-F4)/F4 -> 0.0042626611 | L5: -0.0074287478 | M5: =VALUE(SUBSTITUTE(H5,",","")) -> 20558134
A6: 45513 | B6: 498 | C6: 498 | D6: 493.1 | E6: 494.75 | F6: 495.9 | G6: 495.38 | H6: 92,01,793 | I6: 4,55,83,87,017.25 | J6: 1,44,367 | K6: =(F6-F5)/F5 -> 0.0023244063 | L6: 0.010386864 | M6: =VALUE(SUBSTITUTE(H6,",","")) -> 9201793
A7: 45516 | B7: 492 | C7: 500 | D7: 492 | E7: 495.9 | F7: 494.6 | G7: 497.04 | H7: 90,76,097 | I7: 4,51,11,89,537.95 | J7: 1,33,143 | K7: =(F7-F6)/F6 -> -0.0026214963 | L7: -0.0008412845 | M7: =VALUE(SUBSTITUTE(H7,",","")) -> 9076097
A8: 45517 | B8: 495.95 | C8: 497.85 | D8: 488.25 | E8: 494.6 | F8: 490 | G8: 493.29 | H8: 77,57,706 | I8: 3,82,67,62,550.05 | J8: 1,19,952 | K8: =(F8-F7)/F7 -> -0.0093004448 | L8: -0.008543147 | M8: =VALUE(SUBSTITUTE(H8,",","")) -> 7757706
A9: 45518 | B9: 491.95 | C9: 499 | D9: 489.9 | E9: 490 | F9: 492.2 | G9: 494.04 | H9: 92,53,598 | I9: 4,57,16,25,348.00 | J9: 1,50,643 | K9: =(F9-F8)/F8 -> 0.0044897959 | L9: 0.000196777 | M9: =VALUE(SUBSTITUTE(H9,",","")) -> 9253598
A10: 45520 | B10: 494.5 | C10: 504.2 | D10: 492.65 | E10: 492.2 | F10: 502.65 | G10: 498.53 | H10: 1,31,37,392 | I10: 6,54,94,43,406.85 | J10: 1,64,043 | K10: =(F10-F9)/F9 -> 0.021231207 | L10: 0.016459746 | M10: =VALUE(SUBSTITUTE(H10,",","")) -> 13137392
A11: 45523 | B11: 504.75 | C11: 509.3 | D11: 499.6 | E11: 502.65 | F11: 501.45 | G11: 504.39 | H11: 1,01,98,725 | I11: 5,14,41,20,039.10 | J11: 1,66,648 | K11: =(F11-F10)/F10 -> -0.0023873471 | L11: 0.0012835584 | M11: =VALUE(SUBSTITUTE(H11,",","")) -> 10198725
A12: 45524 | B12: 501 | C12: 503.4 | D12: 497.7 | E12: 501.45 | F12: 498.8 | G12: 499.95 | H12: 66,33,171 | I12: 3,31,62,78,832.00 | J12: 1,15,083 | K12: =(F12-F11)/F11 -> -0.0052846744 | L12: 0.0051357912 | M12: =VALUE(SUBSTITUTE(H12,",","")) -> 6633171
A13: 45525 | B13: 500 | C13: 509 | D13: 499.05 | E13: 498.8 | F13: 505.4 | G13: 505.03 | H13: 84,74,830 | I13: 4,28,00,48,280.45 | J13: 1,21,930 | K13: =(F13-F12)/F12 -> 0.013231756 | L13: 0.0028887985 | M13: =VALUE(SUBSTITUTE(H13,",","")) -> 8474830
A14: 45526 | B14: 507.85 | C14: 508.5 | D14: 501.45 | E14: 505.4 | F14: 504.55 | G14: 504.67 | H14: 83,64,290 | I14: 4,22,12,24,253.25 | J14: 1,45,029 | K14: =(F14-F13)/F13 -> -0.0016818362 | L14: 0.0016673261 | M14: =VALUE(SUBSTITUTE(H14,",","")) -> 8364290
... A30: 45548 | B30: 519.5 | C30: 520 | D30: 512 | E30: 519.5 | F30: 513.85 | G30: 513.81 | H30: 88,25,193 | I30: 4,53,44,84,027.05 | J30: 1,39,096 | K30: =(F30-F29)/F29 -> -0.010875842 | L30: -0.0012761482 | M30: =VALUE(SUBSTITUTE(H30,",","")) -> 8825193
A31: 45551 | B31: 515.9 | C31: 517 | D31: 509.7 | E31: 513.85 | F31: 511.1 | G31: 513.15 | H31: 75,31,604 | I31: 3,86,48,31,357.30 | J31: 80552 | K31: =(F31-F30)/F30 -> -0.0053517563 | L31: 0.0010746751 | M31: =VALUE(SUBSTITUTE(H31,",","")) -> 7531604
A32: 45552 | B32: 511.05 | C32: 513.55 | D32: 506.25 | E32: 511.1 | F32: 507.75 | G32: 508.55 | H32: 1,04,86,015 | I32: 5,33,26,81,431.45 | J32: 1,13,046 | K32: =(F32-F31)/F31 -> -0.0065544903 | L32: 0.0013709558 | M32: =VALUE(SUBSTITUTE(H32,",","")) -> 10486015
A33: 45553 | B33: 507.85 | C33: 512.4 | D33: 505.1 | E33: 507.75 | F33: 507.35 | G33: 509.15 | H33: 54,29,619 | I33: 2,76,45,06,352.10 | J33: 98908 | K33: =(F33-F32)/F32 -> -0.00078778927 | L33: -0.0016129952 | M33: =VALUE(SUBSTITUTE(H33,",","")) -> 5429619
A34: 45554 | B34: 510 | C34: 514.8 | D34: 507.5 | E34: 507.35 | F34: 508.25 | G34: 510.59 | H34: 1,39,25,311 | I34: 7,11,00,66,899.10 | J34: 2,26,927 | K34: =(F34-F33)/F33 -> 0.0017739233 | L34: 0.0015072377 | M34: =VALUE(SUBSTITUTE(H34,",","")) -> 13925311
A35: 45555 | B35: 512 | C35: 517.35 | D35: 508 | E35: 508.25 | F35: 514.4 | G35: 513.97 | H35: 2,38,08,194 | I35: 12,23,67,58,568.15 | J35: 2,31,527 | K35: =(F35-F34)/F34 -> 0.012100344 | L35: 0.014760503 | M35: =VALUE(SUBSTITUTE(H35,",","")) -> 23808194
A36: 45558 | B36: 515.45 | C36: 519.45 | D36: 513.6 | E36: 514.4 | F36: 516.95 | G36: 516.88 | H36: 78,04,918 | I36: 4,03,42,41,784.00 | J36: 1,30,984 | K36: =(F36-F35)/F35 -> 0.0049572317 | L36: 0.0057423243 | M36: =VALUE(SUBSTITUTE(H36,",","")) -> 7804918
A37: 45559 | B37: 517 | C37: 517.8 | D37: 514.15 | E37: 516.95 | F37: 515.25 | G37: 515.47 | H37: 67,55,320 | I37: 3,48,21,95,547.40 | J37: 1,21,014 | K37: =(F37-F36)/F36 -> -0.0032885192 | L37: 5.2045083e-05 | M37: =VALUE(SUBSTITUTE(H37,",","")) -> 6755320
A38: 45560 | B38: 515.5 | C38: 519.3 | D38: 512.3 | E38: 515.25 | F38: 517.55 | G38: 515.67 | H38: 84,76,223 | I38: 4,37,09,74,903.20 | J38: 1,55,236 | K38: =(F38-F37)/F37 -> 0.0044638525 | L38: 0.0024575566 | M38: =VALUE(SUBSTITUTE(H38,",","")) -> 8476223
A39: 45561 | B39: 517.65 | C39: 523.75 | D39: 517 | E39: 517.55 | F39: 522.75 | G39: 521.19 | H39: 1,54,89,991 | I39: 8,07,31,86,016.75 | J39: 2,03,237 | K39: =(F39-F38)/F38 -> 0.010047338 | L39: 0.0081486993 | M39: =VALUE(SUBSTITUTE(H39,",","")) -> 15489991
A40: 45562 | B40: 520.25 | C40: 528.5 | D40: 520.25 | E40: 522.75 | F40: 522.7 | G40: 524.14 | H40: 1,72,51,962 | I40: 9,04,23,61,720.15 | J40: 1,69,240 | K40: =(F40-F39)/F39 -> -9.5648015e-05 | L40: -0.0014151636 | M40: =VALUE(SUBSTITUTE(H40,",","")) -> 17251962
A41: 45565 | B41: 520.6 | C41: 524.35 | D41: 514.05 | E41: 522.7 | F41: 518.15 | G41: 518.56 | H41: 1,05,31,347 | I41: 5,46,11,48,445.10 | J41: 1,63,844 | K41: =(F41-F40)/F40 -> -0.008704802 | L41: -0.014060915 | M41: =VALUE(SUBSTITUTE(H41,",","")) -> 10531347
A42: 45566 | B42: 518.15 | C42: 519.75 | D42: 514 | E42: 518.15 | F42: 516.2 | G42: 515.9 | H42: 50,89,315 | I42: 2,62,55,80,578.35 | J42: 1,09,488 | K42: =(F42-F41)/F41 -> -0.003763389 | L42: -0.00054047038 | M42: =VALUE(SUBSTITUTE(H42,",","")) -> 5089315
A43: 45568 | B43: 508.55 | C43: 515.7 | D43: 508.1 | E43: 516.2 | F43: 512.75 | G43: 512.47 | H43: 1,58,70,147 | I43: 8,13,29,38,477.90 | J43: 2,27,553 | K43: =(F43-F42)/F42 -> -0.006683456 | L43: -0.021196345 | M43: =VALUE(SUBSTITUTE(H43,",","")) -> 15870147
A44: 45569 | B44: 510 | C44: 517.35 | D44: 501.55 | E44: 512.75 | F44: 503.55 | G44: 509.93 | H44: 1,82,28,912 | I44: 9,29,54,09,035.50 | J44: 2,92,636 | K44: =(F44-F43)/F43 -> -0.017942467 | L44: -0.0093266957 | M44: =VALUE(SUBSTITUTE(H44,",","")) -> 18228912
A45: 45572 | B45: 507 | C45: 514.95 | D45: 506.75 | E45: 503.55 | F45: 510.2 | G45: 511.03 | H45: 1,64,79,772 | I45: 8,42,16,88,874.45 | J45: 2,16,682 | K45: =(F45-F44)/F44 -> 0.013206236 | L45: -0.0087488906 | M45: =VALUE(SUBSTITUTE(H45,",","")) -> 16479772
... A61: 45594 | B61: 485 | C61: 489.2 | D61: 481.3 | E61: 484.15 | F61: 487.95 | G61: 486.12 | H61: 68,66,704 | I61: 3,33,80,33,179.65 | J61: 1,11,564 | K61: =(F61-F60)/F60 -> 0.0078488072 | L61: 0.005246691 | M61: =VALUE(SUBSTITUTE(H61,",","")) -> 6866704
A62: 45595 | B62: 487.95 | C62: 493.25 | D62: 486.5 | E62: 487.95 | F62: 491.55 | G62: 490.85 | H62: 63,93,835 | I62: 3,13,83,98,995.85 | J62: 92835 | K62: =(F62-F61)/F61 -> 0.0073778051 | L62: -0.0051498252 | M62: =VALUE(SUBSTITUTE(H62,",","")) -> 6393835
A63: 45596 | B63: 492 | C63: 493 | D63: 484.7 | E63: 491.55 | F63: 488.8 | G63: 487.8 | H63: 78,10,874 | I63: 3,81,01,27,063.40 | J63: 1,61,609 | K63: =(F63-F62)/F62 -> -0.0055945479 | L63: -0.0055667736 | M63: =VALUE(SUBSTITUTE(H63,",","")) -> 7810874
A64: 45597 | B64: 491 | C64: 492.1 | D64: 489.3 | E64: 488.8 | F64: 490.3 | G64: 490.89 | H64: 14,61,602 | I64: 71,74,91,831.90 | J64: 54687 | K64: =(F64-F63)/F63 -> 0.0030687398 | L64: 0.0040900049 | M64: =VALUE(SUBSTITUTE(H64,",","")) -> 1461602
A65: 45600 | B65: 493.45 | C65: 493.45 | D65: 479.55 | E65: 490.3 | F65: 484.6 | G65: 483.55 | H65: 84,29,731 | I65: 4,07,61,59,422.90 | J65: 1,70,904 | K65: =(F65-F64)/F64 -> -0.011625535 | L65: -0.012713773 | M65: =VALUE(SUBSTITUTE(H65,",","")) -> 8429731
A66: 45601 | B66: 482.95 | C66: 485.05 | D66: 476.95 | E66: 484.6 | F66: 480.2 | G66: 479.98 | H66: 73,27,830 | I66: 3,51,72,42,119.05 | J66: 1,50,450 | K66: =(F66-F65)/F65 -> -0.0090796533 | L66: 0.0090830098 | M66: =VALUE(SUBSTITUTE(H66,",","")) -> 7327830
A67: 45602 | B67: 480.2 | C67: 484.4 | D67: 478 | E67: 480.2 | F67: 481.1 | G67: 480.83 | H67: 1,13,13,985 | I67: 5,44,01,09,205.55 | J67: 1,40,673 | K67: =(F67-F66)/F66 -> 0.0018742191 | L67: 0.011181871 | M67: =VALUE(SUBSTITUTE(H67,",","")) -> 11313985
A68: 45603 | B68: 481.75 | C68: 482.7 | D68: 476.1 | E68: 481.1 | F68: 477.9 | G68: 477.82 | H68: 89,24,280 | I68: 4,26,41,65,090.20 | J68: 1,32,407 | K68: =(F68-F67)/F67 -> -0.0066514238 | L68: -0.011627978 | M68: =VALUE(SUBSTITUTE(H68,",","")) -> 8924280
A69: 45604 | B69: 477.9 | C69: 480.7 | D69: 474.6 | E69: 477.9 | F69: 478.05 | G69: 477.78 | H69: 60,90,462 | I69: 2,90,99,20,473.35 | J69: 1,05,996 | K69: =(F69-F68)/F68 -> 0.0003138732 | L69: -0.0021136931 | M69: =VALUE(SUBSTITUTE(H69,",","")) -> 6090462
A70: 45607 | B70: 478.05 | C70: 481.5 | D70: 474.1 | E70: 478.05 | F70: 476.95 | G70: 478.38 | H70: 54,88,948 | I70: 2,62,58,14,462.70 | J70: 1,23,605 | K70: =(F70-F69)/F69 -> -0.0023010145 | L70: -0.00028573558 | M70: =VALUE(SUBSTITUTE(H70,",","")) -> 5488948
A71: 45608 | B71: 477.6 | C71: 477.95 | D71: 471.15 | E71: 476.95 | F71: 472.85 | G71: 474.91 | H71: 50,41,916 | I71: 2,39,44,32,824.50 | J71: 1,29,476 | K71: =(F71-F70)/F70 -> -0.0085962889 | L71: -0.010680866 | M71: =VALUE(SUBSTITUTE(H71,",","")) -> 5041916
A72: 45609 | B72: 470.05 | C72: 474.7 | D72: 468.25 | E72: 472.85 | F72: 472.2 | G72: 471.96 | H72: 1,11,20,381 | I72: 5,24,84,10,369.00 | J72: 1,88,101 | K72: =(F72-F71)/F71 -> -0.0013746431 | L72: -0.013582627 | M72: =VALUE(SUBSTITUTE(H72,",","")) -> 11120381
A73: 45610 | B73: 471.2 | C73: 472.95 | D73: 462.25 | E73: 472.2 | F73: 465.95 | G73: 465.91 | H73: 1,16,39,562 | I73: 5,42,29,31,558.70 | J73: 2,30,824 | K73: =(F73-F72)/F72 -> -0.013235917 | L73: -0.0011184662 | M73: =VALUE(SUBSTITUTE(H73,",","")) -> 11639562
A74: 45614 | B74: 466 | C74: 467.8 | D74: 462 | E74: 465.95 | F74: 466.55 | G74: 464.79 | H74: 81,35,260 | I74: 3,78,11,91,097.20 | J74: 1,83,896 | K74: =(F74-F73)/F73 -> 0.0012876918 | L74: -0.0033527814 | M74: =VALUE(SUBSTITUTE(H74,",","")) -> 8135260
A75: 45615 | B75: 468 | C75: 473.75 | D75: 466.25 | E75: 466.55 | F75: 467.35 | G75: 471.03 | H75: 68,57,374 | I75: 3,23,00,38,399.65 | J75: 1,11,105 | K75: =(F75-F74)/F74 -> 0.0017147144 | L75: 0.0027586148 | M75: =VALUE(SUBSTITUTE(H75,",","")) -> 6857374
A76: 45617 | B76: 461 | C76: 464.05 | D76: 455.4 | E76: 467.35 | F76: 457.15 | G76: 458.53 | H76: 1,95,59,847 | I76: 8,96,87,97,499.25 | J76: 2,36,495 | K76: =(F76-F75)/F75 -> -0.021825185 | L76: -0.0071688245 | M76: =VALUE(SUBSTITUTE(H76,",","")) -> 19559847
... A79: 45622 | B79: 480 | C79: 482.65 | D79: 474.1 | E79: 476.8 | F79: 477 | G79: 476.76 | H79: 65,39,846 | I79: 3,11,79,27,466.80 | J79: 1,24,209 | K79: =(F79-F78)/F78 -> 0.00041946309 | L79: -0.0011312077 | M79: =VALUE(SUBSTITUTE(H79,",","")) -> 6539846
A80: 45623 | B80: 477.5 | C80: 480.1 | D80: 473 | E80: 477 | F80: 476.95 | G80: 475.67 | H80: 70,67,013 | I80: 3,36,15,55,101.90 | J80: 92526 | K80: =(F80-F79)/F79 -> -0.0001048218 | L80: 0.0033230693 | M80: =VALUE(SUBSTITUTE(H80,",","")) -> 7067013
A81: 45624 | B81: 477 | C81: 483.8 | D81: 470.55 | E81: 476.95 | F81: 474.9 | G81: 476.02 | H81: 1,44,12,539 | I81: 6,86,05,90,338.25 | J81: 1,97,328 | K81: =(F81-F80)/F80 -> -0.0042981445 | L81: -0.014861029 | M81: =VALUE(SUBSTITUTE(H81,",","")) -> 14412539
A82: 45625 | B82: 473.2 | C82: 478.9 | D82: 472.6 | E82: 474.9 | F82: 476.75 | G82: 476.39 | H82: 83,46,687 | I82: 3,97,63,06,074.10 | J82: 1,26,718 | K82: =(F82-F81)/F81 -> 0.003895557 | L82: 0.0090720348 | M82: =VALUE(SUBSTITUTE(H82,",","")) -> 8346687
A83: 45628 | B83: 476 | C83: 479.3 | D83: 473.4 | E83: 476.75 | F83: 477.2 | G83: 476.84 | H83: 54,78,598 | I83: 2,61,23,98,108.20 | J83: 1,05,775 | K83: =(F83-F82)/F82 -> 0.00094389093 | L83: 0.0060067713 | M83: =VALUE(SUBSTITUTE(H83,",","")) -> 5478598
A84: 45629 | B84: 466 | C84: 473.4 | D84: 462.75 | E84: 477.2 | F84: 472.55 | G84: 469.06 | H84: 2,22,18,251 | I84: 10,42,16,81,081.05 | J84: 2,89,294 | K84: =(F84-F83)/F83 -> -0.009744342 | L84: 0.0074600275 | M84: =VALUE(SUBSTITUTE(H84,",","")) -> 22218251
A85: 45630 | B85: 474.4 | C85: 478.2 | D85: 466.4 | E85: 472.55 | F85: 467.1 | G85: 470.88 | H85: 1,34,39,484 | I85: 6,32,83,46,244.15 | J85: 1,84,751 | K85: =(F85-F84)/F84 -> -0.011533171 | L85: 0.00042114474 | M85: =VALUE(SUBSTITUTE(H85,",","")) -> 13439484
A86: 45631 | B86: 467.55 | C86: 472.75 | D86: 462.5 | E86: 467.1 | F86: 467.5 | G86: 468 | H86: 2,64,15,053 | I86: 12,36,22,22,644.55 | J86: 2,80,989 | K86: =(F86-F85)/F85 -> 0.00085634768 | L86: 0.0098477774 | M86: =VALUE(SUBSTITUTE(H86,",","")) -> 26415053
A87: 45632 | B87: 470 | C87: 474.95 | D87: 467.7 | E87: 467.5 | F87: 471.15 | G87: 472.38 | H87: 75,51,407 | I87: 3,56,71,34,560.35 | J87: 1,18,458 | K87: =(F87-F86)/F86 -> 0.0078074866 | L87: -0.0012384452 | M87: =VALUE(SUBSTITUTE(H87,",","")) -> 7551407
A88: 45635 | B88: 471.5 | C88: 472 | D88: 462.95 | E88: 471.15 | F88: 464.95 | G88: 467.02 | H88: 1,17,03,384 | I88: 5,46,56,95,132.70 | J88: 1,60,632 | K88: =(F88-F87)/F87 -> -0.013159291 | L88: -0.0023827083 | M88: =VALUE(SUBSTITUTE(H88,",","")) -> 11703384
A89: 45636 | B89: 465.35 | C89: 466.45 | D89: 462.6 | E89: 464.95 | F89: 465.45 | G89: 464.64 | H89: 88,23,805 | I89: 4,09,99,16,466.30 | J89: 1,37,180 | K89: =(F89-F88)/F88 -> 0.0010753844 | L89: -0.00036354036 | M89: =VALUE(SUBSTITUTE(H89,",","")) -> 8823805
A90: 45637 | B90: 467.2 | C90: 468.2 | D90: 464.7 | E90: 465.45 | F90: 465.25 | G90: 466.13 | H90: 67,45,816 | I90: 3,14,44,31,682.05 | J90: 1,08,407 | K90: =(F90-F89)/F89 -> -0.0004296917 | L90: 0.0012901233 | M90: =VALUE(SUBSTITUTE(H90,",","")) -> 6745816
A91: 45638 | B91: 465.5 | C91: 467.9 | D91: 459.15 | E91: 465.25 | F91: 460.6 | G91: 462.32 | H91: 1,28,84,401 | I91: 5,95,67,25,495.60 | J91: 1,65,742 | K91: =(F91-F90)/F90 -> -0.0099946265 | L91: -0.0037781331 | M91: =VALUE(SUBSTITUTE(H91,",","")) -> 12884401
A92: 45639 | B92: 460 | C92: 474.4 | D92: 451.65 | E92: 460.6 | F92: 470 | G92: 464.46 | H92: 3,17,53,858 | I92: 14,74,84,33,018.55 | J92: 2,49,426 | K92: =(F92-F91)/F91 -> 0.020408163 | L92: 0.0089454839 | M92: =VALUE(SUBSTITUTE(H92,",","")) -> 31753858
... A139: 45706 | B139: 408 | C139: 410.85 | D139: 404 | E139: 408.6 | F139: 405.25 | G139: 406.53 | H139: 1,29,98,403 | I139: 5,28,42,37,636.80 | J139: 2,08,753 | K139: =(F139-F138)/F138 -> -0.0081987274 | L139: -0.00061848037 | M139: =VALUE(SUBSTITUTE(H139,",","")) -> 12998403
A140: 45707 | B140: 404.8 | C140: 408.8 | D140: 404.5 | E140: 405.25 | F140: 406.4 | G140: 406.89 | H140: 70,79,032 | I140: 2,88,04,11,815.90 | J140: 88693 | K140: =(F140-F139)/F139 -> 0.0028377545 | L140: -0.00054041568 | M140: =VALUE(SUBSTITUTE(H140,",","")) -> 7079032
A141: 45708 | B141: 399.95 | C141: 403.9 | D141: 396.2 | E141: 406.4 | F141: 402.05 | G141: 401.31 | H141: 1,53,55,585 | I141: 6,16,23,79,397.35 | J141: 2,26,856 | K141: =(F141-F140)/F140 -> -0.01070374 | L141: -0.00086120813 | M141: =VALUE(SUBSTITUTE(H141,",","")) -> 15355585
A142: 45709 | B142: 402.05 | C142: 403.25 | D142: 399.2 | E142: 402.05 | F142: 400.9 | G142: 400.75 | H142: 82,40,986 | I142: 3,30,25,44,309.75 | J142: 1,75,217 | K142: =(F142-F141)/F141 -> -0.0028603408 | L142: -0.0051171489 | M142: =VALUE(SUBSTITUTE(H142,",","")) -> 8240986
A143: 45712 | B143: 400 | C143: 403.4 | D143: 398.75 | E143: 400.9 | F143: 401.9 | G143: 401.96 | H143: 70,37,625 | I143: 2,82,88,32,996.75 | J143: 1,21,155 | K143: =(F143-F142)/F142 -> 0.0024943876 | L143: -0.010640071 | M143: =VALUE(SUBSTITUTE(H143,",","")) -> 7037625
A144: 45713 | B144: 402 | C144: 407 | D144: 400.5 | E144: 401.9 | F144: 404.85 | G144: 404.11 | H144: 1,57,60,891 | I144: 6,36,90,71,142.95 | J144: 1,38,641 | K144: =(F144-F143)/F143 -> 0.0073401344 | L144: -0.000257168 | M144: =VALUE(SUBSTITUTE(H144,",","")) -> 15760891
A145: 45715 | B145: 404.85 | C145: 406.5 | D145: 399.5 | E145: 404.85 | F145: 401.6 | G145: 401.75 | H145: 1,90,51,003 | I145: 7,65,36,97,871.25 | J145: 1,63,369 | K145: =(F145-F144)/F144 -> -0.0080276646 | L145: -0.00011087679 | M145: =VALUE(SUBSTITUTE(H145,",","")) -> 19051003
A146: 45716 | B146: 399 | C146: 402.5 | D146: 392.2 | E146: 401.6 | F146: 395 | G146: 394.79 | H146: 3,19,54,776 | I146: 12,61,54,32,840.90 | J146: 2,44,503 | K146: =(F146-F145)/F145 -> -0.016434263 | L146: -0.018644891 | M146: =VALUE(SUBSTITUTE(H146,",","")) -> 31954776
A147: 45719 | B147: 395.95 | C147: 399 | D147: 391.2 | E147: 395 | F147: 397.45 | G147: 396.98 | H147: 1,07,02,826 | I147: 4,24,87,73,535.65 | J147: 1,69,634 | K147: =(F147-F146)/F146 -> 0.0062025316 | L147: -0.00024407111 | M147: =VALUE(SUBSTITUTE(H147,",","")) -> 10702826
A148: 45720 | B148: 395.4 | C148: 397.2 | D148: 392.85 | E148: 397.45 | F148: 394.85 | G148: 394.38 | H148: 1,34,04,774 | I148: 5,28,65,94,132.80 | J148: 1,54,199 | K148: =(F148-F147)/F147 -> -0.0065417034 | L148: -0.001656924 | M148: =VALUE(SUBSTITUTE(H148,",","")) -> 13404774
A149: 45721 | B149: 394.5 | C149: 412.75 | D149: 394.5 | E149: 394.85 | F149: 405.05 | G149: 399.82 | H149: 1,56,65,018 | I149: 6,26,31,65,318.05 | J149: 1,69,098 | K149: =(F149-F148)/F148 -> 0.025832595 | L149: 0.011531678 | M149: =VALUE(SUBSTITUTE(H149,",","")) -> 15665018
A150: 45722 | B150: 409.15 | C150: 409.7 | D150: 400.55 | E150: 405.05 | F150: 405.7 | G150: 403.66 | H150: 1,78,69,996 | I150: 7,21,34,83,492.20 | J150: 1,70,718 | K150: =(F150-F149)/F149 -> 0.0016047402 | L150: 0.0092849181 | M150: =VALUE(SUBSTITUTE(H150,",","")) -> 17869996
A151: 45723 | B151: 403.55 | C151: 405.85 | D151: 401.7 | E151: 405.7 | F151: 403.9 | G151: 403.66 | H151: 1,11,80,761 | I151: 4,51,31,90,673.15 | J151: 1,29,975 | K151: =(F151-F150)/F150 -> -0.0044367759 | L151: 0.00034597932 | M151: =VALUE(SUBSTITUTE(H151,",","")) -> 11180761
A152: 45726 | B152: 401.05 | C152: 406.85 | D152: 400.4 | E152: 403.9 | F152: 405 | G152: 404.7 | H152: 97,85,018 | I152: 3,96,00,32,837.25 | J152: 1,14,078 | K152: =(F152-F151)/F151 -> 0.0027234464 | L152: -0.0040882386 | M152: =VALUE(SUBSTITUTE(H152,",","")) -> 9785018
A153: 45727 | B153: 401.5 | C153: 408.4 | D153: 401.2 | E153: 405 | F153: 406.2 | G153: 406.58 | H153: 1,10,99,475 | I153: 4,51,27,93,431.70 | J153: 1,16,862 | K153: =(F153-F152)/F152 -> 0.002962963 | L153: 0.0016740649 | M153: =VALUE(SUBSTITUTE(H153,",","")) -> 11099475
A154: 45728 | B154: 406.4 | C154: 413.3 | D154: 404 | E154: 406.2 | F154: 412.4 | G154: 409.75 | H154: 1,38,44,306 | I154: 5,67,27,66,834.60 | J154: 99237 | K154: =(F154-F153)/F153 -> 0.015263417 | L154: -0.0012178914 | M154: =VALUE(SUBSTITUTE(H154,",","")) -> 13844306
A155: 45729 | B155: 413 | C155: 414.4 | D155: 408.2 | E155: 412.4 | F155: 412.05 | G155: 412.4 | H155: 81,96,569 | I155: 3,38,02,86,305.70 | J155: 1,22,083 | K155: =(F155-F154)/F154 -> -0.00084869059 | L155: -0.0032620547 | M155: =VALUE(SUBSTITUTE(H155,",","")) -> 8196569
A156: 45733 | B156: 413 | C156: 416.25 | D156: 407 | E156: 412.05 | F156: 407.95 | G156: 409.81 | H156: 52,57,859 | I156: 2,15,47,06,809.40 | J156: 87899 | K156: =(F156-F155)/F155 -> -0.0099502488 | L156: 0.0049805333 | M156: =VALUE(SUBSTITUTE(H156,",","")) -> 5257859
A157: 45734 | B157: 410 | C157: 411.95 | D157: 407.75 | E157: 407.95 | F157: 409.1 | G157: 409.5 | H157: 1,38,61,897 | I157: 5,67,65,00,784.85 | J157: 1,06,364 | K157: =(F157-F156)/F156 -> 0.0028189729 | L157: 0.014463264 | M157: =VALUE(SUBSTITUTE(H157,",","")) -> 13861897
A158: 45735 | B158: 410 | C158: 410.75 | D158: 402.6 | E158: 409.1 | F158: 403.05 | G158: 404.51 | H158: 1,28,30,387 | I158: 5,18,99,84,214.60 | J158: 1,35,494 | K158: =(F158-F157)/F157 -> -0.01478856 | L158: 0.0032100831 | M158: =VALUE(SUBSTITUTE(H158,",","")) -> 12830387
A159: 45736 | B159: 405 | C159: 406.65 | D159: 401.9 | E159: 403.05 | F159: 403.95 | G159: 403.5 | H159: 1,69,94,037 | I159: 6,85,71,53,651.65 | J159: 1,25,979 | K159: =(F159-F158)/F158 -> 0.0022329736 | L159: 0.012356161 | M159: =VALUE(SUBSTITUTE(H159,",","")) -> 16994037
A160: 45737 | B160: 405.95 | C160: 407.5 | D160: 401.7 | E160: 403.95 | F160: 405.55 | G160: 404.1 | H160: 2,53,02,035 | I160: 10,22,46,18,507.85 | J160: 1,30,427 | K160: =(F160-F159)/F159 -> 0.0039608862 | L160: 0.0068885521 | M160: =VALUE(SUBSTITUTE(H160,",","")) -> 25302035
A161: 45740 | B161: 407 | C161: 412.85 | D161: 405.6 | E161: 405.55 | F161: 410.9 | G161: 409.64 | H161: 1,43,62,572 | I161: 5,88,35,05,695.50 | J161: 1,38,703 | K161: =(F161-F160)/F160 -> 0.013191962 | L161: 0.013188211 | M161: =VALUE(SUBSTITUTE(H161,",","")) -> 14362572
A162: 45741 | B162: 412 | C162: 415.25 | D162: 408.7 | E162: 410.9 | F162: 409.8 | G162: 411.17 | H162: 2,03,38,110 | I162: 8,36,24,11,027.50 | J162: 1,38,414 | K162: =(F162-F161)/F161 -> -0.0026770504 | L162: 0.00043536426 | M162: =VALUE(SUBSTITUTE(H162,",","")) -> 20338110
A163: 45742 | B163: 410.3 | C163: 411.2 | D163: 406.25 | E163: 409.8 | F163: 407.35 | G163: 409.03 | H163: 1,38,91,436 | I163: 5,68,19,50,426.05 | J163: 1,03,317 | K163: =(F163-F162)/F162 -> -0.0059785261 | L163: -0.0076810464 | M163: =VALUE(SUBSTITUTE(H163,",","")) -> 13891436
A164: 45743 | B164: 408 | C164: 410.7 | D164: 405.65 | E164: 407.35 | F164: 409.45 | G164: 409.35 | H164: 1,86,42,328 | I164: 7,63,12,35,472.20 | J164: 1,53,590 | K164: =(F164-F163)/F163 -> 0.0051552719 | L164: 0.0044748444 | M164: =VALUE(SUBSTITUTE(H164,",","")) -> 18642328
A165: 45744 | B165: 410.9 | C165: 415.6 | D165: 408.15 | E165: 409.45 | F165: 409.75 | G165: 410.91 | H165: 1,29,81,873 | I165: 5,33,44,43,057.90 | J165: 1,14,689 | K165: =(F165-F164)/F164 -> 0.00073269019 | L165: -0.0030773209 | M165: =VALUE(SUBSTITUTE(H165,",","")) -> 12981873
A166: 45748 | B166: 409.8 | C166: 414.4 | D166: 405.6 | E166: 409.75 | F166: 406.65 | G166: 409.28 | H166: 1,52,06,240 | I166: 6,22,36,51,577.60 | J166: 1,27,499 | K166: =(F166-F165)/F165 -> -0.0075655888 | L166: -0.015036555 | M166: =VALUE(SUBSTITUTE(H166,",","")) -> 15206240
A167: 45749 | B167: 407.05 | C167: 410 | D167: 406.05 | E167: 406.65 | F167: 409.05 | G167: 408.65 | H167: 80,01,323 | I167: 3,26,97,11,918.80 | J167: 72562 | K167: =(F167-F166)/F166 -> 0.0059018812 | L167: 0.0071938254 | M167: =VALUE(SUBSTITUTE(H167,",","")) -> 8001323
A168: 45750 | B168: 407.05 | C168: 410.2 | D168: 406.7 | E168: 409.05 | F168: 409.4 | G168: 408.93 | H168: 70,59,566 | I168: 2,88,68,81,314.85 | J168: 78934 | K168: =(F168-F167)/F167 -> 0.00085564112 | L168: -0.0035251486 | M168: =VALUE(SUBSTITUTE(H168,",","")) -> 7059566
A169: 45751 | B169: 407.5 | C169: 412.8 | D169: 404.5 | E169: 409.4 | F169: 409.7 | G169: 409.44 | H169: 1,86,27,592 | I169: 7,62,67,98,175.75 | J169: 1,49,408 | K169: =(F169-F168)/F168 -> 0.00073277968 | L169: -0.014866603 | M169: =VALUE(SUBSTITUTE(H169,",","")) -> 18627592
A170: 45754 | B170: 390.15 | C170: 408.1 | D170: 390.15 | E170: 409.7 | F170: 406.05 | G170: 403.02 | H170: 2,67,62,866 | I170: 10,78,58,70,136.45 | J170: 3,07,280 | K170: =(F170-F169)/F169 -> -0.0089089578 | L170: -0.032432562 | M170: =VALUE(SUBSTITUTE(H170,",","")) -> 26762866
A171: 45755 | B171: 411.9 | C171: 415.8 | D171: 407.25 | E171: 406.05 | F171: 412.55 | G171: 411.57 | H171: 1,86,00,796 | I171: 7,65,54,92,505.50 | J171: 2,34,584 | K171: =(F171-F170)/F170 -> 0.016007881 | L171: 0.016887319 | M171: =VALUE(SUBSTITUTE(H171,",","")) -> 18600796
A172: 45756 | B172: 413 | C172: 419.05 | D172: 411.25 | E172: 412.55 | F172: 416.3 | G172: 416.41 | H172: 2,17,85,572 | I172: 9,07,16,50,104.35 | J172: 2,42,191 | K172: =(F172-F171)/F171 -> 0.0090898073 | L172: -0.0060658906 | M172: =VALUE(SUBSTITUTE(H172,",","")) -> 21785572
A173: 45758 | B173: 420 | C173: 422.45 | D173: 417 | E173: 416.3 | F173: 421.55 | G173: 420.4 | H173: 89,39,356 | I173: 3,75,80,63,114.55 | J173: 98015 | K173: =(F173-F172)/F172 -> 0.012611098 | L173: 0.01917037 | M173: =VALUE(SUBSTITUTE(H173,",","")) -> 8939356
A174: 45762 | B174: 429.2 | C174: 429.2 | D174: 419 | E174: 421.55 | F174: 420.4 | G174: 421.35 | H174: 1,16,85,880 | I174: 4,92,38,48,655.80 | J174: 1,29,742 | K174: =(F174-F173)/F173 -> -0.0027280275 | L174: 0.021902399 | M174: =VALUE(SUBSTITUTE(H174,",","")) -> 11685880
A175: 45763 | B175: 418 | C175: 426.05 | D175: 418 | E175: 420.4 | F175: 424.45 | G175: 423.29 | H175: 1,30,34,594 | I175: 5,51,74,51,893.15 | J175: 1,15,189 | K175: =(F175-F174)/F174 -> 0.0096336822 | L175: 0.0046573833 | M175: =VALUE(SUBSTITUTE(H175,",","")) -> 13034594
A176: 45764 | B176: 425 | C176: 427.85 | D176: 421.55 | E176: 424.45 | F176: 427.25 | G176: 425.37 | H176: 2,24,10,217 | I176: 9,53,26,79,412.90 | J176: 2,22,404 | K176: =(F176-F175)/F175 -> 0.0065967723 | L176: 0.017683426 | M176: =VALUE(SUBSTITUTE(H176,",","")) -> 22410217
A177: 45768 | B177: 428.05 | C177: 429.1 | D177: 421.5 | E177: 427.25 | F177: 422.85 | G177: 422.51 | H177: 2,73,88,236 | I177: 11,57,18,85,187.30 | J177: 2,18,049 | K177: =(F177-F176)/F176 -> -0.01029842 | L177: 0.011483482 | M177: =VALUE(SUBSTITUTE(H177,",","")) -> 27388236
A178: 45769 | B178: 425.95 | C178: 434.8 | D178: 423.55 | E178: 422.85 | F178: 433.6 | G178: 427.96 | H178: 3,20,31,936 | I178: 13,70,84,85,407.15 | J178: 1,67,601 | K178: =(F178-F177)/F177 -> 0.025422727 | L178: 0.001728458 | M178: =VALUE(SUBSTITUTE(H178,",","")) -> 32031936
...

Sheet NIFTY 50
A1: Date | B1: Open | C1: High | D1: Low | E1: Close | F1: Shares Traded | G1: Turnover (₹ Cr) | H1: NIFTY RETURN
A2: 45509 | B2: 24302.85 | C2: 24350.05 | D2: 23893.7 | E2: 24055.6 | F2: 486994718 | G2: 45066.65 | I2: MEAN NIFTY DAILY RETURN
A3: 45510 | B3: 24189.85 | C3: 24382.6 | D3: 23960.4 | E3: 23992.55 | F3: 312339387 | G3: 31553.65 | H3: -0.0026210113 | I3: =AVERAGE(H3:H496) -> 9.4862007e-05
A4: 45511 | B4: 24289.4 | C4: 24337.7 | D4: 24184.9 | E4: 24297.5 | F4: 317564429 | G4: 29738.85 | H4: 0.012710195 | I4: =(1+I3)^252-1 -> 0.024192085
A5: 45512 | B5: 24248.55 | C5: 24340.5 | D5: 24079.7 | E5: 24117 | F5: 311875940 | G5: 30858.18 | H5: -0.0074287478
A6: 45513 | B6: 24386.85 | C6: 24419.75 | D6: 24311.2 | E6: 24367.5 | F6: 215129992 | G6: 22339.19 | H6: 0.010386864
A7: 45516 | B7: 24320.05 | C7: 24472.8 | D7: 24212.1 | E7: 24347 | F7: 279925100 | G7: 30311.85 | H7: -0.0008412845
A8: 45517 | B8: 24342.35 | C8: 24359.95 | D8: 24116.5 | E8: 24139 | F8: 239727640 | G8: 25459.58 | H8: -0.008543147
A9: 45518 | B9: 24184.4 | C9: 24196.5 | D9: 24099.7 | E9: 24143.75 | F9: 303254705 | G9: 27834.61 | H9: 0.000196777
A10: 45520 | B10: 24334.85 | C10: 24563.9 | D10: 24204.5 | E10: 24541.15 | F10: 271611087 | G10: 28521.9 | H10: 0.016459746
A11: 45523 | B11: 24636.35 | C11: 24638.8 | D11: 24522.95 | E11: 24572.65 | F11: 243645503 | G11: 22124.41 | H11: 0.0012835584
A12: 45524 | B12: 24648.9 | C12: 24734.3 | D12: 24607.2 | E12: 24698.85 | F12: 238318940 | G12: 25478.73 | H12: 0.0051357912
A13: 45525 | B13: 24680.55 | C13: 24787.95 | D13: 24654.5 | E13: 24770.2 | F13: 257114212 | G13: 27404.63 | H13: 0.0028887985
A14: 45526 | B14: 24863.4 | C14: 24867.35 | D14: 24784.45 | E14: 24811.5 | F14: 220345125 | G14: 24227.03 | H14: 0.0016673261
A15: 45527 | B15: 24845.4 | C15: 24858.4 | D15: 24771.65 | E15: 24823.15 | F15: 206800655 | G15: 23134.22 | H15: 0.00046954033
A16: 45530 | B16: 24906.1 | C16: 25043.8 | D16: 24874.7 | E16: 25010.6 | F16: 210266456 | G16: 22166.86 | H16: 0.0075514187
... A496: 46237 | B496: 24572.7 | C496: 24774.3 | D496: 24515.15 | E496: 24774.3 | F496: 342283085 | G496: 27052.25 | H496: 0.016023065

Sheet RETURN_CALC
A1: Stock | B1: Mean Daily Return | C1: Standard Deviation | D1: Beta
A2: RELIANCE | B2: =AVERAGE(Reliance!K3:K496) -> -0.00011162634 | C2: =STDEV(Reliance!K3:K496) -> 0.013175305 | D2: =_xlfn.COVARIANCE.P(Reliance!K3:K496,Reliance!L3:L496)/VARP(Reliance!L3:L496) -> 1.0571258
A3: TCS | B3: =AVERAGE(TCS!K3:K496) -> -0.00093250606 | C3: =_xlfn.STDEV.S(TCS!K3:K496) -> 0.015273664 | D3: =_xlfn.COVARIANCE.P(TCS!K3:K496,TCS!L3:L496)/VARP(TCS!L3:L496) -> 0.82783985
A4: INFY | B4: =AVERAGE(INFY!K3:K496) -> -0.00064664683 | C4: =_xlfn.STDEV.S(INFY!K3:K496) -> 0.017498426 | D4: =_xlfn.COVARIANCE.P(INFY!K3:K496,INFY!L3:L496)/VARP(INFY!L3:L496) -> 0.90306501
A5: HDFCBANK | B5: =AVERAGE(HDFCBANK!K3:K496) -> -0.0010685507 | C5: =_xlfn.STDEV.S(HDFCBANK!K3:K496) -> 0.025865296 | D5: =_xlfn.COVARIANCE.P(HDFCBANK!K3:K496,HDFCBANK!L3:L496)/VARP(HDFCBANK!L3:L496) -> 1.2255984
A6: ICICIBANK | B6: =AVERAGE(ICICIBANK!K3:K496) -> 0.00051244151 | C6: =_xlfn.STDEV.S(ICICIBANK!K3:K496) -> 0.011739787 | D6: =_xlfn.COVARIANCE.P(ICICIBANK!K3:K496,ICICIBANK!L3:L496)/VARP(ICICIBANK!L3:L496) -> 0.92969866
A7: ITC | B7: =AVERAGE(ITC!K3:K496) -> -0.00099084576 | C7: =_xlfn.STDEV.S(ITC!K3:K496) -> 0.012165966 | D7: =_xlfn.COVARIANCE.P(ITC!K3:K496,ITC!L3:L496)/VARP(ITC!L3:L496) -> 0.64553132
B10: Return Calculation Analysis
B11: Daily returns were calculated using the daily closing prices of the selected stocks and the NIFTY 50 index over a two-year period.
B12: The mean daily return represents the average daily performance of each stock during the sample period.
B13: The standard deviation measures the volatility of stock returns. Higher standard deviation indicates greater risk and larger fluctuations in returns.
B14: Beta measures the sensitivity of a stock's returns relative to the market (NIFTY 50). A beta greater than 1 indicates that the stock is more volatile than the market, while a beta less than 1 indicates lower market sensitivity.
B15: Among the selected stocks, HDFCBANK exhibited the highest volatility based on its standard deviation, whereas ITC had the lowest beta, indicating relatively lower systematic risk.
B16: These calculated statistics provide the foundation for portfolio construction, CAPM analysis, and portfolio performance evaluation.

Sheet Portfolio_Weights
A1: VALUE WEIGHTED PORTFOLIO
A2: Stock | B2: Market Cap (₹ Cr) | C2: Weight
A3: RELIANCE | B3: 1748945.3 | C3: =B3/$B$9 -> 0.31020484
A4: TCS | B4: 885526.92 | C4: =B4/$B$9 -> 0.15706308
A5: INFY | B5: 470557.42 | C5: =B5/$B$9 -> 0.083461266
A6: HDFCBANK | B6: 1139062.2 | C6: =B6/$B$9 -> 0.20203183
A7: ICICIBANK | B7: 1034721.8 | C7: =B7/$B$9 -> 0.18352531
A8: ITC | B8: 359219.85 | C8: =B8/$B$9 -> 0.063713677
A9: Total | B9: 5638033.5 | C9: 1
A11: Price-Weighted Portfolio
A12: Stock | B12: Latest Close Price | C12: Price Weight
A13: RELIANCE | B13: 1319 | C13: =B13/$B$19 -> 0.17650916
A14: TCS | B14: 2473.7 | C14: =B14/$B$19 -> 0.33103162
A15: INFY | B15: 1180 | C15: =B15/$B$19 -> 0.15790812
A16: HDFCBANK | B16: 753 | C16: =B16/$B$19 -> 0.10076679
A17: ICICIBANK | B17: 1460 | C17: =B17/$B$19 -> 0.19537784
A18: ITC | B18: 287 | C18: =B18/$B$19 -> 0.038406466
A19: Total | B19: =SUM(B13:B18) -> 7472.7 | C19: 1
A21: Minimum Variance Portfolio
A22: Stock | B22: Value Weight | C22: Price Weight | D22: Minimum Variance Weight
A23: RELIANCE | B23: 0.3102 | C23: 0.1765 | D23: 0.1767
A24: TCS | B24: 0.1571 | C24: 0.331 | D24: 0.1138
A25: INFY | B25: 0.0835 | C25: 0.1579 | D25: 0.0663
A26: HDFCBANK | B26: 0.202 | C26: 0.1008 | D26: 0.0139
A27: ICICIBANK | B27: 0.1835 | C27: 0.1954 | D27: 0.3332
A28: ITC | B28: 0.0637 | C28: 0.0384 | D28: 0.296
A29: Total | B29: 1 | C29: 1 | D29: 1
A31: Portfolio Weights Analysis
A32: Value-Weighted Portfolio: The portfolio weights are based on the market capitalization of each company. Reliance received the highest weight (31.02%) due to its largest market capitalization, while ITC received the lowest weight (6.37%). This approach gives greater importance to larger companies.
A33: Price-Weighted Portfolio: The weights are determined by the latest stock prices. TCS received the highest weight (33.10%) because it had the highest share price, whereas ITC received the lowest weight (3.84%). In this method, stocks with higher prices have a greater influence on the portfolio.
A34: Minimum Variance Portfolio: The weights were calculated using the covariance matrix to minimize the overall portfolio risk. The portfolio allocated the highest weights to ICICIBANK (33.32%) and ITC (29.60%), while HDFCBANK received the lowest weight (1.39%). This allocation aims to achieve the lowest possible portfolio variance through diversification.
A35: Overall Conclusion
A37: The three portfolio weighting methods produce different allocations because they follow different investment objectives. The Value-Weighted Portfolio emphasizes company size, the Price-Weighted Portfolio emphasizes stock price, and the Minimum Variance Portfolio emphasizes risk reduction. Among the three, the Minimum Variance Portfolio is designed to provide the most efficient diversification by minimizing the portfolio's overall risk.

Sheet COVARIANCE MATRIX
B1: RELIANCE | C1: TCS | D1: INFY | E1: HDFCBANK | F1: ICICIBANK | G1: ITC
A2: RELIANCE | B2: =_xlfn.COVARIANCE.P(Reliance!K3:K496,Reliance!K3:K496) -> 0.00017323654 | C2: =_xlfn.COVARIANCE.P(Reliance!K3:K496,TCS!K3:K496) -> 5.0067571e-05 | D2: =_xlfn.COVARIANCE.P(Reliance!K3:K496,INFY!K3:K496) -> 4.8099968e-05 | E2: =_xlfn.COVARIANCE.P(Reliance!K3:K496,HDFCBANK!K3:K496) -> 8.7462375e-05 | F2: =_xlfn.COVARIANCE.P(Reliance!K3:K496,ICICIBANK!K3:K496) -> 4.4697994e-05 | G2: =_xlfn.COVARIANCE.P(Reliance!K3:K496,ITC!K3:K496) -> 5.3517473e-05
A3: TCS | B3: =_xlfn.COVARIANCE.P(TCS!K3:K496,Reliance!K3:K496) -> 5.0067571e-05 | C3: =_xlfn.COVARIANCE.P(TCS!K3:K496,TCS!K3:K496) -> 0.00023281257 | D3: =_xlfn.COVARIANCE.P(TCS!K3:K496,INFY!K3:K496) -> 0.00020425057 | E3: =_xlfn.COVARIANCE.P(TCS!K3:K496,HDFCBANK!K3:K496) -> 3.0814188e-05 | F3: =_xlfn.COVARIANCE.P(TCS!K3:K496,ICICIBANK!K3:K496) -> 3.2678283e-05 | G3: =_xlfn.COVARIANCE.P(TCS!K3:K496,ITC!K3:K496) -> 3.7898184e-05
A4: INFY | B4: =_xlfn.COVARIANCE.P(INFY!K3:K496,Reliance!K3:K496) -> 4.8099968e-05 | C4: =_xlfn.COVARIANCE.P(INFY!K3:K496,TCS!K3:K496) -> 0.00020425057 | D4: =_xlfn.COVARIANCE.P(INFY!K3:K496,INFY!K3:K496) -> 0.0003055751 | E4: =_xlfn.COVARIANCE.P(INFY!K3:K496,HDFCBANK!K3:K496) -> 3.9618299e-05 | F4: =_xlfn.COVARIANCE.P(INFY!K3:K496,ICICIBANK!K3:K496) -> 3.3809991e-05 | G4: =_xlfn.COVARIANCE.P(INFY!K3:K496,ITC!K3:K496) -> 2.5732384e-05
A5: HDFCBANK | B5: =_xlfn.COVARIANCE.P(HDFCBANK!K3:K496,Reliance!K3:K496) -> 8.7462375e-05 | C5: =_xlfn.COVARIANCE.P(HDFCBANK!K3:K496,TCS!K3:K496) -> 3.0814188e-05 | D5: =_xlfn.COVARIANCE.P(HDFCBANK!K3:K496,INFY!K3:K496) -> 3.9618299e-05 | E5: =_xlfn.COVARIANCE.P(HDFCBANK!K3:K496,HDFCBANK!K3:K496) -> 0.00066765928 | F5: =_xlfn.COVARIANCE.P(HDFCBANK!K3:K496,ICICIBANK!K3:K496) -> 9.2725843e-05 | G5: =_xlfn.COVARIANCE.P(HDFCBANK!K3:K496,ITC!K3:K496) -> 3.2682308e-05
A6: ICICIBANK | B6: =_xlfn.COVARIANCE.P(ICICIBANK!K3:K496,Reliance!K3:K496) -> 4.4697994e-05 | C6: =_xlfn.COVARIANCE.P(ICICIBANK!K3:K496,TCS!K3:K496) -> 3.2678283e-05 | D6: =_xlfn.COVARIANCE.P(ICICIBANK!K3:K496,INFY!K3:K496) -> 3.3809991e-05 | E6: =_xlfn.COVARIANCE.P(ICICIBANK!K3:K496,HDFCBANK!K3:K496) -> 9.2725843e-05 | F6: =_xlfn.COVARIANCE.P(ICICIBANK!K3:K496,ICICIBANK!K3:K496) -> 0.0001375436 | G6: =_xlfn.COVARIANCE.P(ICICIBANK!K3:K496,ITC!K3:K496) -> 3.5368858e-05
A7: ITC | B7: =_xlfn.COVARIANCE.P(ITC!K3:K496,Reliance!K3:K496) -> 5.3517473e-05 | C7: =_xlfn.COVARIANCE.P(ITC!K3:K496,TCS!K3:K496) -> 3.7898184e-05 | D7: =_xlfn.COVARIANCE.P(ITC!K3:K496,INFY!K3:K496) -> 2.5732384e-05 | E7: =_xlfn.COVARIANCE.P(ITC!K3:K496,HDFCBANK!K3:K496) -> 3.2682308e-05 | F7: =_xlfn.COVARIANCE.P(ITC!K3:K496,ICICIBANK!K3:K496) -> 3.5368858e-05 | G7: =_xlfn.COVARIANCE.P(ITC!K3:K496,ITC!K3:K496) -> 0.00014771112

Sheet MIN VARIANCE
A1: 0.0001732 | B1: 5.01e-05 | C1: 4.81e-05 | D1: 8.75e-05 | E1: 4.47e-05 | F1: 5.35e-05 | H1: {=MINVERSE(A1:F6)} -> 7311.816 | I1: -784.24754 | J1: -245.43237 | K1: -646.02354 | L1: -1185.5432 | M1: -1977.3755 | O1: 1 | Q1: {=MMULT(H1:M6,O1:O6)} -> 2473.1938 | R1: =Q1/$Q$8 -> 0.17670105
A2: 5.01e-05 | B2: 0.0002328 | C2: 0.0002043 | D2: 3.08e-05 | E2: 3.27e-05 | F2: 3.79e-05 | H2: -784.24754 | I2: 10834.946 | J2: -6992.6649 | K2: 129.64172 | L2: -376.72814 | M2: -1217.8661 | O2: 1 | Q2: 1593.0809 | R2: =Q2/$Q$8 -> 0.11382006
A3: 4.81e-05 | B3: 0.0002043 | C3: 0.0003056 | D3: 3.96e-05 | E3: 3.38e-05 | F3: 2.57e-05 | H3: -245.43237 | I3: -6992.6649 | J3: 7982.9494 | K3: -105.96084 | L3: -299.92276 | M3: 589.52617 | O3: 1 | Q3: 928.49476 | R3: =Q3/$Q$8 -> 0.066337704
A4: 8.75e-05 | B4: 3.08e-05 | C4: 3.96e-05 | D4: 0.0006677 | E4: 9.27e-05 | F4: 3.27e-05 | H4: -646.02354 | I4: 129.64172 | J4: -105.96084 | K4: 1713.5888 | L4: -968.55775 | M4: 71.93381 | O4: 1 | Q4: 194.62216 | R4: =Q4/$Q$8 -> 0.013905073
A5: 4.47e-05 | B5: 3.27e-05 | C5: 3.38e-05 | D5: 9.27e-05 | E5: 0.0001375 | F5: 3.54e-05 | H5: -1185.5432 | I5: -376.72814 | J5: -299.92276 | K5: -968.55775 | L5: 8814.2373 | M5: -1319.8347 | O5: 1 | Q5: 4663.6507 | R5: =Q5/$Q$8 -> 0.33320154
A6: 5.35e-05 | B6: 3.79e-05 | C6: 2.57e-05 | D6: 3.27e-05 | E6: 3.54e-05 | F6: 0.0001477 | H6: -1977.3755 | I6: -1217.8661 | J6: 589.52617 | K6: 71.93381 | L6: -1319.8347 | M6: 7997.0603 | O6: 1 | Q6: 4143.4439 | R6: =Q6/$Q$8 -> 0.29603458
Q8: =SUM(Q1:Q6) -> 13996.486 | R8: =SUM(R1:R6) -> 1

Sheet Portfolio_Performance
A1: Portfolio | B1: Expected Return | C1: Risk (Std. Dev.) | D1: Sharpe Ratio
A2: Minimum Variance | B2: =SUMPRODUCT(Portfolio_Weights!D23:D28,RETURN_CALC!B2:B7) -> -0.00030611394 | C2: {=SQRT(INDEX(MMULT(TRANSPOSE(Portfolio_Weights!D23:D28),MMULT('COVARIANCE MATRIX'!B2:G7,Portfolio_Weights!D23:D28)),1,1))} -> 0.0084517776 | D2: =(B2-(6%/252))/C2 -> -0.064389907
A3: Value-Weighted | B3: =SUMPRODUCT(Portfolio_Weights!C3:C8,RETURN_CALC!B2:B7) -> -0.00042002496 | C3: {=SQRT(INDEX(MMULT(TRANSPOSE(Portfolio_Weights!C3:C8),MMULT('COVARIANCE MATRIX'!B2:G7,Portfolio_Weights!C3:C8)),1,1))} -> 0.01018361 | D3: =(B3-(6%/252))/C3 -> -0.064625429
A4: Price-Weighted | B4: =SUMPRODUCT(Portfolio_Weights!C13:C18,RETURN_CALC!B2:B7) -> -0.00047611244 | C4: {=SQRT(INDEX(MMULT(TRANSPOSE(Portfolio_Weights!C13:C18),MMULT('COVARIANCE MATRIX'!B2:G7,Portfolio_Weights!C13:C18)),1,1))} -> 0.01014506 | D4: =(B4-(6%/252))/C4 -> -0.070399549
A8: Portfolio Performance Analysis
A9: The Minimum Variance Portfolio recorded the lowest risk (0.8452%) among the three portfolios and also had the least negative expected return (-0.0306%), indicating better risk management compared with the other portfolios.
A10: The Value-Weighted Portfolio had the highest risk (1.0184%) and a more negative expected return (-0.0420%) than the Minimum Variance Portfolio.
A11: The Price-Weighted Portfolio had a similar level of risk (1.0145%) but produced the lowest expected return (-0.0476%), resulting in the weakest overall performance.
A12: All three portfolios recorded negative Sharpe Ratios, indicating that their returns were below the risk-free rate during the sample period. Among them, the Minimum Variance Portfolio performed relatively better due to its lower risk and comparatively higher (less negative) expected return.
A14: Overall Conclusion:
A15: Among the three portfolio construction methods, the Minimum Variance Portfolio provided the best risk-adjusted performance over the selected two-year period because it achieved the lowest portfolio risk while limiting losses compared with the Value-Weighted and Price-Weighted portfolios.

Sheet Volume_Price_Analysis
A1: RELIANCE
A17: Observations
A18: Reliance's stock price declined sharply during late 2024 and remained relatively stable thereafter.
A19: Trading volume increased during periods of significant price movement, indicating higher investor activity.
A20: Volume spikes coincided with periods of increased price volatility.
A21: Overall, higher trading volumes were associated with larger price fluctuations.
A23: TCS
A42: Observations
A43: TCS stock price exhibited an overall downward trend during the two-year period, with intermittent short-term recoveries.
A44: Trading volume remained relatively moderate for most of the period but increased significantly towards the end of the sample period.
A45: The increase in trading volume coincided with periods of higher price volatility, indicating increased investor participation.
A46: Overall, TCS showed a moderate positive relationship between trading volume and price movements, with higher volumes accompanying major price changes.
... A160: Overall, the analysis indicates a moderate positive relationship between trading volume and price volatility across the selected stocks.

Sheet CAPM
A1: Stock | B1: Beta | C1: Annual Market Return (Rm) | D1: Risk-Free Rate (Rf) | E1: Required Return (CAPM)
A2: RELIANCE | B2: 1.0571258 | C2: 0.0242 | D2: 0.06 | E2: =D2+B2*(C2-D2) -> 0.022154896
A3: TCS | B3: 0.82783985 | C3: 0.0242 | D3: 0.06 | E3: =D3+B3*(C3-D3) -> 0.030363334
A4: INFY | B4: 0.90306501 | C4: 0.0242 | D4: 0.06 | E4: =D4+B4*(C4-D4) -> 0.027670273
A5: HDFCBANK | B5: 1.2255984 | C5: 0.0242 | D5: 0.06 | E5: =D5+B5*(C5-D5) -> 0.016123578
A6: ICICIBANK | B6: 0.92969866 | C6: 0.0242 | D6: 0.06 | E6: =D6+B6*(C6-D6) -> 0.026716788
A7: ITC | B7: 0.64553132 | C7: 0.0242 | D7: 0.06 | E7: =D7+B7*(C7-D7) -> 0.036889979
A9: CAPM Analysis
A11: The CAPM estimates the required rate of return based on the systematic risk (Beta) of each stock.
A12: HDFCBANK has the highest Beta (1.23) and therefore is the most sensitive to market movements, resulting in the lowest required return because the market return used in this analysis is below the risk-free rate.
A13: ITC has the lowest Beta (0.65), making it the least sensitive to market fluctuations and resulting in the highest required return among the selected stocks under the given inputs.
A14: The CAPM results indicate that the required return varies according to each stock's Beta and the relationship between the market return and the risk-free rate.

Sheet Bond_Data
A1: Field | B1: Short-Term Government Security (G-Sec) | C1: Long-Term Government Security (G-Sec) | D1: Corporate NCD
A2: Bond Name | B2: 07.06 GS 2028 | C2: 06.94 GS 2036 | D2: MUTHOOT FINANCE LIMITED 8.65 NCD 12JU31 FVRSILAC
A3: Issuer | B3: Government of India | C3: Government of India | D3: Muthoot Finance Limited
A4: Last Traded Price | B4: 101.605 | C4: 100.865 | D4: 100.2425
A5: Volume Traded | B5: 165 | C5: 28155 | D5: 306.5
A6: Yield | B6: 0.060055 | C6: 0.068152 | D6: 0.08633
A7: Face Value | B7: ₹100 | C7: ₹100 | D7: ₹100
A8: Coupon Rate | B8: 0.0706 | C8: 0.0694 | D8: 0.0865
A9: High Price | B9: 101.65 | C9: 100.87 | D9: 100.2425
A10: Low Price | B10: 101.5825 | C10: 100.68 | D10: 100.2425
A11: Buy/Sell | B11: No Active Bid/Offer Orders (N/A) | C11: No Active Bid/Offer Orders (N/A) | D11: N/A (Not displayed)
A12: Trading Data | B12: Trades = 9 | C12: Trades = 3081 | D12: No. of Trades = 5

Sheet Bond_Yield_Analysis
A1: Bond Name | B1: Coupon Rate | C1: Yield (%) | D1: Last Traded Price | E1: Maturity
A2: 07.06 GS 2028 | B2: 0.0706 | C2: 0.0601 | D2: 101.605 | E2: 2028
A3: 06.94 GS 2036 | B3: 0.0694 | C3: 0.0682 | D3: 100.865 | E3: 2036
A4: MUTHOOT FINANCE LTD 8.65 NCD | B4: 0.0865 | C4: 0.0863 | D4: 100.2425 | E4: 2031
H8: Question | I8: Answer
H9: Which security has the highest coupon rate? | I9: MUTHOOT FINANCE LIMITED 8.65 NCD 12JU31 FVRSILAC (8.65%)
H10: Which security has the lowest coupon rate? | I10: 06.94 GS 2036 (6.94%)
H11: Which security has the highest Yield to Maturity (YTM)? | I11: MUTHOOT FINANCE LIMITED 8.65 NCD 12JU31 FVRSILAC (8.63%)
H12: Which security has the lowest Yield to Maturity (YTM)? | I12: 07.06 GS 2028 (6.01%)
H13: Which security has the longest remaining maturity? | I13: 06.94 GS 2036
H16: Bond Price–Yield Analysis
H18: The selected bonds exhibit different coupon rates, yields, and maturities. The Corporate NCD offers the highest coupon rate and yield, reflecting the additional credit risk compared to Government Securities. The Government Securities provide relatively lower yields due to their sovereign backing and lower default risk. The long-term Government Security has the longest maturity and is generally more sensitive to changes in interest rates than the short-term Government Security.

Sheet Summary
A1: Summary
A2: Objective
A4: The objective of this assignment was to analyze selected stocks using Modern Portfolio Theory (MPT), evaluate portfolio performance under different weighting methods, study the relationship between stock prices and trading volume, estimate the required rate of return using the Capital Asset Pricing Model (CAPM), and analyze Government Securities and Corporate Bonds based on their price, yield, and maturity characteristics.
A6: Key Findings
A7: 1. Modern Portfolio Theory
A8: Six Nifty 50 stocks were selected for analysis using two years of daily data.
A9: Mean daily returns, standard deviations, and beta values were calculated for each stock.
A10: Three portfolio construction methods were evaluated:
A11: Minimum Variance Portfolio
A12: Value-Weighted Portfolio
A13: Price-Weighted Portfolio
A14: 2. Portfolio Performance
... A33: This assignment demonstrated the practical application of portfolio management concepts, risk-return analysis, CAPM, and bond valuation using real market data. The analysis showed that different portfolio weighting methods produce different levels of risk and return, while bond yields and maturities significantly influence investment decisions. Overall, the study provided a comprehensive understanding of equity and fixed-income investment analysis.
